Workbook

Sheet PLJ01
C3: Loja 01 | U3: 2025 | X3: Açougue
U4: Janeiro | V4: ='Hist LJ01'!B20 -> 4672168.2 | X4: Venda Ano 2025 | Y4: =SUMIFS('Hist LJ01'!$N:$N,'Hist LJ01'!$P:$P,"Açougue") -> 11128757
C5: Venda 2025 | E5: Venda R$ Funcionarios | H5: Gerente | P5: Abertura da loja | U5: Fevereiro | V5: ='Hist LJ01'!C20 -> 4395175.2 | X5: Media mês | Y5: =Y4/12 -> 927396.42
C6: =V16 -> 59946140 | E6: 43000 | U6: Março | V6: ='Hist LJ01'!D20 -> 5003146.9 | X6: Venda Por QL | Y6: =Y5/H35 -> 71338.186
H7: 1 | U7: Abril | V7: ='Hist LJ01'!E20 -> 5068465.7 | X7: Meta | Y7: 75000
C8: Media 12 mêses | E8: Proposta Quant | P8: Seg a Sab | R8: Domingos | U8: Maio | V8: ='Hist LJ01'!F20 -> 5058912.5
C9: =C6/12 -> 4995511.7 | E9: =C9/E6 -> 116.17469 | H9: Subgerente | P9: 08:00 as 21:00 | R9: 08:00 as 20:00 | U9: Junho | V9: ='Hist LJ01'!G20 -> 4808087.7 | X9: Hortifrut
U10: Julho | V10: ='Hist LJ01'!H20 -> 5011604.6 | X10: Venda Ano 2025 | Y10: =SUMIFS('Hist LJ01'!$N:$N,'Hist LJ01'!$P:$P,"Hortifruti") -> 7890617.3
H11: 2 | U11: Agosto | V11: ='Hist LJ01'!I20 -> 5020870.9 | X11: Media mês | Y11: =Y10/12 -> 657551.44
U12: Setembro | V12: ='Hist LJ01'!J20 -> 4777027.7 | X12: Venda Por QL | Y12: =Y11/J35 -> 93935.92
C13: FRENTE CAIXA | E13: LOJA | H13: AÇOUGUE | J13: HORTFRUTI | L13: FRIOS | N13: PADARIA | O13: CONFEITARIA | P13: ROTISSERIA | R13: Depósito | U13: Outubro | V13: ='Hist LJ01'!K20 -> 5009122.2 | X13: Meta | Y13: 80000
C14: Encarregado | E14: Encarregado | H14: Encarregado | J14: Encarregado | L14: Encarregado | N14: Encarregado | O14: Encarregado | P14: Encarregado | R14: Encarregado | U14: Novembro | V14: ='Hist LJ01'!L20 -> 5078982.2
C15: 1 | E15: 1 | H15: 1 | J15: 1 | L15: 1 | N15: 1 | O15: 0 | P15: 0 | R15: 1 | U15: Dezenbro | V15: ='Hist LJ01'!M20 -> 6042576.6 | X15: Confeitaria
U16: Total | V16: ='Hist LJ01'!N20 -> 59946140 | X16: Venda Ano 2025 | Y16: =SUMIFS('Hist LJ01'!$N:$N,'Hist LJ01'!$P:$P,"Confeitaria") -> 1377199.1
C17: Fiscal de Caixa | E17: Repositor | F17: Limpeza | H17: Desossador | J17: Repositor | L17: Atendente | N17: Atendente | O17: Confeiteira | P17: Cozinheiro | R17: Conferente | U17: Media 12 meses | V17: =V16/12 -> 4995511.7 | X17: Media mês | Y17: =Y16/12 -> 114766.59
C18: 5 | E18: 9 | F18: 3 | H18: 2 | J18: 8 | L18: 4 | N18: 5 | O18: 2 | P18: 2 | R18: 1 | U18: Media por QL | V18: =V17/43000 -> 116.17469 | X18: Venda Por QL | Y18: =Y17/O35 -> 38255.53
X19: Meta | Y19: 26000
C20: Operador Caixa | E20: Cartazista | F20: Estacionamento | H20: Açogueiro | J20: Rep Cortes | L20: Repositor | N20: Padeiro | O20: Auxiliar | P20: Auxiliar | R20: Auxiliar
C21: 22 | E21: 1 | F21: 2 | H21: 5 | J21: 0 | L21: 2 | N21: 3 | O21: 1 | P21: 1 | R21: 3 | U21: Frios / Congelados / Laticinios / Peix | X21: Padaria
U22: Venda Ano 2025 | V22: =SUMIFS('Hist LJ01'!$N:$N,'Hist LJ01'!$P:$P,"Frios") -> 6438152.4 | X22: Venda Ano 2025 | Y22: =SUMIFS('Hist LJ01'!$N:$N,'Hist LJ01'!$P:$P,"Padaria") -> 2731772.5
C23: Empacotador | E23: Auxiliar | F23: Entregador | H23: Balconista | N23: Auxiliar | R23: Controladoria | U23: Media mês | V23: =V22/12 -> 536512.7 | X23: Media mês | Y23: =Y22/12 -> 227647.71
C24: 4 | E24: 1 | F24: 2 | H24: 5 | N24: 3 | R24: 2 | U24: Venda Por QL | V24: =V23/L35 -> 107302.54 | X24: Venda Por QL | Y24: =Y23/N35 -> 18970.643
U25: Meta | V25: 80000 | X25: Meta | Y25: 16000
E26: Aprendiz | F26: E-Commerce | R26: Prevenção
E27: 6 | F27: 0 | R27: 1 | U27: Loja Total | X27: Rotisseria
U28: Venda Ano 2025 | V28: =SUMIFS('Hist LJ01'!$N:$N,'Hist LJ01'!$P:$P,"Loja") -> 29221061 | X28: Venda Ano 2025 | Y28: =SUMIFS('Hist LJ01'!$N:$N,'Hist LJ01'!$P:$P,"Rotisseria") -> 1158581
E29: Gestão Pessoas | F29: Cor. Bancário | U29: Media mês | V29: =V28/12 -> 2435088.4 | X29: Media mês | Y29: =Y28/12 -> 96548.417
E30: 1 | F30: 0 | U30: Venda Por QL | V30: =V29/(E35+R35) -> 65813.201 | X30: Venda Por QL | Y30: =Y29/P35 -> 32182.806
C31: Orçado Acima | U31: Meta | V31: 160000 | X31: Meta | Y31: 25000
C32: Total | E32: Total | H32: Total | J32: Total | L32: Total | N32: PADARIA | O32: CONFEITARIA | P32: ROTISSERIA | R32: Total
C33: =C30+C27+C24+C21+C18+C15 -> 32 | E33: =E30+E27+E24+E21+E18+E15+F18+F21+F24+F27+F30 -> 26 | H33: =H30+H27+H24+H21+H18+H15 -> 13 | J33: =J30+J27+J24+J21+J18+J15 -> 9 | L33: =L30+L27+L24+L21+L18+L15 -> 7 | N33: =N30+N27+N24+N21+N18+N15 -> 12 | O33: =O30+O27+O24+O21+O18+O15 -> 3 | P33: =P30+P27+P24+P21+P18+P15 -> 3 | R33: =R15+R18+R21+R24+R27 -> 8 | U33: Frente Caixa | X33: Prod Alimentos
C34: Total | E34: Total | H34: Total | J34: Total | L34: Total | N34: PADARIA | O34: CONFEITARIA | P34: ROTISSERIA | R34: Total | U34: Venda Ano 2025 | V34: =SUMIFS('Hist LJ01'!$N:$N,'Hist LJ01'!$P:$P,"Loja") -> 29221061 | X34: Venda Ano 2025 | Y34: =Y28+Y22+Y16 -> 5267552.6
C35: 29 | E35: 31 | H35: 13 | J35: 7 | L35: 5 | N35: 12 | O35: 3 | P35: 3 | R35: 6 | U35: Media mês | V35: =V34/12 -> 2435088.4 | X35: Media mês | Y35: =Y34/12 -> 438962.72
C36: Real Fev/26 | U36: Venda Por QL | V36: =V35/C35 -> 83968.567 | X36: Venda Por QL | Y36: =Y35/SUM(N35:P35) -> 24386.818
J37: Total | L37: Real | N37: Diferença | U37: Meta | V37: 138000 | X37: Meta | Y37: 21000
J39: =SUM(C33:R33)+H11+H7 -> 116 | L39: =SUM(A35:S35) -> 109 | N39: =L39-J39 -> -7

Sheet PLJ02
C3: Loja 02 | U3: 2025 | X3: Açougue
U4: Janeiro | V4: ='Hist LJ02'!B20 -> 2839277.9 | X4: Venda Ano 2025 | Y4: =SUMIFS('Hist LJ02'!$N:$N,'Hist LJ02'!$P:$P,"Açougue") -> 5818951.9
C5: Venda 2025 | E5: Venda R$ Funcionarios | H5: Gerente | P5: Abertura da loja | U5: Fevereiro | V5: ='Hist LJ02'!C20 -> 2702365.5 | X5: Media mês | Y5: =Y4/12 -> 484912.66
C6: =V16 -> 35741919 | E6: 43000 | U6: Março | V6: ='Hist LJ02'!D20 -> 3066044.8 | X6: Venda Por QL | Y6: =Y5/H35 -> 80818.777
H7: 1 | U7: Abril | V7: ='Hist LJ02'!E20 -> 3202572.4 | X7: Meta | Y7: 75000
C8: Media 12 mêses | E8: Proposta Quant | P8: Seg a Sab | R8: Domingos | U8: Maio | V8: ='Hist LJ02'!F20 -> 3090885
C9: =C6/12 -> 2978493.2 | E9: =C9/E6 -> 69.267285 | H9: Subgerente | P9: 08:00 as 21:00 | R9: 08:00 as 20:00 | U9: Junho | V9: ='Hist LJ02'!G20 -> 2939070.2 | X9: Hortifrut
U10: Julho | V10: ='Hist LJ02'!H20 -> 3107973 | X10: Venda Ano 2025 | Y10: =SUMIFS('Hist LJ02'!$N:$N,'Hist LJ02'!$P:$P,"Hortifruti") -> 5368221.2
H11: 1 | U11: Agosto | V11: ='Hist LJ02'!I20 -> 3033801.9 | X11: Media mês | Y11: =Y10/12 -> 447351.77
U12: Setembro | V12: ='Hist LJ02'!J20 -> 2801352.7 | X12: Venda Por QL | Y12: =Y11/J35 -> 89470.353
C13: FRENTE CAIXA | E13: LOJA | H13: AÇOUGUE | J13: HORTFRUTI | L13: FRIOS | N13: PADARIA | O13: CONFEITARIA | P13: ROTISSERIA | R13: Depósito | U13: Outubro | V13: ='Hist LJ02'!K20 -> 2892700.9 | X13: Meta | Y13: 80000
C14: Encarregado | E14: Encarregado | H14: Encarregado | J14: Encarregado | L14: Encarregado | N14: Encarregado | O14: Encarregado | P14: Encarregado | R14: Encarregado | U14: Novembro | V14: ='Hist LJ02'!L20 -> 2797129.7
C15: 1 | E15: 1 | H15: 1 | J15: 1 | L15: 1 | N15: 1 | O15: 0 | P15: 0 | R15: 1 | U15: Dezenbro | V15: ='Hist LJ02'!M20 -> 3268745 | X15: Confeitaria
U16: Total | V16: ='Hist LJ02'!N20 -> 35741919 | X16: Venda Ano 2025 | Y16: =SUMIFS('Hist LJ02'!$N:$N,'Hist LJ02'!$P:$P,"Confeitaria") -> 576209.63
C17: Fiscal de Caixa | E17: Repositor | F17: Limpeza | H17: Desossador | J17: Repositor | L17: Atendente | N17: Atendente | O17: Confeiteira | P17: Cozinheiro | R17: Conferente | U17: Media 12 meses | V17: =V16/12 -> 2978493.2 | X17: Media mês | Y17: =Y16/12 -> 48017.469
C18: 3 | E18: 5 | F18: 2 | H18: 1 | J18: 4 | L18: 2 | N18: 3 | O18: 1 | P18: 1 | R18: 1 | U18: Media por QL | V18: =V17/43000 -> 69.267285 | X18: Venda Por QL | Y18: =Y17/O35 -> 24008.735
X19: Meta | Y19: 26000
C20: Operador Caixa | E20: Cartazista | F20: Estacionamento | H20: Açogueiro | J20: Rep Cortes | L20: Repositor | N20: Padeiro | O20: Auxiliar | P20: Auxiliar | R20: Auxiliar
C21: 11 | E21: 1 | F21: 1 | H21: 3 | J21: 1 | L21: 1 | N21: 2 | O21: 1 | P21: 0 | R21: 1 | U21: Frios / Congelados / Laticinios / Peix | X21: Padaria
U22: Venda Ano 2025 | V22: =SUMIFS('Hist LJ02'!$N:$N,'Hist LJ02'!$P:$P,"Frios") -> 4618335.4 | X22: Venda Ano 2025 | Y22: =SUMIFS('Hist LJ02'!$N:$N,'Hist LJ02'!$P:$P,"Padaria") -> 1697669
C23: Empacotador | E23: Auxiliar | F23: Entregador | H23: Balconista | N23: Auxiliar | R23: Controladoria | U23: Media mês | V23: =V22/12 -> 384861.29 | X23: Media mês | Y23: =Y22/12 -> 141472.42
C24: 1 | E24: 0 | F24: 1 | H24: 2 | N24: 1 | R24: 1 | U24: Venda Por QL | V24: =V23/L35 -> 96215.321 | X24: Venda Por QL | Y24: =Y23/N35 -> 15719.157
U25: Meta | V25: 80000 | X25: Meta | Y25: 16000
E26: Aprendiz | F26: E-Commerce | R26: Prevenção
E27: 7 | F27: 1 | R27: 1 | U27: Loja Total | X27: Rotisseria
U28: Venda Ano 2025 | V28: =SUMIFS('Hist LJ02'!$N:$N,'Hist LJ02'!$P:$P,"Loja") -> 17272292 | X28: Venda Ano 2025 | Y28: =SUMIFS('Hist LJ02'!$N:$N,'Hist LJ02'!$P:$P,"Rotisseria") -> 390239.68
E29: Gestão Pessoas | F29: Cor. Bancário | U29: Media mês | V29: =V28/12 -> 1439357.7 | X29: Media mês | Y29: =Y28/12 -> 32519.973
E30: 0 | F30: 0 | U30: Venda Por QL | V30: =V29/(E35+R35) -> 59973.236 | X30: Venda Por QL | Y30: =Y29/P35 -> 32519.973
C31: Orçado Acima | U31: Meta | V31: 160000 | X31: Meta | Y31: 25000
C32: Total | E32: Total | H32: Total | J32: Total | L32: Total | N32: PADARIA | O32: CONFEITARIA | P32: ROTISSERIA | R32: Total
C33: =C30+C27+C24+C21+C18+C15 -> 16 | E33: =E30+E27+E24+E21+E18+E15+F18+F21+F24+F27+F30 -> 19 | H33: =H30+H27+H24+H21+H18+H15 -> 7 | J33: =J30+J27+J24+J21+J18+J15 -> 6 | L33: =L30+L27+L24+L21+L18+L15 -> 4 | N33: =N30+N27+N24+N21+N18+N15 -> 7 | O33: =O30+O27+O24+O21+O18+O15 -> 2 | P33: =P30+P27+P24+P21+P18+P15 -> 1 | R33: =R15+R18+R21+R24+R27+R30 -> 5 | U33: Frente Caixa | X33: Prod Alimentos
C34: Total | E34: Total | H34: Total | J34: Total | L34: Total | N34: PADARIA | O34: CONFEITARIA | P34: ROTISSERIA | R34: Total | U34: Venda Ano 2025 | V34: =SUMIFS('Hist LJ02'!$N:$N,'Hist LJ02'!$P:$P,"Loja") -> 17272292 | X34: Venda Ano 2025 | Y34: =Y28+Y22+Y16 -> 2664118.3
C35: 20 | E35: 22 | H35: 6 | J35: 5 | L35: 4 | N35: 9 | O35: 2 | P35: 1 | R35: 2 | U35: Media mês | V35: =V34/12 -> 1439357.7 | X35: Media mês | Y35: =Y34/12 -> 222009.86
C36: Real Fev/26 | U36: Venda Por QL | V36: =V35/C35 -> 71967.884 | X36: Venda Por QL | Y36: =Y35/SUM(N35:P35) -> 18500.822
J37: Total | L37: Real | N37: Diferença | U37: Meta | V37: 138000 | X37: Meta | Y37: 21000
J39: =SUM(C33:R33)+H11+H7 -> 69 | L39: =SUM(A35:S35) -> 71 | N39: =L39-J39 -> 2

Sheet PLJ03
C3: Loja 03 | U3: 2025 | X3: Açougue
U4: Janeiro | V4: ='Hist LJ03'!B20 -> 2785692.2 | X4: Venda Ano 2025 | Y4: =SUMIFS('Hist LJ03'!$N:$N,'Hist LJ03'!$P:$P,"Açougue") -> 6362337.4
C5: Venda 2025 | E5: Venda R$ Funcionarios | H5: Gerente | P5: Abertura da loja | U5: Fevereiro | V5: ='Hist LJ03'!C20 -> 2655535.3 | X5: Media mês | Y5: =Y4/12 -> 530194.78
C6: =V16 -> 35305398 | E6: 43000 | U6: Março | V6: ='Hist LJ03'!D20 -> 3046525.3 | X6: Venda Por QL | Y6: =Y5/H35 -> 75742.112
H7: 1 | U7: Abril | V7: ='Hist LJ03'!E20 -> 2909466.9 | X7: Meta | Y7: 75000
C8: Media 12 mêses | E8: Proposta Quant | P8: Seg a Sab | R8: Domingos | U8: Maio | V8: ='Hist LJ03'!F20 -> 3015715.3
C9: =C6/12 -> 2942116.5 | E9: =C9/E6 -> 68.421314 | H9: Subgerente | P9: 08:00 as 21:00 | R9: 08:00 as 20:00 | U9: Junho | V9: ='Hist LJ03'!G20 -> 2860012.5 | X9: Hortifrut
U10: Julho | V10: ='Hist LJ03'!H20 -> 2892461.7 | X10: Venda Ano 2025 | Y10: =SUMIFS('Hist LJ03'!$N:$N,'Hist LJ03'!$P:$P,"Hortifruti") -> 4209707.6
H11: 1 | U11: Agosto | V11: ='Hist LJ03'!I20 -> 2995538 | X11: Media mês | Y11: =Y10/12 -> 350808.97
U12: Setembro | V12: ='Hist LJ03'!J20 -> 2852898.7 | X12: Venda Por QL | Y12: =Y11/J35 -> 70161.793
C13: FRENTE CAIXA | E13: LOJA | H13: AÇOUGUE | J13: HORTFRUTI | L13: FRIOS | N13: PADARIA | O13: CONFEITARIA | P13: ROTISSERIA | R13: Depósito | U13: Outubro | V13: ='Hist LJ03'!K20 -> 2900315.7 | X13: Meta | Y13: 80000
C14: Encarregado | E14: Encarregado | H14: Encarregado | J14: Encarregado | L14: Encarregado | N14: Encarregado | O14: Encarregado | P14: Encarregado | R14: Encarregado | U14: Novembro | V14: ='Hist LJ03'!L20 -> 2981089.7
C15: 1 | E15: 1 | H15: 1 | J15: 1 | L15: 1 | N15: 1 | O15: 0 | P15: 0 | R15: 1 | U15: Dezenbro | V15: ='Hist LJ03'!M20 -> 3410146.5 | X15: Confeitaria
U16: Total | V16: ='Hist LJ03'!N20 -> 35305398 | X16: Venda Ano 2025 | Y16: =SUMIFS('Hist LJ03'!$N:$N,'Hist LJ03'!$P:$P,"Confeitaria") -> 410726.58
C17: Fiscal de Caixa | E17: Repositor | F17: Limpeza | H17: Desossador | J17: Repositor | L17: Atendente | N17: Atendente | O17: Confeiteira | P17: Forneiro | R17: Conferente | U17: Media 12 meses | V17: =V16/12 -> 2942116.5 | X17: Media mês | Y17: =Y16/12 -> 34227.215
C18: 3 | E18: 6 | F18: 2 | H18: 1 | J18: 3 | L18: 2 | N18: 1 | O18: 1 | P18: 1 | R18: 1 | U18: Media por QL | V18: =V17/43000 -> 68.421314 | X18: Venda Por QL | Y18: =Y17/O35 -> 17113.607
X19: Meta | Y19: 26000
C20: Operador Caixa | E20: Cartazista | F20: Estacionamento | H20: Açogueiro | J20: Rep Cortes | L20: Repositor | N20: Padeiro | O20: Auxiliar | P20: Auxiliar | R20: Auxiliar
C21: 19 | E21: 1 | F21: 0 | H21: 4 | J21: 1 | L21: 1 | N21: 0 | O21: 1 | P21: 0 | R21: 1 | U21: Frios / Congelados / Laticinios / Peix | X21: Padaria
U22: Venda Ano 2025 | V22: =SUMIFS('Hist LJ03'!$N:$N,'Hist LJ03'!$P:$P,"Frios") -> 3697699.6 | X22: Venda Ano 2025 | Y22: =SUMIFS('Hist LJ03'!$N:$N,'Hist LJ03'!$P:$P,"Padaria") -> 815953.92
C23: Empacotador | E23: Auxiliar | F23: Entregador | H23: Balconista | N23: Auxiliar | R23: Controladoria | U23: Media mês | V23: =V22/12 -> 308141.63 | X23: Media mês | Y23: =Y22/12 -> 67996.16
C24: 1 | E24: 0 | F24: 1 | H24: 2 | N24: 1 | R24: 1 | U24: Venda Por QL | V24: =V23/L35 -> 102713.88 | X24: Venda Por QL | Y24: =Y23/N35 -> 16999.04
U25: Meta | V25: 80000 | X25: Meta | Y25: 16000
E26: Aprendiz | F26: E-Commerce | R26: Prevenção
E27: 2 | F27: 0 | R27: 1 | U27: Loja Total | X27: Rotisseria
U28: Venda Ano 2025 | V28: =SUMIFS('Hist LJ03'!$N:$N,'Hist LJ03'!$P:$P,"Loja") -> 19806359 | X28: Venda Ano 2025 | Y28: =SUMIFS('Hist LJ03'!$N:$N,'Hist LJ03'!$P:$P,"Rotisseria") -> 2613.68
E29: Gestão Pessoas | F29: Cor. Bancário | U29: Media mês | V29: =V28/12 -> 1650529.9 | X29: Media mês | Y29: =Y28/12 -> 217.80667
E30: 0 | F30: 1 | U30: Venda Por QL | V30: =V29/(E35+R35) -> 97089.996 | X30: Venda Por QL | Y30: =IFERROR(Y29/P35,0) -> 0
C31: Orçado Acima | U31: Meta | V31: 160000 | X31: Meta | Y31: 25000
C32: Total | E32: Total | H32: Total | J32: Total | L32: Total | N32: PADARIA | O32: CONFEITARIA | P32: ROTISSERIA | R32: Total
C33: =C30+C27+C24+C21+C18+C15 -> 24 | E33: =E30+E27+E24+E21+E18+E15+F30+F27+F24+F21+F18 -> 14 | H33: =H30+H27+H24+H21+H18+H15 -> 8 | J33: =J30+J27+J24+J21+J18+J15 -> 5 | L33: =L30+L27+L24+L21+L18+L15 -> 4 | N33: =N30+N27+N24+N21+N18+N15 -> 3 | O33: =O30+O27+O24+O21+O18+O15 -> 2 | P33: =P30+P27+P24+P21+P18+P15 -> 1 | R33: =R27+R24+R21+R18+R15 -> 5 | U33: Frente Caixa | X33: Prod Alimentos
C34: Total | E34: Total | H34: Total | J34: Total | L34: Total | N34: PADARIA | O34: CONFEITARIA | P34: ROTISSERIA | R34: Total | U34: Venda Ano 2025 | V34: =SUMIFS('Hist LJ03'!$N:$N,'Hist LJ03'!$P:$P,"Loja") -> 19806359 | X34: Venda Ano 2025 | Y34: =Y28+Y22+Y16 -> 1229294.2
C35: 22 | E35: 15 | H35: 7 | J35: 5 | L35: 3 | N35: 4 | O35: 2 | P35: =P33/SUM($N$33:$P$33)*$O$36 -> 0 | R35: 2 | U35: Media mês | V35: =V34/12 -> 1650529.9 | X35: Media mês | Y35: =Y34/12 -> 102441.18
C36: Real Fev/26 | U36: Venda Por QL | V36: =V35/C35 -> 75024.088 | X36: Venda Por QL | Y36: =Y35/SUM(N35:P35) -> 17073.53
J37: Total | L37: Real | N37: Diferença | U37: Meta | V37: 138000 | X37: Meta | Y37: 21000
J39: =SUM(C33:R33)+H11+H7 -> 68 | L39: =SUM(C35:R35) -> 60 | N39: =L39-J39 -> -8

Sheet PLJ04
C3: Loja 04 | U3: 2025 | X3: Açougue
U4: Janeiro | V4: ='Hist LJ04'!B20 -> 2255242.1 | X4: Venda Ano 2025 | Y4: =SUMIFS('Hist LJ04'!$N:$N,'Hist LJ04'!$P:$P,"Açougue") -> 5249804.4
C5: Venda 2025 | E5: Venda R$ Funcionarios | H5: Gerente | P5: Abertura da loja | U5: Fevereiro | V5: ='Hist LJ04'!C20 -> 2123168.4 | X5: Media mês | Y5: =Y4/12 -> 437483.7
C6: =V16 -> 28365264 | E6: 43000 | U6: Março | V6: ='Hist LJ04'!D20 -> 2418000.3 | X6: Venda Por QL | Y6: =Y5/H35 -> 72913.95
H7: 1 | U7: Abril | V7: ='Hist LJ04'!E20 -> 2311418.4 | X7: Meta | Y7: 75000
C8: Media 12 mêses | E8: Proposta Quant | P8: Seg a Sab | R8: Domingos | U8: Maio | V8: ='Hist LJ04'!F20 -> 2406334.2
C9: =C6/12 -> 2363772 | E9: =C9/E6 -> 54.971441 | H9: Subgerente | P9: 08:00 as 21:00 | R9: 08:00 as 20:00 | U9: Junho | V9: ='Hist LJ04'!G20 -> 2302464.1 | X9: Hortifrut
U10: Julho | V10: ='Hist LJ04'!H20 -> 2373204.1 | X10: Venda Ano 2025 | Y10: =SUMIFS('Hist LJ04'!$N:$N,'Hist LJ04'!$P:$P,"Hortifruti") -> 4006181.3
H11: 1 | U11: Agosto | V11: ='Hist LJ04'!I20 -> 2392137.9 | X11: Media mês | Y11: =Y10/12 -> 333848.45
U12: Setembro | V12: ='Hist LJ04'!J20 -> 2319689.5 | X12: Venda Por QL | Y12: =Y11/J35 -> 66769.689
C13: FRENTE CAIXA | E13: LOJA | H13: AÇOUGUE | J13: HORTFRUTI | L13: FRIOS | N13: PADARIA | O13: CONFEITARIA | P13: ROTISSERIA | R13: Depósito | U13: Outubro | V13: ='Hist LJ04'!K20 -> 2358183 | X13: Meta | Y13: 80000
C14: Encarregado | E14: Encarregado | H14: Encarregado | J14: Encarregado | L14: Encarregado | N14: Encarregado | O14: Encarregado | P14: Encarregado | R14: Encarregado | U14: Novembro | V14: ='Hist LJ04'!L20 -> 2405167.4
C15: 1 | E15: 1 | H15: 1 | J15: 1 | L15: 0 | N15: 0 | O15: 0 | P15: 0 | R15: 0 | U15: Dezenbro | V15: ='Hist LJ04'!M20 -> 2700254.2 | X15: Confeitaria
U16: Total | V16: ='Hist LJ04'!N20 -> 28365264 | X16: Venda Ano 2025 | Y16: =SUMIFS('Hist LJ04'!$N:$N,'Hist LJ04'!$P:$P,"Confeitaria") -> 435801.47
C17: Fiscal de Caixa | E17: Repositor | F17: Limpeza | H17: Desossador | J17: Repositor | L17: Atendente | N17: Atendente | O17: Confeiteira | P17: Cozinheiro | R17: Conferente | U17: Media 12 meses | V17: =V16/12 -> 2363772 | X17: Media mês | Y17: =Y16/12 -> 36316.789
C18: 3 | E18: 4 | F18: 2 | H18: 1 | J18: 2 | L18: 0 | N18: 3 | O18: 1 | P18: 0 | R18: 1 | U18: Media por QL | V18: =V17/43000 -> 54.971441 | X18: Venda Por QL | Y18: =Y17/O35 -> 18158.395
X19: Meta | Y19: 26000
C20: Operador Caixa | E20: Cartazista | F20: Estacionamento | H20: Açogueiro | J20: Rep Cortes | L20: Repositor | N20: Padeiro | O20: Auxiliar | P20: Auxiliar | R20: Auxiliar
C21: 12 | E21: 1 | F21: 1 | H21: 2 | J21: 1 | L21: 1 | N21: 1 | O21: 1 | P21: 0 | R21: 1 | U21: Frios / Congelados / Laticinios / Peix | X21: Padaria
U22: Venda Ano 2025 | V22: =SUMIFS('Hist LJ04'!$N:$N,'Hist LJ04'!$P:$P,"Frios") -> 3364237.4 | X22: Venda Ano 2025 | Y22: =SUMIFS('Hist LJ04'!$N:$N,'Hist LJ04'!$P:$P,"Padaria") -> 988989.5
C23: Empacotador | E23: Auxiliar | F23: Entregador | H23: Balconista | N23: Auxiliar | R23: Controladoria | U23: Media mês | V23: =V22/12 -> 280353.12 | X23: Media mês | Y23: =Y22/12 -> 82415.792
C24: 1 | E24: 0 | F24: 1 | H24: 2 | N24: 1 | R24: 1 | U24: Venda Por QL | V24: =V23/L35 -> 280353.12 | X24: Venda Por QL | Y24: =Y23/N35 -> 13735.965
U25: Meta | V25: 80000 | X25: Meta | Y25: 16000
E26: Aprendiz | F26: E-Commerce | R26: Prevenção
E27: 4 | F27: 0 | R27: 1 | U27: Loja Total | X27: Rotisseria
U28: Venda Ano 2025 | V28: =SUMIFS('Hist LJ04'!$N:$N,'Hist LJ04'!$P:$P,"Loja") -> 14295425 | X28: Venda Ano 2025 | Y28: =SUMIFS('Hist LJ04'!$N:$N,'Hist LJ04'!$P:$P,"Rotisseria") -> 24824.36
E29: Gestão Pessoas | F29: Cor. Bancário | U29: Media mês | V29: =V28/12 -> 1191285.4 | X29: Media mês | Y29: =Y28/12 -> 2068.6967
E30: 0 | F30: 0 | U30: Venda Por QL | V30: =V29/(E35+R35) -> 70075.613 | X30: Venda Por QL | Y30: =IFERROR(Y29/P35,0) -> 0
C31: Orçado Acima | U31: Meta | V31: 160000 | X31: Meta | Y31: 25000
C32: Total | E32: Total | H32: Total | J32: Total | L32: Total | N32: PADARIA | O32: CONFEITARIA | P32: ROTISSERIA | R32: Total
C33: =C30+C27+C24+C21+C18+C15 -> 17 | E33: =E30+E27+E24+E21+E18+E15+F30+F27+F24+F21+F18 -> 14 | H33: =H30+H27+H24+H21+H18+H15 -> 6 | J33: =J30+J27+J24+J21+J18+J15 -> 4 | L33: =L30+L27+L24+L21+L18+L15 -> 1 | N33: =N30+N27+N24+N21+N18+N15 -> 5 | O33: =O30+O27+O24+O21+O18+O15 -> 2 | P33: =P30+P27+P24+P21+P18+P15 -> 0 | R33: =R30+R27+R24+R21+R18+R15 -> 4 | U33: Frente Caixa | X33: Prod Alimentos
C34: Total | E34: Total | H34: Total | J34: Total | L34: Total | N34: PADARIA | O34: CONFEITARIA | P34: ROTISSERIA | R34: Total | U34: Venda Ano 2025 | V34: =SUMIFS('Hist LJ04'!$N:$N,'Hist LJ04'!$P:$P,"Loja") -> 14295425 | X34: Venda Ano 2025 | Y34: =Y28+Y22+Y16 -> 1449615.3
C35: 14 | E35: 14 | H35: 6 | J35: 5 | L35: 1 | N35: 6 | O35: 2 | P35: =P33/SUM($N$33:$P$33)*$O$36 -> 0 | R35: 3 | U35: Media mês | V35: =V34/12 -> 1191285.4 | X35: Media mês | Y35: =Y34/12 -> 120801.28
C36: Real Fev/26 | U36: Venda Por QL | V36: =V35/C35 -> 85091.816 | X36: Venda Por QL | Y36: =Y35/SUM(N35:P35) -> 15100.16
J37: Total | L37: Real | N37: Diferença | U37: Meta | V37: 138000 | X37: Meta | Y37: 21000
J39: =SUM(C33:R33)+H11+H7 -> 55 | L39: =SUM(C35:R35) -> 51 | N39: =L39-J39 -> -4

Sheet PLJ05
C3: Loja 05 | U3: 2025 | X3: Açougue
U4: Janeiro | V4: ='Hist LJ05'!B20 -> 3181874.2 | X4: Venda Ano 2025 | Y4: =SUMIFS('Hist LJ05'!$N:$N,'Hist LJ05'!$P:$P,"Açougue") -> 9071357.5
C5: Venda 2025 | E5: Venda R$ Funcionarios | H5: Gerente | P5: Abertura da loja | U5: Fevereiro | V5: ='Hist LJ05'!C20 -> 3138878.8 | X5: Media mês | Y5: =Y4/12 -> 755946.46
C6: =V16 -> 42055414 | E6: 43000 | U6: Março | V6: ='Hist LJ05'!D20 -> 3437306.3 | X6: Venda Por QL | Y6: =Y5/H35 -> 94493.307
H7: 1 | U7: Abril | V7: ='Hist LJ05'!E20 -> 3626851.4 | X7: Meta | Y7: 75000
C8: Media 12 mêses | E8: Proposta Quant | P8: Seg a Sab | R8: Domingos | U8: Maio | V8: ='Hist LJ05'!F20 -> 3511361.3
C9: =C6/12 -> 3504617.8 | E9: =C9/E6 -> 81.50274 | H9: Subgerente | P9: 08:00 as 21:00 | R9: 08:00 as 20:00 | U9: Junho | V9: ='Hist LJ05'!G20 -> 3390641.6 | X9: Hortifrut
U10: Julho | V10: ='Hist LJ05'!H20 -> 3635736 | X10: Venda Ano 2025 | Y10: =SUMIFS('Hist LJ05'!$N:$N,'Hist LJ05'!$P:$P,"Hortifruti") -> 5529932.1
H11: 1 | U11: Agosto | V11: ='Hist LJ05'!I20 -> 3635916.8 | X11: Media mês | Y11: =Y10/12 -> 460827.68
U12: Setembro | V12: ='Hist LJ05'!J20 -> 3451916.6 | X12: Venda Por QL | Y12: =Y11/J35 -> 230413.84
C13: FRENTE CAIXA | E13: LOJA | H13: AÇOUGUE | J13: HORTFRUTI | L13: FRIOS | N13: PADARIA | O13: CONFEITARIA | P13: ROTISSERIA | R13: Depósito | U13: Outubro | V13: ='Hist LJ05'!K20 -> 3491968.4 | X13: Meta | Y13: 80000
C14: Encarregado | E14: Encarregado | H14: Encarregado | J14: Encarregado | L14: Encarregado | N14: Encarregado | O14: Encarregado | P14: Encarregado | R14: Encarregado | U14: Novembro | V14: ='Hist LJ05'!L20 -> 3548148.3
C15: 1 | E15: 1 | H15: 1 | J15: 1 | L15: 1 | N15: 1 | O15: 0 | P15: 0 | R15: 1 | U15: Dezenbro | V15: ='Hist LJ05'!M20 -> 4004814.2 | X15: Confeitaria
U16: Total | V16: ='Hist LJ05'!N20 -> 42055414 | X16: Venda Ano 2025 | Y16: =SUMIFS('Hist LJ05'!$N:$N,'Hist LJ05'!$P:$P,"Confeitaria") -> 530367.37
C17: Fiscal de Caixa | E17: Repositor | F17: Limpeza | H17: Desossador | J17: Repositor | L17: Atendente | N17: Atendente | O17: Confeiteira | P17: Cozinheiro | R17: Conferente | U17: Media 12 meses | V17: =V16/12 -> 3504617.8 | X17: Media mês | Y17: =Y16/12 -> 44197.281
C18: 4 | E18: 6 | F18: 2 | H18: 2 | J18: 4 | L18: 2 | N18: 5 | O18: 1 | P18: 0 | R18: 1 | U18: Media por QL | V18: =V17/43000 -> 81.50274 | X18: Venda Por QL | Y18: =Y17/O35 -> 22098.64
X19: Meta | Y19: 26000
C20: Operador Caixa | E20: Cartazista | F20: Estacionamento | H20: Açogueiro | J20: Rep Cortes | L20: Repositor | N20: Padeiro | O20: Auxiliar | P20: Auxiliar | R20: Auxiliar
C21: 18 | E21: 1 | F21: 1 | H21: 4 | J21: 1 | L21: 2 | N21: 2 | O21: 1 | P21: 0 | R21: 1 | U21: Frios / Congelados / Laticinios / Peix | X21: Padaria
U22: Venda Ano 2025 | V22: =SUMIFS('Hist LJ05'!$N:$N,'Hist LJ05'!$P:$P,"Frios") -> 5330681 | X22: Venda Ano 2025 | Y22: =SUMIFS('Hist LJ05'!$N:$N,'Hist LJ05'!$P:$P,"Padaria") -> 1785382.5
C23: Empacotador | E23: Auxiliar | F23: Entregador | H23: Balconista | N23: Auxiliar | R23: Controladoria | U23: Media mês | V23: =V22/12 -> 444223.41 | X23: Media mês | Y23: =Y22/12 -> 148781.87
C24: 2 | E24: 0 | F24: 1 | H24: 3 | N24: 2 | R24: 2 | U24: Venda Por QL | V24: =V23/L35 -> 111055.85 | X24: Venda Por QL | Y24: =Y23/N35 -> 14878.187
U25: Meta | V25: 80000 | X25: Meta | Y25: 16000
E26: Aprendiz | F26: E-Commerce | R26: Prevenção
E27: 4 | F27: 0 | R27: 1 | U27: Loja Total | X27: Rotisseria
U28: Venda Ano 2025 | V28: =SUMIFS('Hist LJ05'!$N:$N,'Hist LJ05'!$P:$P,"Loja") -> 19802402 | X28: Venda Ano 2025 | Y28: =SUMIFS('Hist LJ05'!$N:$N,'Hist LJ05'!$P:$P,"Rotisseria") -> 5290.95
E29: Gestão Pessoas | F29: Cor. Bancário | U29: Media mês | V29: =V28/12 -> 1650200.2 | X29: Media mês | Y29: =Y28/12 -> 440.9125
E30: 0 | F30: 0 | U30: Venda Por QL | V30: =V29/(E35+R35) -> 61118.526 | X30: Venda Por QL | Y30: =IFERROR(Y29/P35,0) -> 0
C31: Orçado Acima | U31: Meta | V31: 160000 | X31: Meta | Y31: 25000
C32: Total | E32: Total | H32: Total | J32: Total | L32: Total | N32: PADARIA | O32: CONFEITARIA | P32: ROTISSERIA | R32: Total
C33: =C30+C27+C24+C21+C18+C15 -> 25 | E33: =E30+E27+E24+E21+E18+E15+F30+F27+F24+F21+F18 -> 16 | H33: =H30+H27+H24+H21+H18+H15 -> 10 | J33: =J30+J27+J24+J21+J18+J15 -> 6 | L33: =L30+L27+L24+L21+L18+L15 -> 5 | N33: =N30+N27+N24+N21+N18+N15 -> 10 | O33: =O30+O27+O24+O21+O18+O15 -> 2 | P33: =P30+P27+P24+P21+P18+P15 -> 0 | R33: =R30+R27+R24+R21+R18+R15 -> 6 | U33: Frente Caixa | X33: Prod Alimentos
C34: Total | E34: Total | H34: Total | J34: Total | L34: Total | N34: PADARIA | O34: CONFEITARIA | P34: ROTISSERIA | R34: Total | U34: Venda Ano 2025 | V34: =SUMIFS('Hist LJ05'!$N:$N,'Hist LJ05'!$P:$P,"Loja") -> 19802402 | X34: Venda Ano 2025 | Y34: =Y28+Y22+Y16 -> 2321040.8
C35: 19 | E35: 22 | H35: 8 | J35: 2 | L35: 4 | N35: 10 | O35: 2 | P35: =P33/SUM($N$33:$P$33)*$O$36 -> 0 | R35: 5 | U35: Media mês | V35: =V34/12 -> 1650200.2 | X35: Media mês | Y35: =Y34/12 -> 193420.07
C36: Real Fev/26 | U36: Venda Por QL | V36: =V35/C35 -> 86852.642 | X36: Venda Por QL | Y36: =Y35/SUM(N35:P35) -> 16118.339
J37: Total | L37: Real | N37: Diferença | U37: Meta | V37: 138000 | X37: Meta | Y37: 21000
J39: =SUM(C33:R33)+H11+H7 -> 82 | L39: =SUM(A35:S35) -> 72 | N39: =L39-J39 -> -10

Sheet PLJ06
C3: Loja 06 | U3: 2025 | X3: Açougue
U4: Janeiro | V4: ='Hist LJ06'!B20 -> 3688089.7 | X4: Venda Ano 2025 | Y4: =SUMIFS('Hist LJ06'!$N:$N,'Hist LJ06'!$P:$P,"Açougue") -> 9739563.2
C5: Venda 2025 | E5: Venda R$ Funcionarios | H5: Gerente | P5: Abertura da loja | U5: Fevereiro | V5: ='Hist LJ06'!C20 -> 3750186.4 | X5: Media mês | Y5: =Y4/12 -> 811630.26
C6: =V16 -> 49244758 | E6: 43000 | U6: Março | V6: ='Hist LJ06'!D20 -> 4120868.4 | X6: Venda Por QL | Y6: =Y5/H35 -> 90181.14
H7: 1 | U7: Abril | V7: ='Hist LJ06'!E20 -> 4257513.6 | X7: Meta | Y7: 75000
C8: Media 12 mêses | E8: Proposta Quant | P8: Seg a Sab | R8: Domingos | U8: Maio | V8: ='Hist LJ06'!F20 -> 4148699.6
C9: =C6/12 -> 4103729.8 | E9: =C9/E6 -> 95.435578 | H9: Subgerente | P9: 08:00 as 21:00 | R9: 08:00 as 20:00 | U9: Junho | V9: ='Hist LJ06'!G20 -> 3975894.7 | X9: Hortifrut
U10: Julho | V10: ='Hist LJ06'!H20 -> 4210990.4 | X10: Venda Ano 2025 | Y10: =SUMIFS('Hist LJ06'!$N:$N,'Hist LJ06'!$P:$P,"Hortifruti") -> 6605936.1
H11: 1 | U11: Agosto | V11: ='Hist LJ06'!I20 -> 4228069.2 | X11: Media mês | Y11: =Y10/12 -> 550494.68
U12: Setembro | V12: ='Hist LJ06'!J20 -> 3934609.1 | X12: Venda Por QL | Y12: =Y11/J35 -> 110098.94
C13: FRENTE CAIXA | E13: LOJA | H13: AÇOUGUE | J13: HORTFRUTI | L13: FRIOS | N13: PADARIA | O13: CONFEITARIA | P13: ROTISSERIA | R13: Depósito | U13: Outubro | V13: ='Hist LJ06'!K20 -> 4116730.4 | X13: Meta | Y13: 80000
C14: Encarregado | E14: Encarregado | H14: Encarregado | J14: Encarregado | L14: Encarregado | N14: Encarregado | O14: Encarregado | P14: Encarregado | R14: Encarregado | U14: Novembro | V14: ='Hist LJ06'!L20 -> 4088787.4
C15: 1 | E15: 1 | H15: 1 | J15: 1 | L15: 1 | N15: 1 | O15: 0 | P15: 0 | R15: 0 | U15: Dezenbro | V15: ='Hist LJ06'!M20 -> 4724319.3 | X15: Confeitaria
U16: Total | V16: ='Hist LJ06'!N20 -> 49244758 | X16: Venda Ano 2025 | Y16: =SUMIFS('Hist LJ06'!$N:$N,'Hist LJ06'!$P:$P,"Confeitaria") -> 656472.21
C17: Fiscal de Caixa | E17: Repositor | F17: Limpeza | H17: Desossador | J17: Repositor | L17: Atendente | N17: Atendente | O17: Confeiteira | P17: Cozinheiro | R17: Conferente | U17: Media 12 meses | V17: =V16/12 -> 4103729.8 | X17: Media mês | Y17: =Y16/12 -> 54706.017
C18: 4 | E18: 8 | F18: 3 | H18: 2 | J18: 5 | L18: 3 | N18: 5 | O18: 1 | P18: 1 | R18: 2 | U18: Media por QL | V18: =V17/43000 -> 95.435578 | X18: Venda Por QL | Y18: =Y17/O35 -> 27353.009
X19: Meta | Y19: 26000
C20: Operador Caixa | E20: Cartazista | F20: Estacionamento | H20: Açogueiro | J20: Rep Cortes | L20: Repositor | N20: Padeiro | O20: Auxiliar | P20: Auxiliar | R20: Auxiliar
C21: 18 | E21: 1 | F21: 2 | H21: 4 | J21: 1 | L21: 2 | N21: 3 | O21: 2 | P21: 1 | R21: 1 | U21: Frios / Congelados / Laticinios / Peix | X21: Padaria
U22: Venda Ano 2025 | V22: =SUMIFS('Hist LJ06'!$N:$N,'Hist LJ06'!$P:$P,"Frios") -> 6241154.5 | X22: Venda Ano 2025 | Y22: =SUMIFS('Hist LJ06'!$N:$N,'Hist LJ06'!$P:$P,"Padaria") -> 2156970.5
C23: Empacotador | E23: Auxiliar | F23: Entregador | H23: Balconista | N23: Auxiliar | R23: Controladoria | U23: Media mês | V23: =V22/12 -> 520096.21 | X23: Media mês | Y23: =Y22/12 -> 179747.54
C24: 2 | E24: 0 | F24: 2 | H24: 4 | N24: 2 | R24: 2 | U24: Venda Por QL | V24: =V23/L35 -> 104019.24 | X24: Venda Por QL | Y24: =Y23/N35 -> 14978.962
U25: Meta | V25: 80000 | X25: Meta | Y25: 16000
E26: Aprendiz | F26: E-Commerce | R26: Prevenção
E27: 5 | F27: 0 | R27: 1 | U27: Loja Total | X27: Rotisseria
U28: Venda Ano 2025 | V28: =SUMIFS('Hist LJ06'!$N:$N,'Hist LJ06'!$P:$P,"Loja") -> 23299394 | X28: Venda Ano 2025 | Y28: =SUMIFS('Hist LJ06'!$N:$N,'Hist LJ06'!$P:$P,"Rotisseria") -> 545267.73
E29: Gestão Pessoas | F29: Cor. Bancário | U29: Media mês | V29: =V28/12 -> 1941616.1 | X29: Media mês | Y29: =Y28/12 -> 45438.978
E30: 0 | F30: 0 | U30: Venda Por QL | V30: =V29/(E35+R35) -> 71911.709 | X30: Venda Por QL | Y30: =IFERROR(Y29/P35,0) -> 22719.489
C31: Orçado Acima | U31: Meta | V31: 160000 | X31: Meta | Y31: 25000
C32: Total | E32: Total | H32: Total | J32: Total | L32: Total | N32: PADARIA | O32: CONFEITARIA | P32: ROTISSERIA | R32: Total
C33: =C30+C27+C24+C21+C18+C15 -> 25 | E33: =E30+E27+E24+E21+E18+E15+F30+F27+F24+F21+F18 -> 22 | H33: =H30+H27+H24+H21+H18+H15 -> 11 | J33: =J30+J27+J24+J21+J18+J15 -> 7 | L33: =L30+L27+L24+L21+L18+L15 -> 6 | N33: =N30+N27+N24+N21+N18+N15 -> 11 | O33: =O30+O27+O24+O21+O18+O15 -> 3 | P33: =P30+P27+P24+P21+P18+P15 -> 2 | R33: =R30+R27+R24+R21+R18+R15 -> 6 | U33: Frente Caixa | X33: Prod Alimentos
C34: Total | E34: Total | H34: Total | J34: Total | L34: Total | N34: PADARIA | O34: CONFEITARIA | P34: ROTISSERIA | R34: Total | U34: Venda Ano 2025 | V34: =SUMIFS('Hist LJ06'!$N:$N,'Hist LJ06'!$P:$P,"Loja") -> 23299394 | X34: Venda Ano 2025 | Y34: =Y28+Y22+Y16 -> 3358710.5
C35: 23 | E35: 23 | H35: 9 | J35: 5 | L35: 5 | N35: 12 | O35: 2 | P35: 2 | R35: 4 | U35: Media mês | V35: =V34/12 -> 1941616.1 | X35: Media mês | Y35: =Y34/12 -> 279892.54
C36: Real Fev/26 | U36: Venda Por QL | V36: =V35/C35 -> 84418.093 | X36: Venda Por QL | Y36: =Y35/SUM(N35:P35) -> 17493.284
J37: Total | L37: Real | N37: Diferença | U37: Meta | V37: 138000 | X37: Meta | Y37: 21000
J39: =SUM(C33:R33)+H11+H7 -> 95 | L39: =SUM(A35:S35) -> 85 | N39: =L39-J39 -> -10

Sheet PLJ07
C3: Loja 07 | U3: 2025 | X3: Açougue
U4: Janeiro | V4: ='Hist LJ07'!B20 -> 3821531.6 | X4: Venda Ano 2025 | Y4: =SUMIFS('Hist LJ07'!$N:$N,'Hist LJ07'!$P:$P,"Açougue") -> 8011649.5
C5: Venda 2025 | E5: Venda R$ Funcionarios | H5: Gerente | P5: Abertura da loja | U5: Fevereiro | V5: ='Hist LJ07'!C20 -> 3629668.5 | X5: Media mês | Y5: =Y4/12 -> 667637.46
C6: =V16 -> 48793096 | E6: 43000 | U6: Março | V6: ='Hist LJ07'!D20 -> 4145407.5 | X6: Venda Por QL | Y6: =Y5/H35 -> 95376.78
H7: 1 | U7: Abril | V7: ='Hist LJ07'!E20 -> 4341610.6 | X7: Meta | Y7: 75000
C8: Media 12 mêses | E8: Proposta Quant | P8: Seg a Sab | R8: Domingos | U8: Maio | V8: ='Hist LJ07'!F20 -> 4016592.6
C9: =C6/12 -> 4066091.4 | E9: =C9/E6 -> 94.560264 | H9: Subgerente | P9: 08:00 as 21:00 | R9: 08:00 as 20:00 | U9: Junho | V9: ='Hist LJ07'!G20 -> 3792851.8 | X9: Hortifrut
U10: Julho | V10: ='Hist LJ07'!H20 -> 4114301.7 | X10: Venda Ano 2025 | Y10: =SUMIFS('Hist LJ07'!$N:$N,'Hist LJ07'!$P:$P,"Hortifruti") -> 5758169.4
H11: 1 | U11: Agosto | V11: ='Hist LJ07'!I20 -> 4102324.9 | X11: Media mês | Y11: =Y10/12 -> 479847.45
U12: Setembro | V12: ='Hist LJ07'!J20 -> 3896949.4 | X12: Venda Por QL | Y12: =Y11/J35 -> 79974.574
C13: FRENTE CAIXA | E13: LOJA | H13: AÇOUGUE | J13: HORTFRUTI | L13: FRIOS | N13: PADARIA | O13: CONFEITARIA | P13: ROTISSERIA | R13: Depósito | U13: Outubro | V13: ='Hist LJ07'!K20 -> 3922833.8 | X13: Meta | Y13: 80000
C14: Encarregado | E14: Encarregado | H14: Encarregado | J14: Encarregado | L14: Encarregado | N14: Encarregado | O14: Encarregado | P14: Encarregado | R14: Encarregado | U14: Novembro | V14: ='Hist LJ07'!L20 -> 4199361.4
C15: 1 | E15: 1 | H15: 1 | J15: 1 | L15: 1 | N15: 1 | O15: 0 | P15: 0 | R15: 1 | U15: Dezenbro | V15: ='Hist LJ07'!M20 -> 4809662.7 | X15: Confeitaria
U16: Total | V16: ='Hist LJ07'!N20 -> 48793096 | X16: Venda Ano 2025 | Y16: =SUMIFS('Hist LJ07'!$N:$N,'Hist LJ07'!$P:$P,"Confeitaria") -> 612869.45
C17: Fiscal de Caixa | E17: Repositor | F17: Limpeza | H17: Desossador | J17: Repositor | L17: Atendente | N17: Atendente | O17: Confeiteira | P17: Cozinheiro | R17: Conferente | U17: Media 12 meses | V17: =V16/12 -> 4066091.4 | X17: Media mês | Y17: =Y16/12 -> 51072.454
C18: 4 | E18: 9 | F18: 3 | H18: 2 | J18: 4 | L18: 3 | N18: 4 | O18: 1 | P18: 1 | R18: 1 | U18: Media por QL | V18: =V17/43000 -> 94.560264 | X18: Venda Por QL | Y18: =Y17/O35 -> 25536.227
X19: Meta | Y19: 26000
C20: Operador Caixa | E20: Cartazista | F20: Estacionamento | H20: Açogueiro | J20: Rep Cortes | L20: Repositor | N20: Padeiro | O20: Auxiliar | P20: Auxiliar | R20: Auxiliar
C21: 20 | E21: 1 | F21: 1 | H21: 4 | J21: 1 | L21: 2 | N21: 2 | O21: 1 | P21: 1 | R21: 2 | U21: Frios / Congelados / Laticinios / Peix | X21: Padaria
U22: Venda Ano 2025 | V22: =SUMIFS('Hist LJ07'!$N:$N,'Hist LJ07'!$P:$P,"Frios") -> 5677925.2 | X22: Venda Ano 2025 | Y22: =SUMIFS('Hist LJ07'!$N:$N,'Hist LJ07'!$P:$P,"Padaria") -> 1235218
C23: Empacotador | E23: Auxiliar | F23: Entregador | H23: Balconista | N23: Auxiliar | R23: Controladoria | U23: Media mês | V23: =V22/12 -> 473160.43 | X23: Media mês | Y23: =Y22/12 -> 102934.84
C24: 4 | E24: 0 | F24: 4 | H24: 3 | N24: 1 | R24: 2 | U24: Venda Por QL | V24: =V23/L35 -> 157720.14 | X24: Venda Por QL | Y24: =Y23/N35 -> 9357.7123
U25: Meta | V25: 80000 | X25: Meta | Y25: 16000
E26: Aprendiz | F26: E-Commerce | R26: Prevenção
E27: 2 | F27: 2 | R27: 1 | U27: Loja Total | X27: Rotisseria
U28: Venda Ano 2025 | V28: =SUMIFS('Hist LJ07'!$N:$N,'Hist LJ07'!$P:$P,"Loja") -> 27119395 | X28: Venda Ano 2025 | Y28: =SUMIFS('Hist LJ07'!$N:$N,'Hist LJ07'!$P:$P,"Rotisseria") -> 377870.25
E29: Gestão Pessoas | F29: Cor. Bancário | U29: Media mês | V29: =V28/12 -> 2259949.6 | X29: Media mês | Y29: =Y28/12 -> 31489.187
E30: 0 | F30: 0 | U30: Venda Por QL | V30: =V29/(E35+R35) -> 77929.295 | X30: Venda Por QL | Y30: =IFERROR(Y29/P35,0) -> 15744.594
C31: Orçado Acima | U31: Meta | V31: 160000 | X31: Meta | Y31: 25000
C32: Total | E32: Total | H32: Total | J32: Total | L32: Total | N32: PADARIA | O32: CONFEITARIA | P32: ROTISSERIA | R32: Total
C33: =C30+C27+C24+C21+C18+C15 -> 29 | E33: =E30+E27+E24+E21+E18+E15+F30+F27+F24+F21+F18 -> 23 | H33: =H30+H27+H24+H21+H18+H15 -> 10 | J33: =J30+J27+J24+J21+J18+J15 -> 6 | L33: =L30+L27+L24+L21+L18+L15 -> 6 | N33: =N30+N27+N24+N21+N18+N15 -> 8 | O33: =O30+O27+O24+O21+O18+O15 -> 2 | P33: =P30+P27+P24+P21+P18+P15 -> 2 | R33: =R30+R27+R24+R21+R18+R15 -> 7 | U33: Frente Caixa | X33: Prod Alimentos
C34: Total | E34: Total | H34: Total | J34: Total | L34: Total | N34: PADARIA | O34: CONFEITARIA | P34: ROTISSERIA | R34: Total | U34: Venda Ano 2025 | V34: =SUMIFS('Hist LJ07'!$N:$N,'Hist LJ07'!$P:$P,"Loja") -> 27119395 | X34: Venda Ano 2025 | Y34: =Y28+Y22+Y16 -> 2225957.7
C35: 32 | E35: 25 | H35: 7 | J35: 6 | L35: 3 | N35: 11 | O35: 2 | P35: 2 | R35: 4 | U35: Media mês | V35: =V34/12 -> 2259949.6 | X35: Media mês | Y35: =Y34/12 -> 185496.48
C36: Real Fev/26 | U36: Venda Por QL | V36: =V35/C35 -> 70623.423 | X36: Venda Por QL | Y36: =Y35/SUM(N35:P35) -> 12366.432
J37: Total | L37: Real | N37: Diferença | U37: Meta | V37: 138000 | X37: Meta | Y37: 21000
J39: =SUM(C33:R33)+H11+H7 -> 95 | L39: =SUM(C35:R35) -> 92 | N39: =L39-J39 -> -3

Sheet PLJ08
C3: Loja 08 | U3: 2025 | X3: Açougue
U4: Janeiro | V4: ='Hist LJ08'!B20 -> 3219511.4 | X4: Venda Ano 2025 | Y4: =SUMIFS('Hist LJ08'!$N:$N,'Hist LJ08'!$P:$P,"Açougue") -> 5763222.3
C5: Venda 2025 | E5: Venda R$ Funcionarios | H5: Gerente | P5: Abertura da loja | U5: Fevereiro | V5: ='Hist LJ08'!C20 -> 3101720.3 | X5: Media mês | Y5: =Y4/12 -> 480268.53
C6: =V16 -> 40395067 | E6: 43000 | U6: Março | V6: ='Hist LJ08'!D20 -> 3370344.1 | X6: Venda Por QL | Y6: =Y5/H35 -> 53363.17
H7: 1 | U7: Abril | V7: ='Hist LJ08'!E20 -> 3379026.8 | X7: Meta | Y7: 75000
C8: Media 12 mêses | E8: Proposta Quant | P8: Seg a Sab | R8: Domingos | U8: Maio | V8: ='Hist LJ08'!F20 -> 3349745.2
C9: =C6/12 -> 3366255.5 | E9: =C9/E6 -> 78.285013 | H9: Subgerente | P9: 08:00 as 21:00 | R9: 08:00 as 20:00 | U9: Junho | V9: ='Hist LJ08'!G20 -> 3073146 | X9: Hortifrut
U10: Julho | V10: ='Hist LJ08'!H20 -> 3277172.2 | X10: Venda Ano 2025 | Y10: =SUMIFS('Hist LJ08'!$N:$N,'Hist LJ08'!$P:$P,"Hortifruti") -> 4834607.6
H11: 1 | U11: Agosto | V11: ='Hist LJ08'!I20 -> 3265256.8 | X11: Media mês | Y11: =Y10/12 -> 402883.97
U12: Setembro | V12: ='Hist LJ08'!J20 -> 3058804 | X12: Venda Por QL | Y12: =Y11/J35 -> 80576.793
C13: FRENTE CAIXA | E13: LOJA | H13: AÇOUGUE | J13: HORTFRUTI | L13: FRIOS | N13: PADARIA | O13: CONFEITARIA | P13: ROTISSERIA | R13: Depósito | U13: Outubro | V13: ='Hist LJ08'!K20 -> 3373792.9 | X13: Meta | Y13: 80000
C14: Encarregado | E14: Encarregado | H14: Encarregado | J14: Encarregado | L14: Encarregado | N14: Encarregado | O14: Encarregado | P14: Encarregado | R14: Encarregado | U14: Novembro | V14: ='Hist LJ08'!L20 -> 3601251.9
C15: 1 | E15: 1 | H15: 1 | J15: 1 | L15: 1 | N15: 1 | O15: 0 | P15: 0 | R15: 1 | U15: Dezenbro | V15: ='Hist LJ08'!M20 -> 4325295.1 | X15: Confeitaria
U16: Total | V16: ='Hist LJ08'!N20 -> 40395067 | X16: Venda Ano 2025 | Y16: =SUMIFS('Hist LJ08'!$N:$N,'Hist LJ08'!$P:$P,"Confeitaria") -> 608704.17
C17: Fiscal de Caixa | E17: Repositor | F17: Limpeza | H17: Desossador | J17: Repositor | L17: Atendente | N17: Atendente | O17: Confeiteira | P17: Cozinheiro | R17: Conferente | U17: Media 12 meses | V17: =V16/12 -> 3366255.5 | X17: Media mês | Y17: =Y16/12 -> 50725.347
C18: 3 | E18: 6 | F18: 3 | H18: 2 | J18: 4 | L18: 2 | N18: 5 | O18: 1 | P18: 1 | R18: 1 | U18: Media por QL | V18: =V17/43000 -> 78.285013 | X18: Venda Por QL | Y18: =Y17/O35 -> 25362.674
X19: Meta | Y19: 26000
C20: Operador Caixa | E20: Cartazista | F20: Estacionamento | H20: Açogueiro | J20: Rep Cortes | L20: Repositor | N20: Padeiro | O20: Auxiliar | P20: Auxiliar | R20: Auxiliar
C21: 15 | E21: 1 | F21: 2 | H21: 3 | J21: 1 | L21: 2 | N21: 3 | O21: 1 | P21: 1 | R21: 1 | U21: Frios / Congelados / Laticinios / Peix | X21: Padaria
U22: Venda Ano 2025 | V22: =SUMIFS('Hist LJ08'!$N:$N,'Hist LJ08'!$P:$P,"Frios") -> 5713222.6 | X22: Venda Ano 2025 | Y22: =SUMIFS('Hist LJ08'!$N:$N,'Hist LJ08'!$P:$P,"Padaria") -> 1850270.9
C23: Empacotador | E23: Auxiliar | F23: Entregador | H23: Balconista | N23: Auxiliar | R23: Controladoria | U23: Media mês | V23: =V22/12 -> 476101.89 | X23: Media mês | Y23: =Y22/12 -> 154189.24
C24: 0 | E24: 0 | F24: 1 | H24: 2 | N24: 1 | R24: 2 | U24: Venda Por QL | V24: =V23/L35 -> 68014.555 | X24: Venda Por QL | Y24: =Y23/N35 -> 11860.711
U25: Meta | V25: 80000 | X25: Meta | Y25: 16000
E26: Aprendiz | F26: E-Commerce | R26: Prevenção
E27: 2 | F27: 1 | R27: 1 | U27: Loja Total | X27: Rotisseria
U28: Venda Ano 2025 | V28: =SUMIFS('Hist LJ08'!$N:$N,'Hist LJ08'!$P:$P,"Loja") -> 20800045 | X28: Venda Ano 2025 | Y28: =SUMIFS('Hist LJ08'!$N:$N,'Hist LJ08'!$P:$P,"Rotisseria") -> 824993.41
E29: Gestão Pessoas | F29: Cor. Bancário | U29: Media mês | V29: =V28/12 -> 1733337.1 | X29: Media mês | Y29: =Y28/12 -> 68749.451
E30: 1 | F30: 0 | U30: Venda Por QL | V30: =V29/(E35+R35) -> 86666.856 | X30: Venda Por QL | Y30: =IFERROR(Y29/P35,0) -> 34374.725
C31: Orçado Acima | U31: Meta | V31: 160000 | X31: Meta | Y31: 25000
C32: Total | E32: Total | H32: Total | J32: Total | L32: Total | N32: PADARIA | O32: CONFEITARIA | P32: ROTISSERIA | R32: Total
C33: =C30+C27+C24+C21+C18+C15 -> 19 | E33: =E30+E27+E24+E21+E18+E15+F30+F27+F24+F21+F18 -> 18 | H33: =H30+H27+H24+H21+H18+H15 -> 8 | J33: =J30+J27+J24+J21+J18+J15 -> 6 | L33: =L30+L27+L24+L21+L18+L15 -> 5 | N33: =N30+N27+N24+N21+N18+N15 -> 10 | O33: =O30+O27+O24+O21+O18+O15 -> 2 | P33: =P30+P27+P24+P21+P18+P15 -> 2 | R33: =R27+R30+R24+R21+R18+R15 -> 6 | U33: Frente Caixa | X33: Prod Alimentos
C34: Total | E34: Total | H34: Total | J34: Total | L34: Total | N34: PADARIA | O34: CONFEITARIA | P34: ROTISSERIA | R34: Total | U34: Venda Ano 2025 | V34: =SUMIFS('Hist LJ08'!$N:$N,'Hist LJ08'!$P:$P,"Loja") -> 20800045 | X34: Venda Ano 2025 | Y34: =Y28+Y22+Y16 -> 3283968.5
C35: 31 | E35: 16 | H35: 9 | J35: 5 | L35: 7 | N35: 13 | O35: 2 | P35: 2 | R35: 4 | U35: Media mês | V35: =V34/12 -> 1733337.1 | X35: Media mês | Y35: =Y34/12 -> 273664.04
C36: Real Fev/26 | U36: Venda Por QL | V36: =V35/C35 -> 55914.101 | X36: Venda Por QL | Y36: =Y35/SUM(N35:P35) -> 16097.885
J37: Total | L37: Real | N37: Diferença | U37: Meta | V37: 138000 | X37: Meta | Y37: 21000
J39: =SUM(C33:R33)+H11+H7 -> 78 | L39: =SUM(C35:R35) -> 89 | N39: =L39-J39 -> 11

Sheet PLJTT
C3: Lojas TT | U3: 2025 | X3: Açougue
U4: Janeiro | V4: ='Hist LJTT'!B20 -> 26463387 | X4: Venda Ano 2025 | Y4: =SUMIFS('Hist LJTT'!$N:$N,'Hist LJTT'!$P:$P,"Açougue") -> 61145643
C5: Venda 2025 | E5: Venda R$ Funcionarios | H5: Gerente | P5: Abertura da loja | U5: Fevereiro | V5: ='Hist LJTT'!C20 -> 25496698 | X5: Media mês | Y5: =Y4/12 -> 5095470.3
C6: =V16 -> 3.3984706e+08 | E6: 43000 | U6: Março | V6: ='Hist LJTT'!D20 -> 28607644 | X6: Venda Por QL | Y6: =Y5/H35 -> 78391.85
H7: 8 | U7: Abril | V7: ='Hist LJTT'!E20 -> 29096926 | X7: Meta | Y7: 75000
C8: Media 12 mêses | E8: Proposta Quant | P8: Seg a Sab | R8: Domingos | U8: Maio | V8: ='Hist LJTT'!F20 -> 28598246
C9: =C6/12 -> 28320588 | E9: ='PLJ01'!E9+'PLJ02'!E9+'PLJ03'!E9+'PLJ04'!E9+'PLJ05'!E9+'PLJ06'!E9+'PLJ07'!E9+'PLJ08'!E9 -> 658.61832 | H9: Subgerente | P9: 08:00 as 21:00 | R9: 08:00 as 20:00 | U9: Junho | V9: ='Hist LJTT'!G20 -> 27142168 | X9: Hortifrut
U10: Julho | V10: ='Hist LJTT'!H20 -> 28623444 | X10: Venda Ano 2025 | Y10: =SUMIFS('Hist LJTT'!$N:$N,'Hist LJTT'!$P:$P,"Hortifruti") -> 44203373
H11: 9 | U11: Agosto | V11: ='Hist LJTT'!I20 -> 28673916 | X11: Media mês | Y11: =Y10/12 -> 3683614.4
U12: Setembro | V12: ='Hist LJTT'!J20 -> 27093248 | X12: Venda Por QL | Y12: =Y11/J35 -> 92090.36
C13: FRENTE CAIXA | E13: LOJA | H13: AÇOUGUE | J13: HORTFRUTI | L13: FRIOS | N13: PADARIA | O13: CONFEITARIA | P13: ROTISSERIA | R13: Depósito | U13: Outubro | V13: ='Hist LJTT'!K20 -> 28065647 | X13: Meta | Y13: 80000
C14: Encarregado | E14: Encarregado | H14: Encarregado | J14: Encarregado | L14: Encarregado | N14: Encarregado | O14: Encarregado | P14: Encarregado | R14: Encarregado | U14: Novembro | V14: ='Hist LJTT'!L20 -> 28699918
C15: ='PLJ01'!C15+'PLJ02'!C15+'PLJ03'!C15+'PLJ04'!C15+'PLJ05'!C15+'PLJ06'!C15+'PLJ07'!C15+'PLJ08'!C15 -> 8 | E15: ='PLJ01'!E15+'PLJ02'!E15+'PLJ03'!E15+'PLJ04'!E15+'PLJ05'!E15+'PLJ06'!E15+'PLJ07'!E15+'PLJ08'!E15 -> 8 | F15: ='PLJ01'!F15+'PLJ02'!F15+'PLJ03'!F15+'PLJ04'!F15+'PLJ05'!F15+'PLJ06'!F15+'PLJ07'!F15+'PLJ08'!F15 -> 0 | H15: ='PLJ01'!H15+'PLJ02'!H15+'PLJ03'!H15+'PLJ04'!H15+'PLJ05'!H15+'PLJ06'!H15+'PLJ07'!H15+'PLJ08'!H15 -> 8 | J15: ='PLJ01'!J15+'PLJ02'!J15+'PLJ03'!J15+'PLJ04'!J15+'PLJ05'!J15+'PLJ06'!J15+'PLJ07'!J15+'PLJ08'!J15 -> 8 | L15: ='PLJ01'!L15+'PLJ02'!L15+'PLJ03'!L15+'PLJ04'!L15+'PLJ05'!L15+'PLJ06'!L15+'PLJ07'!L15+'PLJ08'!L15 -> 7 | N15: ='PLJ01'!N15+'PLJ02'!N15+'PLJ03'!N15+'PLJ04'!N15+'PLJ05'!N15+'PLJ06'!N15+'PLJ07'!N15+'PLJ08'!N15 -> 7 | O15: ='PLJ01'!O15+'PLJ02'!O15+'PLJ03'!O15+'PLJ04'!O15+'PLJ05'!O15+'PLJ06'!O15+'PLJ07'!O15+'PLJ08'!O15 -> 0 | P15: ='PLJ01'!P15+'PLJ02'!P15+'PLJ03'!P15+'PLJ04'!P15+'PLJ05'!P15+'PLJ06'!P15+'PLJ07'!P15+'PLJ08'!P15 -> 0 | R15: ='PLJ01'!R15+'PLJ02'!R15+'PLJ03'!R15+'PLJ04'!R15+'PLJ05'!R15+'PLJ06'!R15+'PLJ07'!R15+'PLJ08'!R15 -> 6 | U15: Dezenbro | V15: ='Hist LJTT'!M20 -> 33285814 | X15: Confeitaria
U16: Total | V16: ='Hist LJTT'!N20 -> 3.3984706e+08 | X16: Venda Ano 2025 | Y16: =SUMIFS('Hist LJTT'!$N:$N,'Hist LJTT'!$P:$P,"Confeitaria") -> 5208350
C17: Fiscal de Caixa | E17: Repositor | F17: Limpeza | H17: Desossador | J17: Repositor | L17: Atendente | N17: Atendente | O17: Confeiteira | P17: Cozinheiro | R17: Conferente | U17: Media 12 meses | V17: =V16/12 -> 28320588 | X17: Media mês | Y17: =Y16/12 -> 434029.16
C18: ='PLJ01'!C18+'PLJ02'!C18+'PLJ03'!C18+'PLJ04'!C18+'PLJ05'!C18+'PLJ06'!C18+'PLJ07'!C18+'PLJ08'!C18 -> 29 | E18: ='PLJ01'!E18+'PLJ02'!E18+'PLJ03'!E18+'PLJ04'!E18+'PLJ05'!E18+'PLJ06'!E18+'PLJ07'!E18+'PLJ08'!E18 -> 53 | F18: ='PLJ01'!F18+'PLJ02'!F18+'PLJ03'!F18+'PLJ04'!F18+'PLJ05'!F18+'PLJ06'!F18+'PLJ07'!F18+'PLJ08'!F18 -> 20 | H18: ='PLJ01'!H18+'PLJ02'!H18+'PLJ03'!H18+'PLJ04'!H18+'PLJ05'!H18+'PLJ06'!H18+'PLJ07'!H18+'PLJ08'!H18 -> 13 | J18: ='PLJ01'!J18+'PLJ02'!J18+'PLJ03'!J18+'PLJ04'!J18+'PLJ05'!J18+'PLJ06'!J18+'PLJ07'!J18+'PLJ08'!J18 -> 34 | L18: ='PLJ01'!L18+'PLJ02'!L18+'PLJ03'!L18+'PLJ04'!L18+'PLJ05'!L18+'PLJ06'!L18+'PLJ07'!L18+'PLJ08'!L18 -> 18 | N18: ='PLJ01'!N18+'PLJ02'!N18+'PLJ03'!N18+'PLJ04'!N18+'PLJ05'!N18+'PLJ06'!N18+'PLJ07'!N18+'PLJ08'!N18 -> 31 | O18: ='PLJ01'!O18+'PLJ02'!O18+'PLJ03'!O18+'PLJ04'!O18+'PLJ05'!O18+'PLJ06'!O18+'PLJ07'!O18+'PLJ08'!O18 -> 9 | P18: ='PLJ01'!P18+'PLJ02'!P18+'PLJ03'!P18+'PLJ04'!P18+'PLJ05'!P18+'PLJ06'!P18+'PLJ07'!P18+'PLJ08'!P18 -> 7 | R18: ='PLJ01'!R18+'PLJ02'!R18+'PLJ03'!R18+'PLJ04'!R18+'PLJ05'!R18+'PLJ06'!R18+'PLJ07'!R18+'PLJ08'!R18 -> 9 | U18: Media por QL | V18: =V17/43000 -> 658.61832 | X18: Venda Por QL | Y18: =Y17/O35 -> 28935.278
X19: Meta | Y19: 26000
C20: Operador Caixa | E20: Cartazista | F20: Estacionamento | H20: Açogueiro | J20: Rep Cortes | L20: Repositor | N20: Padeiro | O20: Auxiliar | P20: Auxiliar | R20: Auxiliar
C21: ='PLJ01'!C21+'PLJ02'!C21+'PLJ03'!C21+'PLJ04'!C21+'PLJ05'!C21+'PLJ06'!C21+'PLJ07'!C21+'PLJ08'!C21 -> 135 | E21: ='PLJ01'!E21+'PLJ02'!E21+'PLJ03'!E21+'PLJ04'!E21+'PLJ05'!E21+'PLJ06'!E21+'PLJ07'!E21+'PLJ08'!E21 -> 8 | F21: ='PLJ01'!F21+'PLJ02'!F21+'PLJ03'!F21+'PLJ04'!F21+'PLJ05'!F21+'PLJ06'!F21+'PLJ07'!F21+'PLJ08'!F21 -> 10 | H21: ='PLJ01'!H21+'PLJ02'!H21+'PLJ03'!H21+'PLJ04'!H21+'PLJ05'!H21+'PLJ06'!H21+'PLJ07'!H21+'PLJ08'!H21 -> 29 | J21: ='PLJ01'!J21+'PLJ02'!J21+'PLJ03'!J21+'PLJ04'!J21+'PLJ05'!J21+'PLJ06'!J21+'PLJ07'!J21+'PLJ08'!J21 -> 7 | L21: ='PLJ01'!L21+'PLJ02'!L21+'PLJ03'!L21+'PLJ04'!L21+'PLJ05'!L21+'PLJ06'!L21+'PLJ07'!L21+'PLJ08'!L21 -> 13 | N21: ='PLJ01'!N21+'PLJ02'!N21+'PLJ03'!N21+'PLJ04'!N21+'PLJ05'!N21+'PLJ06'!N21+'PLJ07'!N21+'PLJ08'!N21 -> 16 | O21: ='PLJ01'!O21+'PLJ02'!O21+'PLJ03'!O21+'PLJ04'!O21+'PLJ05'!O21+'PLJ06'!O21+'PLJ07'!O21+'PLJ08'!O21 -> 9 | P21: ='PLJ01'!P21+'PLJ02'!P21+'PLJ03'!P21+'PLJ04'!P21+'PLJ05'!P21+'PLJ06'!P21+'PLJ07'!P21+'PLJ08'!P21 -> 4 | R21: ='PLJ01'!R21+'PLJ02'!R21+'PLJ03'!R21+'PLJ04'!R21+'PLJ05'!R21+'PLJ06'!R21+'PLJ07'!R21+'PLJ08'!R21 -> 11 | U21: Frios / Congelados / Laticinios / Peix | X21: Padaria
U22: Venda Ano 2025 | V22: =SUMIFS('Hist LJTT'!$N:$N,'Hist LJTT'!$P:$P,"Frios") -> 41081408 | X22: Venda Ano 2025 | Y22: =SUMIFS('Hist LJTT'!$N:$N,'Hist LJTT'!$P:$P,"Padaria") -> 13262227
C23: Empacotador | E23: Auxiliar | F23: Entregador | H23: Balconista | N23: Auxiliar | R23: Controladoria | U23: Media mês | V23: =V22/12 -> 3423450.7 | X23: Media mês | Y23: =Y22/12 -> 1105185.6
C24: ='PLJ01'!C24+'PLJ02'!C24+'PLJ03'!C24+'PLJ04'!C24+'PLJ05'!C24+'PLJ06'!C24+'PLJ07'!C24+'PLJ08'!C24 -> 15 | E24: ='PLJ01'!E24+'PLJ02'!E24+'PLJ03'!E24+'PLJ04'!E24+'PLJ05'!E24+'PLJ06'!E24+'PLJ07'!E24+'PLJ08'!E24 -> 1 | F24: ='PLJ01'!F24+'PLJ02'!F24+'PLJ03'!F24+'PLJ04'!F24+'PLJ05'!F24+'PLJ06'!F24+'PLJ07'!F24+'PLJ08'!F24 -> 13 | H24: ='PLJ01'!H24+'PLJ02'!H24+'PLJ03'!H24+'PLJ04'!H24+'PLJ05'!H24+'PLJ06'!H24+'PLJ07'!H24+'PLJ08'!H24 -> 23 | N24: ='PLJ01'!N24+'PLJ02'!N24+'PLJ03'!N24+'PLJ04'!N24+'PLJ05'!N24+'PLJ06'!N24+'PLJ07'!N24+'PLJ08'!N24 -> 12 | R24: ='PLJ01'!R24+'PLJ02'!R24+'PLJ03'!R24+'PLJ04'!R24+'PLJ05'!R24+'PLJ06'!R24+'PLJ07'!R24+'PLJ08'!R24 -> 13 | U24: Venda Por QL | V24: =V23/L35 -> 106982.83 | X24: Venda Por QL | Y24: =Y23/N35 -> 14934.94
U25: Meta | V25: 80000 | X25: Meta | Y25: 16000
E26: Aprendiz | F26: E-Commerce | R26: Prevenção
E27: ='PLJ01'!E27+'PLJ02'!E27+'PLJ03'!E27+'PLJ04'!E27+'PLJ05'!E27+'PLJ06'!E27+'PLJ07'!E27+'PLJ08'!E27 -> 32 | F27: ='PLJ01'!F27+'PLJ02'!F27+'PLJ03'!F27+'PLJ04'!F27+'PLJ05'!F27+'PLJ06'!F27+'PLJ07'!F27+'PLJ08'!F27 -> 4 | R27: ='PLJ01'!R27+'PLJ02'!R27+'PLJ03'!R27+'PLJ04'!R27+'PLJ05'!R27+'PLJ06'!R27+'PLJ07'!R27+'PLJ08'!R27 -> 8 | U27: Loja Total | X27: Rotisseria
U28: Venda Ano 2025 | V28: =SUMIFS('Hist LJTT'!$N:$N,'Hist LJTT'!$P:$P,"Loja") -> 1.7161637e+08 | X28: Venda Ano 2025 | Y28: =SUMIFS('Hist LJTT'!$N:$N,'Hist LJTT'!$P:$P,"Rotisseria") -> 3329681.1
E29: Gestão Pessoas | F29: Cor. Bancário | U29: Media mês | V29: =V28/12 -> 14301364 | X29: Media mês | Y29: =Y28/12 -> 277473.42
E30: ='PLJ01'!E30+'PLJ02'!E30+'PLJ03'!E30+'PLJ04'!E30+'PLJ05'!E30+'PLJ06'!E30+'PLJ07'!E30+'PLJ08'!E30 -> 2 | F30: ='PLJ01'!F30+'PLJ02'!F30+'PLJ03'!F30+'PLJ04'!F30+'PLJ05'!F30+'PLJ06'!F30+'PLJ07'!F30+'PLJ08'!F30 -> 1 | U30: Venda Por QL | V30: =V29/(E35+R35) -> 72229.113 | X30: Venda Por QL | Y30: =Y29/P35 -> 18498.228
C31: Orçado Acima | U31: Meta | V31: 160000 | X31: Meta | Y31: 25000
C32: Total | E32: Total | H32: Total | J32: Total | L32: Total | N32: PADARIA | O32: CONFEITARIA | P32: ROTISSERIA | R32: Total
C33: =C30+C27+C24+C21+C18+C15 -> 187 | E33: =E30+E27+E24+E21+E18+E15+F30+F27+F24+F21+F18 -> 152 | H33: =H30+H27+H24+H21+H18+H15 -> 73 | J33: =J30+J27+J24+J21+J18+J15 -> 49 | L33: =L30+L27+L24+L21+L18+L15 -> 38 | N33: =N30+N27+N24+N21+N18+N15 -> 66 | O33: =O30+O27+O24+O21+O18+O15 -> 18 | P33: =P30+P27+P24+P21+P18+P15 -> 11 | R33: =R27+R30+R24+R21+R18+R15 -> 47 | U33: Frente Caixa | X33: Prod Alimentos
C34: Total | E34: Total | H34: Total | J34: Total | L34: Total | N34: PADARIA | O34: CONFEITARIA | P34: ROTISSERIA | R34: Total | U34: Venda Ano 2025 | V34: =SUMIFS('Hist LJTT'!$N:$N,'Hist LJTT'!$P:$P,"Loja") -> 1.7161637e+08 | X34: Venda Ano 2025 | Y34: =Y28+Y22+Y16 -> 21800258
C35: 190 | E35: 167 | H35: 65 | J35: 40 | L35: 32 | N35: 74 | O35: 15 | P35: 15 | R35: 31 | U35: Media mês | V35: =V34/12 -> 14301364 | X35: Media mês | Y35: =Y34/12 -> 1816688.2
C36: Real Fev/26 | U36: Venda Por QL | V36: =V35/C35 -> 75270.339 | X36: Venda Por QL | Y36: =Y35/SUM(N35:P35) -> 17468.155
J37: Total | L37: REAL | N37: Diferença | U37: Meta | V37: 138000 | X37: Meta | Y37: 21000
J39: =SUM(C33:R33)+H11+H7 -> 658 | L39: 629 | N39: =L39-J39 -> -29
K41: * | L41: ='PLJ01'!L39+'PLJ02'!L39+'PLJ03'!L39+'PLJ04'!L39+'PLJ05'!L39+'PLJ06'!L39+'PLJ07'!L39+'PLJ08'!L39 -> 629 | N41: Apenas Ativos e Férias

Sheet QLP 30
B5: Orçado | C5: Ativos | F5: Demitidos
B6: =SUM(C10:C375) -> 60 | C6: =SUM(E10:E352) -> 0 | D6: =C6-B6 -> -60 | F6: =COUNTIFS(D:D,"Demitido") -> 0
D8: DONO: ANALISTA | G8: DONO: SUPERVISOR | H8: DONO: GERENTE | M8: DONO: RH
A9: Titulo | B9: GERENTE | D9: Status | E9: Nomes | F9: Horário Sistema | G9: =IFERROR(IF(VLOOKUP($A9,#REF!,7,0)="","",VLOOKUP($A9,#REF!,7,0)),"") | H9: =IFERROR(IF(VLOOKUP($A9,#REF!,8,0)="","",VLOOKUP($A9,#REF!,8,0)),"") | I9: =IFERROR(IF(VLOOKUP($A9,#REF!,9,0)="","",VLOOKUP($A9,#REF!,9,0)),"") | J9: =IFERROR(IF(VLOOKUP($A9,#REF!,10,0)="","",VLOOKUP($A9,#REF!,10,0)),"") | K9: =IFERROR(IF(VLOOKUP($A9,#REF!,11,0)="","",VLOOKUP($A9,#REF!,11,0)),"") | L9: =IFERROR(IF(VLOOKUP($A9,#REF!,12,0)="","",VLOOKUP($A9,#REF!,12,0)),"") | M9: =IFERROR(IF(VLOOKUP($A9,#REF!,13,0)="","",VLOOKUP($A9,#REF!,13,0)),"") | N9: =IFERROR(IF(VLOOKUP($A9,#REF!,14,0)="","",VLOOKUP($A9,#REF!,14,0)),"") | O9: =IFERROR(IF(VLOOKUP($A9,#REF!,15,0)="","",VLOOKUP($A9,#REF!,15,0)),"")
A10: 1.30_DEPOSITO_GERENTE | D10: =IFERROR(VLOOKUP($A10,Banco!$A:$D,7,0),"") | E10: =IFERROR(VLOOKUP($A10,Banco!$A:$G,10,0),"-") -> - | F10: =IFERROR(RIGHT(VLOOKUP($E10,Banco!$G:$I,3,0),24),"") | G10: =IFERROR(IF(VLOOKUP($A10,#REF!,7,0)="","",VLOOKUP($A10,#REF!,7,0)),"") | H10: =IFERROR(IF(VLOOKUP($A10,#REF!,8,0)="","",VLOOKUP($A10,#REF!,8,0)),"") | I10: =IFERROR(IF(VLOOKUP($A10,#REF!,9,0)="","",VLOOKUP($A10,#REF!,9,0)),"") | J10: =IFERROR(IF(VLOOKUP($A10,#REF!,10,0)="","",VLOOKUP($A10,#REF!,10,0)),"") | K10: =IFERROR(IF(VLOOKUP($A10,#REF!,11,0)="","",VLOOKUP($A10,#REF!,11,0)),"") | L10: =IFERROR(IF(VLOOKUP($A10,#REF!,12,0)="","",VLOOKUP($A10,#REF!,12,0)),"") | M10: =IFERROR(IF(VLOOKUP($A10,#REF!,13,0)="","",VLOOKUP($A10,#REF!,13,0)),"") | N10: =IFERROR(IF(VLOOKUP($A10,#REF!,14,0)="","",VLOOKUP($A10,#REF!,14,0)),"") | O10: =IFERROR(IF(VLOOKUP($A10,#REF!,15,0)="","",VLOOKUP($A10,#REF!,15,0)),"")
A11: 2.30_DEPOSITO_GERENTE | D11: =IFERROR(VLOOKUP($A11,Banco!$A:$D,7,0),"") | E11: =IFERROR(VLOOKUP($A11,Banco!$A:$G,10,0),"-") -> - | F11: =IFERROR(RIGHT(VLOOKUP($E11,Banco!$G:$I,3,0),24),"") | G11: =IFERROR(IF(VLOOKUP($A11,#REF!,7,0)="","",VLOOKUP($A11,#REF!,7,0)),"") | H11: =IFERROR(IF(VLOOKUP($A11,#REF!,8,0)="","",VLOOKUP($A11,#REF!,8,0)),"") | I11: =IFERROR(IF(VLOOKUP($A11,#REF!,9,0)="","",VLOOKUP($A11,#REF!,9,0)),"") | J11: =IFERROR(IF(VLOOKUP($A11,#REF!,10,0)="","",VLOOKUP($A11,#REF!,10,0)),"") | K11: =IFERROR(IF(VLOOKUP($A11,#REF!,11,0)="","",VLOOKUP($A11,#REF!,11,0)),"") | L11: =IFERROR(IF(VLOOKUP($A11,#REF!,12,0)="","",VLOOKUP($A11,#REF!,12,0)),"") | M11: =IFERROR(IF(VLOOKUP($A11,#REF!,13,0)="","",VLOOKUP($A11,#REF!,13,0)),"") | N11: =IFERROR(IF(VLOOKUP($A11,#REF!,14,0)="","",VLOOKUP($A11,#REF!,14,0)),"") | O11: =IFERROR(IF(VLOOKUP($A11,#REF!,15,0)="","",VLOOKUP($A11,#REF!,15,0)),"")
A12: 3.30_DEPOSITO_GERENTE | B12: Autorizado | C12: ='PLJ30'!H7 -> 2 | D12: =IFERROR(VLOOKUP($A12,Banco!$A:$D,7,0),"") | E12: =IFERROR(VLOOKUP($A12,Banco!$A:$G,10,0),"-") -> - | F12: =IFERROR(RIGHT(VLOOKUP($E12,Banco!$G:$I,3,0),24),"") | G12: =IFERROR(IF(VLOOKUP($A12,#REF!,7,0)="","",VLOOKUP($A12,#REF!,7,0)),"") | H12: =IFERROR(IF(VLOOKUP($A12,#REF!,8,0)="","",VLOOKUP($A12,#REF!,8,0)),"") | I12: =IFERROR(IF(VLOOKUP($A12,#REF!,9,0)="","",VLOOKUP($A12,#REF!,9,0)),"") | J12: =IFERROR(IF(VLOOKUP($A12,#REF!,10,0)="","",VLOOKUP($A12,#REF!,10,0)),"") | K12: =IFERROR(IF(VLOOKUP($A12,#REF!,11,0)="","",VLOOKUP($A12,#REF!,11,0)),"") | L12: =IFERROR(IF(VLOOKUP($A12,#REF!,12,0)="","",VLOOKUP($A12,#REF!,12,0)),"") | M12: =IFERROR(IF(VLOOKUP($A12,#REF!,13,0)="","",VLOOKUP($A12,#REF!,13,0)),"") | N12: =IFERROR(IF(VLOOKUP($A12,#REF!,14,0)="","",VLOOKUP($A12,#REF!,14,0)),"") | O12: =IFERROR(IF(VLOOKUP($A12,#REF!,15,0)="","",VLOOKUP($A12,#REF!,15,0)),"")
B13: Ativos ---> | E13: =COUNTIFS(E10:E11,"<>-")-COUNTIFS(D10:D11,"Afastamento")-COUNTIFS(D10:D11,"Demitido") -> 0 | F13: =E13-C11 -> 0 | G13: =IFERROR(IF(VLOOKUP($A13,#REF!,7,0)="","",VLOOKUP($A13,#REF!,7,0)),"") | H13: =IFERROR(IF(VLOOKUP($A13,#REF!,8,0)="","",VLOOKUP($A13,#REF!,8,0)),"") | I13: =IFERROR(IF(VLOOKUP($A13,#REF!,9,0)="","",VLOOKUP($A13,#REF!,9,0)),"") | J13: =IFERROR(IF(VLOOKUP($A13,#REF!,10,0)="","",VLOOKUP($A13,#REF!,10,0)),"") | K13: =IFERROR(IF(VLOOKUP($A13,#REF!,11,0)="","",VLOOKUP($A13,#REF!,11,0)),"") | L13: =IFERROR(IF(VLOOKUP($A13,#REF!,12,0)="","",VLOOKUP($A13,#REF!,12,0)),"") | M13: =IFERROR(IF(VLOOKUP($A13,#REF!,13,0)="","",VLOOKUP($A13,#REF!,13,0)),"") | N13: =IFERROR(IF(VLOOKUP($A13,#REF!,14,0)="","",VLOOKUP($A13,#REF!,14,0)),"") | O13: =IFERROR(IF(VLOOKUP($A13,#REF!,15,0)="","",VLOOKUP($A13,#REF!,15,0)),"")
G14: =IFERROR(IF(VLOOKUP($A14,#REF!,7,0)="","",VLOOKUP($A14,#REF!,7,0)),"") | H14: =IFERROR(IF(VLOOKUP($A14,#REF!,8,0)="","",VLOOKUP($A14,#REF!,8,0)),"") | I14: =IFERROR(IF(VLOOKUP($A14,#REF!,9,0)="","",VLOOKUP($A14,#REF!,9,0)),"") | J14: =IFERROR(IF(VLOOKUP($A14,#REF!,10,0)="","",VLOOKUP($A14,#REF!,10,0)),"") | K14: =IFERROR(IF(VLOOKUP($A14,#REF!,11,0)="","",VLOOKUP($A14,#REF!,11,0)),"") | L14: =IFERROR(IF(VLOOKUP($A14,#REF!,12,0)="","",VLOOKUP($A14,#REF!,12,0)),"") | M14: =IFERROR(IF(VLOOKUP($A14,#REF!,13,0)="","",VLOOKUP($A14,#REF!,13,0)),"") | N14: =IFERROR(IF(VLOOKUP($A14,#REF!,14,0)="","",VLOOKUP($A14,#REF!,14,0)),"") | O14: =IFERROR(IF(VLOOKUP($A14,#REF!,15,0)="","",VLOOKUP($A14,#REF!,15,0)),"")
A15: Titulo | B15: ENCARREGADO | D15: Status | E15: Nomes | F15: Horário Sistema | G15: =IFERROR(IF(VLOOKUP($A15,#REF!,7,0)="","",VLOOKUP($A15,#REF!,7,0)),"") | H15: =IFERROR(IF(VLOOKUP($A15,#REF!,8,0)="","",VLOOKUP($A15,#REF!,8,0)),"") | I15: =IFERROR(IF(VLOOKUP($A15,#REF!,9,0)="","",VLOOKUP($A15,#REF!,9,0)),"") | J15: =IFERROR(IF(VLOOKUP($A15,#REF!,10,0)="","",VLOOKUP($A15,#REF!,10,0)),"") | K15: =IFERROR(IF(VLOOKUP($A15,#REF!,11,0)="","",VLOOKUP($A15,#REF!,11,0)),"") | L15: =IFERROR(IF(VLOOKUP($A15,#REF!,12,0)="","",VLOOKUP($A15,#REF!,12,0)),"") | M15: =IFERROR(IF(VLOOKUP($A15,#REF!,13,0)="","",VLOOKUP($A15,#REF!,13,0)),"") | N15: =IFERROR(IF(VLOOKUP($A15,#REF!,14,0)="","",VLOOKUP($A15,#REF!,14,0)),"") | O15: =IFERROR(IF(VLOOKUP($A15,#REF!,15,0)="","",VLOOKUP($A15,#REF!,15,0)),"")
A16: 1.30_DEPOSITO_ENCARREGADO | D16: =IFERROR(VLOOKUP($A16,Banco!$A:$D,7,0),"") | E16: =IFERROR(VLOOKUP($A16,Banco!$A:$G,10,0),"-") -> - | F16: =IFERROR(RIGHT(VLOOKUP($E16,Banco!$G:$I,3,0),24),"") | G16: =IFERROR(IF(VLOOKUP($A16,#REF!,7,0)="","",VLOOKUP($A16,#REF!,7,0)),"") | H16: =IFERROR(IF(VLOOKUP($A16,#REF!,8,0)="","",VLOOKUP($A16,#REF!,8,0)),"") | I16: =IFERROR(IF(VLOOKUP($A16,#REF!,9,0)="","",VLOOKUP($A16,#REF!,9,0)),"") | J16: =IFERROR(IF(VLOOKUP($A16,#REF!,10,0)="","",VLOOKUP($A16,#REF!,10,0)),"") | K16: =IFERROR(IF(VLOOKUP($A16,#REF!,11,0)="","",VLOOKUP($A16,#REF!,11,0)),"") | L16: =IFERROR(IF(VLOOKUP($A16,#REF!,12,0)="","",VLOOKUP($A16,#REF!,12,0)),"") | M16: =IFERROR(IF(VLOOKUP($A16,#REF!,13,0)="","",VLOOKUP($A16,#REF!,13,0)),"") | N16: =IFERROR(IF(VLOOKUP($A16,#REF!,14,0)="","",VLOOKUP($A16,#REF!,14,0)),"") | O16: =IFERROR(IF(VLOOKUP($A16,#REF!,15,0)="","",VLOOKUP($A16,#REF!,15,0)),"")
A17: 2.30_DEPOSITO_ENCARREGADO | B17: Autorizado | C17: ='PLJ30'!H11 -> 1 | D17: =IFERROR(VLOOKUP($A17,Banco!$A:$D,7,0),"") | E17: =IFERROR(VLOOKUP($A17,Banco!$A:$G,10,0),"-") -> - | F17: =IFERROR(RIGHT(VLOOKUP($E17,Banco!$G:$I,3,0),24),"") | G17: =IFERROR(IF(VLOOKUP($A17,#REF!,7,0)="","",VLOOKUP($A17,#REF!,7,0)),"") | H17: =IFERROR(IF(VLOOKUP($A17,#REF!,8,0)="","",VLOOKUP($A17,#REF!,8,0)),"") | I17: =IFERROR(IF(VLOOKUP($A17,#REF!,9,0)="","",VLOOKUP($A17,#REF!,9,0)),"") | J17: =IFERROR(IF(VLOOKUP($A17,#REF!,10,0)="","",VLOOKUP($A17,#REF!,10,0)),"") | K17: =IFERROR(IF(VLOOKUP($A17,#REF!,11,0)="","",VLOOKUP($A17,#REF!,11,0)),"") | L17: =IFERROR(IF(VLOOKUP($A17,#REF!,12,0)="","",VLOOKUP($A17,#REF!,12,0)),"") | M17: =IFERROR(IF(VLOOKUP($A17,#REF!,13,0)="","",VLOOKUP($A17,#REF!,13,0)),"") | N17: =IFERROR(IF(VLOOKUP($A17,#REF!,14,0)="","",VLOOKUP($A17,#REF!,14,0)),"") | O17: =IFERROR(IF(VLOOKUP($A17,#REF!,15,0)="","",VLOOKUP($A17,#REF!,15,0)),"")
B18: Ativos ---> | E18: =COUNTIFS(E16:E17,"<>-")-COUNTIFS(D16:D17,"Afastamento")-COUNTIFS(D16:D17,"Demitido") -> 0 | F18: =E18-C17 -> -1 | G18: =IFERROR(IF(VLOOKUP($A18,#REF!,7,0)="","",VLOOKUP($A18,#REF!,7,0)),"") | H18: =IFERROR(IF(VLOOKUP($A18,#REF!,8,0)="","",VLOOKUP($A18,#REF!,8,0)),"") | I18: =IFERROR(IF(VLOOKUP($A18,#REF!,9,0)="","",VLOOKUP($A18,#REF!,9,0)),"") | J18: =IFERROR(IF(VLOOKUP($A18,#REF!,10,0)="","",VLOOKUP($A18,#REF!,10,0)),"") | K18: =IFERROR(IF(VLOOKUP($A18,#REF!,11,0)="","",VLOOKUP($A18,#REF!,11,0)),"") | L18: =IFERROR(IF(VLOOKUP($A18,#REF!,12,0)="","",VLOOKUP($A18,#REF!,12,0)),"") | M18: =IFERROR(IF(VLOOKUP($A18,#REF!,13,0)="","",VLOOKUP($A18,#REF!,13,0)),"") | N18: =IFERROR(IF(VLOOKUP($A18,#REF!,14,0)="","",VLOOKUP($A18,#REF!,14,0)),"") | O18: =IFERROR(IF(VLOOKUP($A18,#REF!,15,0)="","",VLOOKUP($A18,#REF!,15,0)),"")
G19: =IFERROR(IF(VLOOKUP($A19,#REF!,7,0)="","",VLOOKUP($A19,#REF!,7,0)),"") | H19: =IFERROR(IF(VLOOKUP($A19,#REF!,8,0)="","",VLOOKUP($A19,#REF!,8,0)),"") | I19: =IFERROR(IF(VLOOKUP($A19,#REF!,9,0)="","",VLOOKUP($A19,#REF!,9,0)),"") | J19: =IFERROR(IF(VLOOKUP($A19,#REF!,10,0)="","",VLOOKUP($A19,#REF!,10,0)),"") | K19: =IFERROR(IF(VLOOKUP($A19,#REF!,11,0)="","",VLOOKUP($A19,#REF!,11,0)),"") | L19: =IFERROR(IF(VLOOKUP($A19,#REF!,12,0)="","",VLOOKUP($A19,#REF!,12,0)),"") | M19: =IFERROR(IF(VLOOKUP($A19,#REF!,13,0)="","",VLOOKUP($A19,#REF!,13,0)),"") | N19: =IFERROR(IF(VLOOKUP($A19,#REF!,14,0)="","",VLOOKUP($A19,#REF!,14,0)),"") | O19: =IFERROR(IF(VLOOKUP($A19,#REF!,15,0)="","",VLOOKUP($A19,#REF!,15,0)),"")
A20: Titulo | B20: CONFERENTE | D20: Status | E20: Nomes | F20: Horário Sistema | G20: =IFERROR(IF(VLOOKUP($A20,#REF!,7,0)="","",VLOOKUP($A20,#REF!,7,0)),"") | H20: =IFERROR(IF(VLOOKUP($A20,#REF!,8,0)="","",VLOOKUP($A20,#REF!,8,0)),"") | I20: =IFERROR(IF(VLOOKUP($A20,#REF!,9,0)="","",VLOOKUP($A20,#REF!,9,0)),"") | J20: =IFERROR(IF(VLOOKUP($A20,#REF!,10,0)="","",VLOOKUP($A20,#REF!,10,0)),"") | K20: =IFERROR(IF(VLOOKUP($A20,#REF!,11,0)="","",VLOOKUP($A20,#REF!,11,0)),"") | L20: =IFERROR(IF(VLOOKUP($A20,#REF!,12,0)="","",VLOOKUP($A20,#REF!,12,0)),"") | M20: =IFERROR(IF(VLOOKUP($A20,#REF!,13,0)="","",VLOOKUP($A20,#REF!,13,0)),"") | N20: =IFERROR(IF(VLOOKUP($A20,#REF!,14,0)="","",VLOOKUP($A20,#REF!,14,0)),"") | O20: =IFERROR(IF(VLOOKUP($A20,#REF!,15,0)="","",VLOOKUP($A20,#REF!,15,0)),"")
A21: 1.30_DEPOSITO_CONFERENTE | D21: =IFERROR(VLOOKUP($A21,Banco!$A:$D,7,0),"") | E21: =IFERROR(VLOOKUP($A21,Banco!$A:$G,10,0),"-") -> - | F21: =IFERROR(RIGHT(VLOOKUP($E21,Banco!$G:$I,3,0),24),"") | G21: =IFERROR(IF(VLOOKUP($A21,#REF!,7,0)="","",VLOOKUP($A21,#REF!,7,0)),"") | H21: =IFERROR(IF(VLOOKUP($A21,#REF!,8,0)="","",VLOOKUP($A21,#REF!,8,0)),"") | I21: =IFERROR(IF(VLOOKUP($A21,#REF!,9,0)="","",VLOOKUP($A21,#REF!,9,0)),"") | J21: =IFERROR(IF(VLOOKUP($A21,#REF!,10,0)="","",VLOOKUP($A21,#REF!,10,0)),"") | K21: =IFERROR(IF(VLOOKUP($A21,#REF!,11,0)="","",VLOOKUP($A21,#REF!,11,0)),"") | L21: =IFERROR(IF(VLOOKUP($A21,#REF!,12,0)="","",VLOOKUP($A21,#REF!,12,0)),"") | M21: =IFERROR(IF(VLOOKUP($A21,#REF!,13,0)="","",VLOOKUP($A21,#REF!,13,0)),"") | N21: =IFERROR(IF(VLOOKUP($A21,#REF!,14,0)="","",VLOOKUP($A21,#REF!,14,0)),"") | O21: =IFERROR(IF(VLOOKUP($A21,#REF!,15,0)="","",VLOOKUP($A21,#REF!,15,0)),"")
A22: 2.30_DEPOSITO_CONFERENTE | D22: =IFERROR(VLOOKUP($A22,Banco!$A:$D,7,0),"") | E22: =IFERROR(VLOOKUP($A22,Banco!$A:$G,10,0),"-") -> - | F22: =IFERROR(RIGHT(VLOOKUP($E22,Banco!$G:$I,3,0),24),"") | G22: =IFERROR(IF(VLOOKUP($A22,#REF!,7,0)="","",VLOOKUP($A22,#REF!,7,0)),"") | H22: =IFERROR(IF(VLOOKUP($A22,#REF!,8,0)="","",VLOOKUP($A22,#REF!,8,0)),"") | I22: =IFERROR(IF(VLOOKUP($A22,#REF!,9,0)="","",VLOOKUP($A22,#REF!,9,0)),"") | J22: =IFERROR(IF(VLOOKUP($A22,#REF!,10,0)="","",VLOOKUP($A22,#REF!,10,0)),"") | K22: =IFERROR(IF(VLOOKUP($A22,#REF!,11,0)="","",VLOOKUP($A22,#REF!,11,0)),"") | L22: =IFERROR(IF(VLOOKUP($A22,#REF!,12,0)="","",VLOOKUP($A22,#REF!,12,0)),"") | M22: =IFERROR(IF(VLOOKUP($A22,#REF!,13,0)="","",VLOOKUP($A22,#REF!,13,0)),"") | N22: =IFERROR(IF(VLOOKUP($A22,#REF!,14,0)="","",VLOOKUP($A22,#REF!,14,0)),"") | O22: =IFERROR(IF(VLOOKUP($A22,#REF!,15,0)="","",VLOOKUP($A22,#REF!,15,0)),"")
A23: 3.30_DEPOSITO_CONFERENTE | D23: =IFERROR(VLOOKUP($A23,Banco!$A:$D,7,0),"") | E23: =IFERROR(VLOOKUP($A23,Banco!$A:$G,10,0),"-") -> - | F23: =IFERROR(RIGHT(VLOOKUP($E23,Banco!$G:$I,3,0),24),"") | G23: =IFERROR(IF(VLOOKUP($A23,#REF!,7,0)="","",VLOOKUP($A23,#REF!,7,0)),"") | H23: =IFERROR(IF(VLOOKUP($A23,#REF!,8,0)="","",VLOOKUP($A23,#REF!,8,0)),"") | I23: =IFERROR(IF(VLOOKUP($A23,#REF!,9,0)="","",VLOOKUP($A23,#REF!,9,0)),"") | J23: =IFERROR(IF(VLOOKUP($A23,#REF!,10,0)="","",VLOOKUP($A23,#REF!,10,0)),"") | K23: =IFERROR(IF(VLOOKUP($A23,#REF!,11,0)="","",VLOOKUP($A23,#REF!,11,0)),"") | L23: =IFERROR(IF(VLOOKUP($A23,#REF!,12,0)="","",VLOOKUP($A23,#REF!,12,0)),"") | M23: =IFERROR(IF(VLOOKUP($A23,#REF!,13,0)="","",VLOOKUP($A23,#REF!,13,0)),"") | N23: =IFERROR(IF(VLOOKUP($A23,#REF!,14,0)="","",VLOOKUP($A23,#REF!,14,0)),"") | O23: =IFERROR(IF(VLOOKUP($A23,#REF!,15,0)="","",VLOOKUP($A23,#REF!,15,0)),"")
A24: 4.30_DEPOSITO_CONFERENTE | D24: =IFERROR(VLOOKUP($A24,Banco!$A:$D,7,0),"") | E24: =IFERROR(VLOOKUP($A24,Banco!$A:$G,10,0),"-") -> - | F24: =IFERROR(RIGHT(VLOOKUP($E24,Banco!$G:$I,3,0),24),"") | G24: =IFERROR(IF(VLOOKUP($A24,#REF!,7,0)="","",VLOOKUP($A24,#REF!,7,0)),"") | H24: =IFERROR(IF(VLOOKUP($A24,#REF!,8,0)="","",VLOOKUP($A24,#REF!,8,0)),"") | I24: =IFERROR(IF(VLOOKUP($A24,#REF!,9,0)="","",VLOOKUP($A24,#REF!,9,0)),"") | J24: =IFERROR(IF(VLOOKUP($A24,#REF!,10,0)="","",VLOOKUP($A24,#REF!,10,0)),"") | K24: =IFERROR(IF(VLOOKUP($A24,#REF!,11,0)="","",VLOOKUP($A24,#REF!,11,0)),"") | L24: =IFERROR(IF(VLOOKUP($A24,#REF!,12,0)="","",VLOOKUP($A24,#REF!,12,0)),"") | M24: =IFERROR(IF(VLOOKUP($A24,#REF!,13,0)="","",VLOOKUP($A24,#REF!,13,0)),"") | N24: =IFERROR(IF(VLOOKUP($A24,#REF!,14,0)="","",VLOOKUP($A24,#REF!,14,0)),"") | O24: =IFERROR(IF(VLOOKUP($A24,#REF!,15,0)="","",VLOOKUP($A24,#REF!,15,0)),"")
A25: 5.30_DEPOSITO_CONFERENTE | D25: =IFERROR(VLOOKUP($A25,Banco!$A:$D,7,0),"") | E25: =IFERROR(VLOOKUP($A25,Banco!$A:$G,10,0),"-") -> - | F25: =IFERROR(RIGHT(VLOOKUP($E25,Banco!$G:$I,3,0),24),"") | G25: =IFERROR(IF(VLOOKUP($A25,#REF!,7,0)="","",VLOOKUP($A25,#REF!,7,0)),"") | H25: =IFERROR(IF(VLOOKUP($A25,#REF!,8,0)="","",VLOOKUP($A25,#REF!,8,0)),"") | I25: =IFERROR(IF(VLOOKUP($A25,#REF!,9,0)="","",VLOOKUP($A25,#REF!,9,0)),"") | J25: =IFERROR(IF(VLOOKUP($A25,#REF!,10,0)="","",VLOOKUP($A25,#REF!,10,0)),"") | K25: =IFERROR(IF(VLOOKUP($A25,#REF!,11,0)="","",VLOOKUP($A25,#REF!,11,0)),"") | L25: =IFERROR(IF(VLOOKUP($A25,#REF!,12,0)="","",VLOOKUP($A25,#REF!,12,0)),"") | M25: =IFERROR(IF(VLOOKUP($A25,#REF!,13,0)="","",VLOOKUP($A25,#REF!,13,0)),"") | N25: =IFERROR(IF(VLOOKUP($A25,#REF!,14,0)="","",VLOOKUP($A25,#REF!,14,0)),"") | O25: =IFERROR(IF(VLOOKUP($A25,#REF!,15,0)="","",VLOOKUP($A25,#REF!,15,0)),"")
A26: 6.30_DEPOSITO_CONFERENTE | D26: =IFERROR(VLOOKUP($A26,Banco!$A:$D,7,0),"") | E26: =IFERROR(VLOOKUP($A26,Banco!$A:$G,10,0),"-") -> - | F26: =IFERROR(RIGHT(VLOOKUP($E26,Banco!$G:$I,3,0),24),"") | G26: =IFERROR(IF(VLOOKUP($A26,#REF!,7,0)="","",VLOOKUP($A26,#REF!,7,0)),"") | H26: =IFERROR(IF(VLOOKUP($A26,#REF!,8,0)="","",VLOOKUP($A26,#REF!,8,0)),"") | I26: =IFERROR(IF(VLOOKUP($A26,#REF!,9,0)="","",VLOOKUP($A26,#REF!,9,0)),"") | J26: =IFERROR(IF(VLOOKUP($A26,#REF!,10,0)="","",VLOOKUP($A26,#REF!,10,0)),"") | K26: =IFERROR(IF(VLOOKUP($A26,#REF!,11,0)="","",VLOOKUP($A26,#REF!,11,0)),"") | L26: =IFERROR(IF(VLOOKUP($A26,#REF!,12,0)="","",VLOOKUP($A26,#REF!,12,0)),"") | M26: =IFERROR(IF(VLOOKUP($A26,#REF!,13,0)="","",VLOOKUP($A26,#REF!,13,0)),"") | N26: =IFERROR(IF(VLOOKUP($A26,#REF!,14,0)="","",VLOOKUP($A26,#REF!,14,0)),"") | O26: =IFERROR(IF(VLOOKUP($A26,#REF!,15,0)="","",VLOOKUP($A26,#REF!,15,0)),"")
A27: 7.30_DEPOSITO_CONFERENTE | D27: =IFERROR(VLOOKUP($A27,Banco!$A:$D,7,0),"") | E27: =IFERROR(VLOOKUP($A27,Banco!$A:$G,10,0),"-") -> - | F27: =IFERROR(RIGHT(VLOOKUP($E27,Banco!$G:$I,3,0),24),"") | G27: =IFERROR(IF(VLOOKUP($A27,#REF!,7,0)="","",VLOOKUP($A27,#REF!,7,0)),"") | H27: =IFERROR(IF(VLOOKUP($A27,#REF!,8,0)="","",VLOOKUP($A27,#REF!,8,0)),"") | I27: =IFERROR(IF(VLOOKUP($A27,#REF!,9,0)="","",VLOOKUP($A27,#REF!,9,0)),"") | J27: =IFERROR(IF(VLOOKUP($A27,#REF!,10,0)="","",VLOOKUP($A27,#REF!,10,0)),"") | K27: =IFERROR(IF(VLOOKUP($A27,#REF!,11,0)="","",VLOOKUP($A27,#REF!,11,0)),"") | L27: =IFERROR(IF(VLOOKUP($A27,#REF!,12,0)="","",VLOOKUP($A27,#REF!,12,0)),"") | M27: =IFERROR(IF(VLOOKUP($A27,#REF!,13,0)="","",VLOOKUP($A27,#REF!,13,0)),"") | N27: =IFERROR(IF(VLOOKUP($A27,#REF!,14,0)="","",VLOOKUP($A27,#REF!,14,0)),"") | O27: =IFERROR(IF(VLOOKUP($A27,#REF!,15,0)="","",VLOOKUP($A27,#REF!,15,0)),"")
A28: 8.30_DEPOSITO_CONFERENTE | D28: =IFERROR(VLOOKUP($A28,Banco!$A:$D,7,0),"") | E28: =IFERROR(VLOOKUP($A28,Banco!$A:$G,10,0),"-") -> - | F28: =IFERROR(RIGHT(VLOOKUP($E28,Banco!$G:$I,3,0),24),"") | G28: =IFERROR(IF(VLOOKUP($A28,#REF!,7,0)="","",VLOOKUP($A28,#REF!,7,0)),"") | H28: =IFERROR(IF(VLOOKUP($A28,#REF!,8,0)="","",VLOOKUP($A28,#REF!,8,0)),"") | I28: =IFERROR(IF(VLOOKUP($A28,#REF!,9,0)="","",VLOOKUP($A28,#REF!,9,0)),"") | J28: =IFERROR(IF(VLOOKUP($A28,#REF!,10,0)="","",VLOOKUP($A28,#REF!,10,0)),"") | K28: =IFERROR(IF(VLOOKUP($A28,#REF!,11,0)="","",VLOOKUP($A28,#REF!,11,0)),"") | L28: =IFERROR(IF(VLOOKUP($A28,#REF!,12,0)="","",VLOOKUP($A28,#REF!,12,0)),"") | M28: =IFERROR(IF(VLOOKUP($A28,#REF!,13,0)="","",VLOOKUP($A28,#REF!,13,0)),"") | N28: =IFERROR(IF(VLOOKUP($A28,#REF!,14,0)="","",VLOOKUP($A28,#REF!,14,0)),"") | O28: =IFERROR(IF(VLOOKUP($A28,#REF!,15,0)="","",VLOOKUP($A28,#REF!,15,0)),"")
A29: 9.30_DEPOSITO_CONFERENTE | D29: =IFERROR(VLOOKUP($A29,Banco!$A:$D,7,0),"") | E29: =IFERROR(VLOOKUP($A29,Banco!$A:$G,10,0),"-") -> - | F29: =IFERROR(RIGHT(VLOOKUP($E29,Banco!$G:$I,3,0),24),"") | G29: =IFERROR(IF(VLOOKUP($A29,#REF!,7,0)="","",VLOOKUP($A29,#REF!,7,0)),"") | H29: =IFERROR(IF(VLOOKUP($A29,#REF!,8,0)="","",VLOOKUP($A29,#REF!,8,0)),"") | I29: =IFERROR(IF(VLOOKUP($A29,#REF!,9,0)="","",VLOOKUP($A29,#REF!,9,0)),"") | J29: =IFERROR(IF(VLOOKUP($A29,#REF!,10,0)="","",VLOOKUP($A29,#REF!,10,0)),"") | K29: =IFERROR(IF(VLOOKUP($A29,#REF!,11,0)="","",VLOOKUP($A29,#REF!,11,0)),"") | L29: =IFERROR(IF(VLOOKUP($A29,#REF!,12,0)="","",VLOOKUP($A29,#REF!,12,0)),"") | M29: =IFERROR(IF(VLOOKUP($A29,#REF!,13,0)="","",VLOOKUP($A29,#REF!,13,0)),"") | N29: =IFERROR(IF(VLOOKUP($A29,#REF!,14,0)="","",VLOOKUP($A29,#REF!,14,0)),"") | O29: =IFERROR(IF(VLOOKUP($A29,#REF!,15,0)="","",VLOOKUP($A29,#REF!,15,0)),"")
A30: 10.30_DEPOSITO_CONFERENTE | D30: =IFERROR(VLOOKUP($A30,Banco!$A:$D,7,0),"") | E30: =IFERROR(VLOOKUP($A30,Banco!$A:$G,10,0),"-") -> - | F30: =IFERROR(RIGHT(VLOOKUP($E30,Banco!$G:$I,3,0),24),"") | G30: =IFERROR(IF(VLOOKUP($A30,#REF!,7,0)="","",VLOOKUP($A30,#REF!,7,0)),"") | H30: =IFERROR(IF(VLOOKUP($A30,#REF!,8,0)="","",VLOOKUP($A30,#REF!,8,0)),"") | I30: =IFERROR(IF(VLOOKUP($A30,#REF!,9,0)="","",VLOOKUP($A30,#REF!,9,0)),"") | J30: =IFERROR(IF(VLOOKUP($A30,#REF!,10,0)="","",VLOOKUP($A30,#REF!,10,0)),"") | K30: =IFERROR(IF(VLOOKUP($A30,#REF!,11,0)="","",VLOOKUP($A30,#REF!,11,0)),"") | L30: =IFERROR(IF(VLOOKUP($A30,#REF!,12,0)="","",VLOOKUP($A30,#REF!,12,0)),"") | M30: =IFERROR(IF(VLOOKUP($A30,#REF!,13,0)="","",VLOOKUP($A30,#REF!,13,0)),"") | N30: =IFERROR(IF(VLOOKUP($A30,#REF!,14,0)="","",VLOOKUP($A30,#REF!,14,0)),"") | O30: =IFERROR(IF(VLOOKUP($A30,#REF!,15,0)="","",VLOOKUP($A30,#REF!,15,0)),"")
A31: 11.30_DEPOSITO_CONFERENTE | D31: =IFERROR(VLOOKUP($A31,Banco!$A:$D,7,0),"") | E31: =IFERROR(VLOOKUP($A31,Banco!$A:$G,10,0),"-") -> - | F31: =IFERROR(RIGHT(VLOOKUP($E31,Banco!$G:$I,3,0),24),"") | G31: =IFERROR(IF(VLOOKUP($A31,#REF!,7,0)="","",VLOOKUP($A31,#REF!,7,0)),"") | H31: =IFERROR(IF(VLOOKUP($A31,#REF!,8,0)="","",VLOOKUP($A31,#REF!,8,0)),"") | I31: =IFERROR(IF(VLOOKUP($A31,#REF!,9,0)="","",VLOOKUP($A31,#REF!,9,0)),"") | J31: =IFERROR(IF(VLOOKUP($A31,#REF!,10,0)="","",VLOOKUP($A31,#REF!,10,0)),"") | K31: =IFERROR(IF(VLOOKUP($A31,#REF!,11,0)="","",VLOOKUP($A31,#REF!,11,0)),"") | L31: =IFERROR(IF(VLOOKUP($A31,#REF!,12,0)="","",VLOOKUP($A31,#REF!,12,0)),"") | M31: =IFERROR(IF(VLOOKUP($A31,#REF!,13,0)="","",VLOOKUP($A31,#REF!,13,0)),"") | N31: =IFERROR(IF(VLOOKUP($A31,#REF!,14,0)="","",VLOOKUP($A31,#REF!,14,0)),"") | O31: =IFERROR(IF(VLOOKUP($A31,#REF!,15,0)="","",VLOOKUP($A31,#REF!,15,0)),"")
A32: 12.30_DEPOSITO_CONFERENTE | D32: =IFERROR(VLOOKUP($A32,Banco!$A:$D,7,0),"") | E32: =IFERROR(VLOOKUP($A32,Banco!$A:$G,10,0),"-") -> - | F32: =IFERROR(RIGHT(VLOOKUP($E32,Banco!$G:$I,3,0),24),"") | G32: =IFERROR(IF(VLOOKUP($A32,#REF!,7,0)="","",VLOOKUP($A32,#REF!,7,0)),"") | H32: =IFERROR(IF(VLOOKUP($A32,#REF!,8,0)="","",VLOOKUP($A32,#REF!,8,0)),"") | I32: =IFERROR(IF(VLOOKUP($A32,#REF!,9,0)="","",VLOOKUP($A32,#REF!,9,0)),"") | J32: =IFERROR(IF(VLOOKUP($A32,#REF!,10,0)="","",VLOOKUP($A32,#REF!,10,0)),"") | K32: =IFERROR(IF(VLOOKUP($A32,#REF!,11,0)="","",VLOOKUP($A32,#REF!,11,0)),"") | L32: =IFERROR(IF(VLOOKUP($A32,#REF!,12,0)="","",VLOOKUP($A32,#REF!,12,0)),"") | M32: =IFERROR(IF(VLOOKUP($A32,#REF!,13,0)="","",VLOOKUP($A32,#REF!,13,0)),"") | N32: =IFERROR(IF(VLOOKUP($A32,#REF!,14,0)="","",VLOOKUP($A32,#REF!,14,0)),"") | O32: =IFERROR(IF(VLOOKUP($A32,#REF!,15,0)="","",VLOOKUP($A32,#REF!,15,0)),"")
... A36: 16.30_DEPOSITO_CONFERENTE | D36: =IFERROR(VLOOKUP($A36,Banco!$A:$D,7,0),"") | E36: =IFERROR(VLOOKUP($A36,Banco!$A:$G,10,0),"-") -> - | F36: =IFERROR(RIGHT(VLOOKUP($E36,Banco!$G:$I,3,0),24),"") | G36: =IFERROR(IF(VLOOKUP($A36,#REF!,7,0)="","",VLOOKUP($A36,#REF!,7,0)),"") | H36: =IFERROR(IF(VLOOKUP($A36,#REF!,8,0)="","",VLOOKUP($A36,#REF!,8,0)),"") | I36: =IFERROR(IF(VLOOKUP($A36,#REF!,9,0)="","",VLOOKUP($A36,#REF!,9,0)),"") | J36: =IFERROR(IF(VLOOKUP($A36,#REF!,10,0)="","",VLOOKUP($A36,#REF!,10,0)),"") | K36: =IFERROR(IF(VLOOKUP($A36,#REF!,11,0)="","",VLOOKUP($A36,#REF!,11,0)),"") | L36: =IFERROR(IF(VLOOKUP($A36,#REF!,12,0)="","",VLOOKUP($A36,#REF!,12,0)),"") | M36: =IFERROR(IF(VLOOKUP($A36,#REF!,13,0)="","",VLOOKUP($A36,#REF!,13,0)),"") | N36: =IFERROR(IF(VLOOKUP($A36,#REF!,14,0)="","",VLOOKUP($A36,#REF!,14,0)),"") | O36: =IFERROR(IF(VLOOKUP($A36,#REF!,15,0)="","",VLOOKUP($A36,#REF!,15,0)),"")
A37: 32.30_DEPOSITO_CONFERENTE | B37: Autorizado | C37: ='PLJ30'!H18 -> 15 | D37: =IFERROR(VLOOKUP($A37,Banco!$A:$D,7,0),"") | E37: =IFERROR(VLOOKUP($A37,Banco!$A:$G,10,0),"-") -> - | F37: =IFERROR(RIGHT(VLOOKUP($E37,Banco!$G:$I,3,0),24),"") | G37: =IFERROR(IF(VLOOKUP($A37,#REF!,7,0)="","",VLOOKUP($A37,#REF!,7,0)),"") | H37: =IFERROR(IF(VLOOKUP($A37,#REF!,8,0)="","",VLOOKUP($A37,#REF!,8,0)),"") | I37: =IFERROR(IF(VLOOKUP($A37,#REF!,9,0)="","",VLOOKUP($A37,#REF!,9,0)),"") | J37: =IFERROR(IF(VLOOKUP($A37,#REF!,10,0)="","",VLOOKUP($A37,#REF!,10,0)),"") | K37: =IFERROR(IF(VLOOKUP($A37,#REF!,11,0)="","",VLOOKUP($A37,#REF!,11,0)),"") | L37: =IFERROR(IF(VLOOKUP($A37,#REF!,12,0)="","",VLOOKUP($A37,#REF!,12,0)),"") | M37: =IFERROR(IF(VLOOKUP($A37,#REF!,13,0)="","",VLOOKUP($A37,#REF!,13,0)),"") | N37: =IFERROR(IF(VLOOKUP($A37,#REF!,14,0)="","",VLOOKUP($A37,#REF!,14,0)),"") | O37: =IFERROR(IF(VLOOKUP($A37,#REF!,15,0)="","",VLOOKUP($A37,#REF!,15,0)),"")
B38: Ativos ---> | E38: =COUNTIFS(E21:E37,"<>-")-COUNTIFS(D21:D37,"Afastamento")-COUNTIFS(D21:D37,"Demitido") -> 0 | F38: =E38-C37 -> -15 | G38: =IFERROR(IF(VLOOKUP($A38,#REF!,7,0)="","",VLOOKUP($A38,#REF!,7,0)),"") | H38: =IFERROR(IF(VLOOKUP($A38,#REF!,8,0)="","",VLOOKUP($A38,#REF!,8,0)),"") | I38: =IFERROR(IF(VLOOKUP($A38,#REF!,9,0)="","",VLOOKUP($A38,#REF!,9,0)),"") | J38: =IFERROR(IF(VLOOKUP($A38,#REF!,10,0)="","",VLOOKUP($A38,#REF!,10,0)),"") | K38: =IFERROR(IF(VLOOKUP($A38,#REF!,11,0)="","",VLOOKUP($A38,#REF!,11,0)),"") | L38: =IFERROR(IF(VLOOKUP($A38,#REF!,12,0)="","",VLOOKUP($A38,#REF!,12,0)),"") | M38: =IFERROR(IF(VLOOKUP($A38,#REF!,13,0)="","",VLOOKUP($A38,#REF!,13,0)),"") | N38: =IFERROR(IF(VLOOKUP($A38,#REF!,14,0)="","",VLOOKUP($A38,#REF!,14,0)),"") | O38: =IFERROR(IF(VLOOKUP($A38,#REF!,15,0)="","",VLOOKUP($A38,#REF!,15,0)),"")
G39: =IFERROR(IF(VLOOKUP($A39,#REF!,7,0)="","",VLOOKUP($A39,#REF!,7,0)),"") | H39: =IFERROR(IF(VLOOKUP($A39,#REF!,8,0)="","",VLOOKUP($A39,#REF!,8,0)),"") | I39: =IFERROR(IF(VLOOKUP($A39,#REF!,9,0)="","",VLOOKUP($A39,#REF!,9,0)),"") | J39: =IFERROR(IF(VLOOKUP($A39,#REF!,10,0)="","",VLOOKUP($A39,#REF!,10,0)),"") | K39: =IFERROR(IF(VLOOKUP($A39,#REF!,11,0)="","",VLOOKUP($A39,#REF!,11,0)),"") | L39: =IFERROR(IF(VLOOKUP($A39,#REF!,12,0)="","",VLOOKUP($A39,#REF!,12,0)),"") | M39: =IFERROR(IF(VLOOKUP($A39,#REF!,13,0)="","",VLOOKUP($A39,#REF!,13,0)),"") | N39: =IFERROR(IF(VLOOKUP($A39,#REF!,14,0)="","",VLOOKUP($A39,#REF!,14,0)),"") | O39: =IFERROR(IF(VLOOKUP($A39,#REF!,15,0)="","",VLOOKUP($A39,#REF!,15,0)),"")
A40: Titulo | B40: EMPILHADEIRA | D40: Status | E40: Nomes | F40: Horário Sistema | G40: =IFERROR(IF(VLOOKUP($A40,#REF!,7,0)="","",VLOOKUP($A40,#REF!,7,0)),"") | H40: =IFERROR(IF(VLOOKUP($A40,#REF!,8,0)="","",VLOOKUP($A40,#REF!,8,0)),"") | I40: =IFERROR(IF(VLOOKUP($A40,#REF!,9,0)="","",VLOOKUP($A40,#REF!,9,0)),"") | J40: =IFERROR(IF(VLOOKUP($A40,#REF!,10,0)="","",VLOOKUP($A40,#REF!,10,0)),"") | K40: =IFERROR(IF(VLOOKUP($A40,#REF!,11,0)="","",VLOOKUP($A40,#REF!,11,0)),"") | L40: =IFERROR(IF(VLOOKUP($A40,#REF!,12,0)="","",VLOOKUP($A40,#REF!,12,0)),"") | M40: =IFERROR(IF(VLOOKUP($A40,#REF!,13,0)="","",VLOOKUP($A40,#REF!,13,0)),"") | N40: =IFERROR(IF(VLOOKUP($A40,#REF!,14,0)="","",VLOOKUP($A40,#REF!,14,0)),"") | O40: =IFERROR(IF(VLOOKUP($A40,#REF!,15,0)="","",VLOOKUP($A40,#REF!,15,0)),"")
A41: 1.30_DEPOSITO_EMPILHADEIRA | D41: =IFERROR(VLOOKUP($A41,Banco!$A:$D,7,0),"") | E41: =IFERROR(VLOOKUP($A41,Banco!$A:$G,10,0),"-") -> - | F41: =IFERROR(RIGHT(VLOOKUP($E41,Banco!$G:$I,3,0),24),"") | G41: =IFERROR(IF(VLOOKUP($A41,#REF!,7,0)="","",VLOOKUP($A41,#REF!,7,0)),"") | H41: =IFERROR(IF(VLOOKUP($A41,#REF!,8,0)="","",VLOOKUP($A41,#REF!,8,0)),"") | I41: =IFERROR(IF(VLOOKUP($A41,#REF!,9,0)="","",VLOOKUP($A41,#REF!,9,0)),"") | J41: =IFERROR(IF(VLOOKUP($A41,#REF!,10,0)="","",VLOOKUP($A41,#REF!,10,0)),"") | K41: =IFERROR(IF(VLOOKUP($A41,#REF!,11,0)="","",VLOOKUP($A41,#REF!,11,0)),"") | L41: =IFERROR(IF(VLOOKUP($A41,#REF!,12,0)="","",VLOOKUP($A41,#REF!,12,0)),"") | M41: =IFERROR(IF(VLOOKUP($A41,#REF!,13,0)="","",VLOOKUP($A41,#REF!,13,0)),"") | N41: =IFERROR(IF(VLOOKUP($A41,#REF!,14,0)="","",VLOOKUP($A41,#REF!,14,0)),"") | O41: =IFERROR(IF(VLOOKUP($A41,#REF!,15,0)="","",VLOOKUP($A41,#REF!,15,0)),"")
A42: 2.30_DEPOSITO_EMPILHADEIRA | D42: =IFERROR(VLOOKUP($A42,Banco!$A:$D,7,0),"") | E42: =IFERROR(VLOOKUP($A42,Banco!$A:$G,10,0),"-") -> - | F42: =IFERROR(RIGHT(VLOOKUP($E42,Banco!$G:$I,3,0),24),"") | G42: =IFERROR(IF(VLOOKUP($A42,#REF!,7,0)="","",VLOOKUP($A42,#REF!,7,0)),"") | H42: =IFERROR(IF(VLOOKUP($A42,#REF!,8,0)="","",VLOOKUP($A42,#REF!,8,0)),"") | I42: =IFERROR(IF(VLOOKUP($A42,#REF!,9,0)="","",VLOOKUP($A42,#REF!,9,0)),"") | J42: =IFERROR(IF(VLOOKUP($A42,#REF!,10,0)="","",VLOOKUP($A42,#REF!,10,0)),"") | K42: =IFERROR(IF(VLOOKUP($A42,#REF!,11,0)="","",VLOOKUP($A42,#REF!,11,0)),"") | L42: =IFERROR(IF(VLOOKUP($A42,#REF!,12,0)="","",VLOOKUP($A42,#REF!,12,0)),"") | M42: =IFERROR(IF(VLOOKUP($A42,#REF!,13,0)="","",VLOOKUP($A42,#REF!,13,0)),"") | N42: =IFERROR(IF(VLOOKUP($A42,#REF!,14,0)="","",VLOOKUP($A42,#REF!,14,0)),"") | O42: =IFERROR(IF(VLOOKUP($A42,#REF!,15,0)="","",VLOOKUP($A42,#REF!,15,0)),"")
A43: 3.30_DEPOSITO_EMPILHADEIRA | D43: =IFERROR(VLOOKUP($A43,Banco!$A:$D,7,0),"") | E43: =IFERROR(VLOOKUP($A43,Banco!$A:$G,10,0),"-") -> - | F43: =IFERROR(RIGHT(VLOOKUP($E43,Banco!$G:$I,3,0),24),"") | G43: =IFERROR(IF(VLOOKUP($A43,#REF!,7,0)="","",VLOOKUP($A43,#REF!,7,0)),"") | H43: =IFERROR(IF(VLOOKUP($A43,#REF!,8,0)="","",VLOOKUP($A43,#REF!,8,0)),"") | I43: =IFERROR(IF(VLOOKUP($A43,#REF!,9,0)="","",VLOOKUP($A43,#REF!,9,0)),"") | J43: =IFERROR(IF(VLOOKUP($A43,#REF!,10,0)="","",VLOOKUP($A43,#REF!,10,0)),"") | K43: =IFERROR(IF(VLOOKUP($A43,#REF!,11,0)="","",VLOOKUP($A43,#REF!,11,0)),"") | L43: =IFERROR(IF(VLOOKUP($A43,#REF!,12,0)="","",VLOOKUP($A43,#REF!,12,0)),"") | M43: =IFERROR(IF(VLOOKUP($A43,#REF!,13,0)="","",VLOOKUP($A43,#REF!,13,0)),"") | N43: =IFERROR(IF(VLOOKUP($A43,#REF!,14,0)="","",VLOOKUP($A43,#REF!,14,0)),"") | O43: =IFERROR(IF(VLOOKUP($A43,#REF!,15,0)="","",VLOOKUP($A43,#REF!,15,0)),"")
A44: 4.30_DEPOSITO_EMPILHADEIRA | D44: =IFERROR(VLOOKUP($A44,Banco!$A:$D,7,0),"") | E44: =IFERROR(VLOOKUP($A44,Banco!$A:$G,10,0),"-") -> - | F44: =IFERROR(RIGHT(VLOOKUP($E44,Banco!$G:$I,3,0),24),"") | G44: =IFERROR(IF(VLOOKUP($A44,#REF!,7,0)="","",VLOOKUP($A44,#REF!,7,0)),"") | H44: =IFERROR(IF(VLOOKUP($A44,#REF!,8,0)="","",VLOOKUP($A44,#REF!,8,0)),"") | I44: =IFERROR(IF(VLOOKUP($A44,#REF!,9,0)="","",VLOOKUP($A44,#REF!,9,0)),"") | J44: =IFERROR(IF(VLOOKUP($A44,#REF!,10,0)="","",VLOOKUP($A44,#REF!,10,0)),"") | K44: =IFERROR(IF(VLOOKUP($A44,#REF!,11,0)="","",VLOOKUP($A44,#REF!,11,0)),"") | L44: =IFERROR(IF(VLOOKUP($A44,#REF!,12,0)="","",VLOOKUP($A44,#REF!,12,0)),"") | M44: =IFERROR(IF(VLOOKUP($A44,#REF!,13,0)="","",VLOOKUP($A44,#REF!,13,0)),"") | N44: =IFERROR(IF(VLOOKUP($A44,#REF!,14,0)="","",VLOOKUP($A44,#REF!,14,0)),"") | O44: =IFERROR(IF(VLOOKUP($A44,#REF!,15,0)="","",VLOOKUP($A44,#REF!,15,0)),"")
A45: 5.30_DEPOSITO_EMPILHADEIRA | D45: =IFERROR(VLOOKUP($A45,Banco!$A:$D,7,0),"") | E45: =IFERROR(VLOOKUP($A45,Banco!$A:$G,10,0),"-") -> - | F45: =IFERROR(RIGHT(VLOOKUP($E45,Banco!$G:$I,3,0),24),"") | G45: =IFERROR(IF(VLOOKUP($A45,#REF!,7,0)="","",VLOOKUP($A45,#REF!,7,0)),"") | H45: =IFERROR(IF(VLOOKUP($A45,#REF!,8,0)="","",VLOOKUP($A45,#REF!,8,0)),"") | I45: =IFERROR(IF(VLOOKUP($A45,#REF!,9,0)="","",VLOOKUP($A45,#REF!,9,0)),"") | J45: =IFERROR(IF(VLOOKUP($A45,#REF!,10,0)="","",VLOOKUP($A45,#REF!,10,0)),"") | K45: =IFERROR(IF(VLOOKUP($A45,#REF!,11,0)="","",VLOOKUP($A45,#REF!,11,0)),"") | L45: =IFERROR(IF(VLOOKUP($A45,#REF!,12,0)="","",VLOOKUP($A45,#REF!,12,0)),"") | M45: =IFERROR(IF(VLOOKUP($A45,#REF!,13,0)="","",VLOOKUP($A45,#REF!,13,0)),"") | N45: =IFERROR(IF(VLOOKUP($A45,#REF!,14,0)="","",VLOOKUP($A45,#REF!,14,0)),"") | O45: =IFERROR(IF(VLOOKUP($A45,#REF!,15,0)="","",VLOOKUP($A45,#REF!,15,0)),"")
A46: 6.30_DEPOSITO_EMPILHADEIRA | D46: =IFERROR(VLOOKUP($A46,Banco!$A:$D,7,0),"") | E46: =IFERROR(VLOOKUP($A46,Banco!$A:$G,10,0),"-") -> - | F46: =IFERROR(RIGHT(VLOOKUP($E46,Banco!$G:$I,3,0),24),"") | G46: =IFERROR(IF(VLOOKUP($A46,#REF!,7,0)="","",VLOOKUP($A46,#REF!,7,0)),"") | H46: =IFERROR(IF(VLOOKUP($A46,#REF!,8,0)="","",VLOOKUP($A46,#REF!,8,0)),"") | I46: =IFERROR(IF(VLOOKUP($A46,#REF!,9,0)="","",VLOOKUP($A46,#REF!,9,0)),"") | J46: =IFERROR(IF(VLOOKUP($A46,#REF!,10,0)="","",VLOOKUP($A46,#REF!,10,0)),"") | K46: =IFERROR(IF(VLOOKUP($A46,#REF!,11,0)="","",VLOOKUP($A46,#REF!,11,0)),"") | L46: =IFERROR(IF(VLOOKUP($A46,#REF!,12,0)="","",VLOOKUP($A46,#REF!,12,0)),"") | M46: =IFERROR(IF(VLOOKUP($A46,#REF!,13,0)="","",VLOOKUP($A46,#REF!,13,0)),"") | N46: =IFERROR(IF(VLOOKUP($A46,#REF!,14,0)="","",VLOOKUP($A46,#REF!,14,0)),"") | O46: =IFERROR(IF(VLOOKUP($A46,#REF!,15,0)="","",VLOOKUP($A46,#REF!,15,0)),"")
A47: 7.30_DEPOSITO_EMPILHADEIRA | B47: Autorizado | C47: ='PLJ30'!N15 -> 4 | D47: =IFERROR(VLOOKUP($A47,Banco!$A:$D,7,0),"") | E47: =IFERROR(VLOOKUP($A47,Banco!$A:$G,10,0),"-") -> - | F47: =IFERROR(RIGHT(VLOOKUP($E47,Banco!$G:$I,3,0),24),"") | G47: =IFERROR(IF(VLOOKUP($A47,#REF!,7,0)="","",VLOOKUP($A47,#REF!,7,0)),"") | H47: =IFERROR(IF(VLOOKUP($A47,#REF!,8,0)="","",VLOOKUP($A47,#REF!,8,0)),"") | I47: =IFERROR(IF(VLOOKUP($A47,#REF!,9,0)="","",VLOOKUP($A47,#REF!,9,0)),"") | J47: =IFERROR(IF(VLOOKUP($A47,#REF!,10,0)="","",VLOOKUP($A47,#REF!,10,0)),"") | K47: =IFERROR(IF(VLOOKUP($A47,#REF!,11,0)="","",VLOOKUP($A47,#REF!,11,0)),"") | L47: =IFERROR(IF(VLOOKUP($A47,#REF!,12,0)="","",VLOOKUP($A47,#REF!,12,0)),"") | M47: =IFERROR(IF(VLOOKUP($A47,#REF!,13,0)="","",VLOOKUP($A47,#REF!,13,0)),"") | N47: =IFERROR(IF(VLOOKUP($A47,#REF!,14,0)="","",VLOOKUP($A47,#REF!,14,0)),"") | O47: =IFERROR(IF(VLOOKUP($A47,#REF!,15,0)="","",VLOOKUP($A47,#REF!,15,0)),"")
B48: Ativos ---> | E48: =COUNTIFS(E41:E47,"<>-")-COUNTIFS(D41:D47,"Afastamento")-COUNTIFS(D41:D47,"Demitido") -> 0 | F48: =E48-C47 -> -4 | G48: =IFERROR(IF(VLOOKUP($A48,#REF!,7,0)="","",VLOOKUP($A48,#REF!,7,0)),"") | H48: =IFERROR(IF(VLOOKUP($A48,#REF!,8,0)="","",VLOOKUP($A48,#REF!,8,0)),"") | I48: =IFERROR(IF(VLOOKUP($A48,#REF!,9,0)="","",VLOOKUP($A48,#REF!,9,0)),"") | J48: =IFERROR(IF(VLOOKUP($A48,#REF!,10,0)="","",VLOOKUP($A48,#REF!,10,0)),"") | K48: =IFERROR(IF(VLOOKUP($A48,#REF!,11,0)="","",VLOOKUP($A48,#REF!,11,0)),"") | L48: =IFERROR(IF(VLOOKUP($A48,#REF!,12,0)="","",VLOOKUP($A48,#REF!,12,0)),"") | M48: =IFERROR(IF(VLOOKUP($A48,#REF!,13,0)="","",VLOOKUP($A48,#REF!,13,0)),"") | N48: =IFERROR(IF(VLOOKUP($A48,#REF!,14,0)="","",VLOOKUP($A48,#REF!,14,0)),"") | O48: =IFERROR(IF(VLOOKUP($A48,#REF!,15,0)="","",VLOOKUP($A48,#REF!,15,0)),"")
G49: =IFERROR(IF(VLOOKUP($A49,#REF!,7,0)="","",VLOOKUP($A49,#REF!,7,0)),"") | H49: =IFERROR(IF(VLOOKUP($A49,#REF!,8,0)="","",VLOOKUP($A49,#REF!,8,0)),"") | I49: =IFERROR(IF(VLOOKUP($A49,#REF!,9,0)="","",VLOOKUP($A49,#REF!,9,0)),"") | J49: =IFERROR(IF(VLOOKUP($A49,#REF!,10,0)="","",VLOOKUP($A49,#REF!,10,0)),"") | K49: =IFERROR(IF(VLOOKUP($A49,#REF!,11,0)="","",VLOOKUP($A49,#REF!,11,0)),"") | L49: =IFERROR(IF(VLOOKUP($A49,#REF!,12,0)="","",VLOOKUP($A49,#REF!,12,0)),"") | M49: =IFERROR(IF(VLOOKUP($A49,#REF!,13,0)="","",VLOOKUP($A49,#REF!,13,0)),"") | N49: =IFERROR(IF(VLOOKUP($A49,#REF!,14,0)="","",VLOOKUP($A49,#REF!,14,0)),"") | O49: =IFERROR(IF(VLOOKUP($A49,#REF!,15,0)="","",VLOOKUP($A49,#REF!,15,0)),"")
A50: Titulo | B50: TROCAS | D50: Status | E50: Nomes | F50: Horário Sistema | G50: =IFERROR(IF(VLOOKUP($A50,#REF!,7,0)="","",VLOOKUP($A50,#REF!,7,0)),"") | H50: =IFERROR(IF(VLOOKUP($A50,#REF!,8,0)="","",VLOOKUP($A50,#REF!,8,0)),"") | I50: =IFERROR(IF(VLOOKUP($A50,#REF!,9,0)="","",VLOOKUP($A50,#REF!,9,0)),"") | J50: =IFERROR(IF(VLOOKUP($A50,#REF!,10,0)="","",VLOOKUP($A50,#REF!,10,0)),"") | K50: =IFERROR(IF(VLOOKUP($A50,#REF!,11,0)="","",VLOOKUP($A50,#REF!,11,0)),"") | L50: =IFERROR(IF(VLOOKUP($A50,#REF!,12,0)="","",VLOOKUP($A50,#REF!,12,0)),"") | M50: =IFERROR(IF(VLOOKUP($A50,#REF!,13,0)="","",VLOOKUP($A50,#REF!,13,0)),"") | N50: =IFERROR(IF(VLOOKUP($A50,#REF!,14,0)="","",VLOOKUP($A50,#REF!,14,0)),"") | O50: =IFERROR(IF(VLOOKUP($A50,#REF!,15,0)="","",VLOOKUP($A50,#REF!,15,0)),"")
A51: 1.30_DEPOSITO_TROCAS | D51: =IFERROR(VLOOKUP($A51,Banco!$A:$D,7,0),"") | E51: =IFERROR(VLOOKUP($A51,Banco!$A:$G,10,0),"-") -> - | F51: =IFERROR(RIGHT(VLOOKUP($E51,Banco!$G:$I,3,0),24),"") | G51: =IFERROR(IF(VLOOKUP($A51,#REF!,7,0)="","",VLOOKUP($A51,#REF!,7,0)),"") | H51: =IFERROR(IF(VLOOKUP($A51,#REF!,8,0)="","",VLOOKUP($A51,#REF!,8,0)),"") | I51: =IFERROR(IF(VLOOKUP($A51,#REF!,9,0)="","",VLOOKUP($A51,#REF!,9,0)),"") | J51: =IFERROR(IF(VLOOKUP($A51,#REF!,10,0)="","",VLOOKUP($A51,#REF!,10,0)),"") | K51: =IFERROR(IF(VLOOKUP($A51,#REF!,11,0)="","",VLOOKUP($A51,#REF!,11,0)),"") | L51: =IFERROR(IF(VLOOKUP($A51,#REF!,12,0)="","",VLOOKUP($A51,#REF!,12,0)),"") | M51: =IFERROR(IF(VLOOKUP($A51,#REF!,13,0)="","",VLOOKUP($A51,#REF!,13,0)),"") | N51: =IFERROR(IF(VLOOKUP($A51,#REF!,14,0)="","",VLOOKUP($A51,#REF!,14,0)),"") | O51: =IFERROR(IF(VLOOKUP($A51,#REF!,15,0)="","",VLOOKUP($A51,#REF!,15,0)),"")
A52: 2.30_DEPOSITO_TROCAS | D52: =IFERROR(VLOOKUP($A52,Banco!$A:$D,7,0),"") | E52: =IFERROR(VLOOKUP($A52,Banco!$A:$G,10,0),"-") -> - | F52: =IFERROR(RIGHT(VLOOKUP($E52,Banco!$G:$I,3,0),24),"") | G52: =IFERROR(IF(VLOOKUP($A52,#REF!,7,0)="","",VLOOKUP($A52,#REF!,7,0)),"") | H52: =IFERROR(IF(VLOOKUP($A52,#REF!,8,0)="","",VLOOKUP($A52,#REF!,8,0)),"") | I52: =IFERROR(IF(VLOOKUP($A52,#REF!,9,0)="","",VLOOKUP($A52,#REF!,9,0)),"") | J52: =IFERROR(IF(VLOOKUP($A52,#REF!,10,0)="","",VLOOKUP($A52,#REF!,10,0)),"") | K52: =IFERROR(IF(VLOOKUP($A52,#REF!,11,0)="","",VLOOKUP($A52,#REF!,11,0)),"") | L52: =IFERROR(IF(VLOOKUP($A52,#REF!,12,0)="","",VLOOKUP($A52,#REF!,12,0)),"") | M52: =IFERROR(IF(VLOOKUP($A52,#REF!,13,0)="","",VLOOKUP($A52,#REF!,13,0)),"") | N52: =IFERROR(IF(VLOOKUP($A52,#REF!,14,0)="","",VLOOKUP($A52,#REF!,14,0)),"") | O52: =IFERROR(IF(VLOOKUP($A52,#REF!,15,0)="","",VLOOKUP($A52,#REF!,15,0)),"")
A53: 3.30_DEPOSITO_TROCAS | D53: =IFERROR(VLOOKUP($A53,Banco!$A:$D,7,0),"") | E53: =IFERROR(VLOOKUP($A53,Banco!$A:$G,10,0),"-") -> - | F53: =IFERROR(RIGHT(VLOOKUP($E53,Banco!$G:$I,3,0),24),"") | G53: =IFERROR(IF(VLOOKUP($A53,#REF!,7,0)="","",VLOOKUP($A53,#REF!,7,0)),"") | H53: =IFERROR(IF(VLOOKUP($A53,#REF!,8,0)="","",VLOOKUP($A53,#REF!,8,0)),"") | I53: =IFERROR(IF(VLOOKUP($A53,#REF!,9,0)="","",VLOOKUP($A53,#REF!,9,0)),"") | J53: =IFERROR(IF(VLOOKUP($A53,#REF!,10,0)="","",VLOOKUP($A53,#REF!,10,0)),"") | K53: =IFERROR(IF(VLOOKUP($A53,#REF!,11,0)="","",VLOOKUP($A53,#REF!,11,0)),"") | L53: =IFERROR(IF(VLOOKUP($A53,#REF!,12,0)="","",VLOOKUP($A53,#REF!,12,0)),"") | M53: =IFERROR(IF(VLOOKUP($A53,#REF!,13,0)="","",VLOOKUP($A53,#REF!,13,0)),"") | N53: =IFERROR(IF(VLOOKUP($A53,#REF!,14,0)="","",VLOOKUP($A53,#REF!,14,0)),"") | O53: =IFERROR(IF(VLOOKUP($A53,#REF!,15,0)="","",VLOOKUP($A53,#REF!,15,0)),"")
A54: 4.30_DEPOSITO_TROCAS | B54: Autorizado | C54: ='PLJ30'!J18 -> 3 | D54: =IFERROR(VLOOKUP($A54,Banco!$A:$D,7,0),"") | E54: =IFERROR(VLOOKUP($A54,Banco!$A:$G,10,0),"-") -> - | F54: =IFERROR(RIGHT(VLOOKUP($E54,Banco!$G:$I,3,0),24),"") | G54: =IFERROR(IF(VLOOKUP($A54,#REF!,7,0)="","",VLOOKUP($A54,#REF!,7,0)),"") | H54: =IFERROR(IF(VLOOKUP($A54,#REF!,8,0)="","",VLOOKUP($A54,#REF!,8,0)),"") | I54: =IFERROR(IF(VLOOKUP($A54,#REF!,9,0)="","",VLOOKUP($A54,#REF!,9,0)),"") | J54: =IFERROR(IF(VLOOKUP($A54,#REF!,10,0)="","",VLOOKUP($A54,#REF!,10,0)),"") | K54: =IFERROR(IF(VLOOKUP($A54,#REF!,11,0)="","",VLOOKUP($A54,#REF!,11,0)),"") | L54: =IFERROR(IF(VLOOKUP($A54,#REF!,12,0)="","",VLOOKUP($A54,#REF!,12,0)),"") | M54: =IFERROR(IF(VLOOKUP($A54,#REF!,13,0)="","",VLOOKUP($A54,#REF!,13,0)),"") | N54: =IFERROR(IF(VLOOKUP($A54,#REF!,14,0)="","",VLOOKUP($A54,#REF!,14,0)),"") | O54: =IFERROR(IF(VLOOKUP($A54,#REF!,15,0)="","",VLOOKUP($A54,#REF!,15,0)),"")
B55: Ativos ---> | E55: =COUNTIFS(E51:E53,"<>-")-COUNTIFS(D51:D53,"Afastamento")-COUNTIFS(D51:D53,"Demitido") -> 0 | F55: =E55-C53 -> 0 | G55: =IFERROR(IF(VLOOKUP($A55,#REF!,7,0)="","",VLOOKUP($A55,#REF!,7,0)),"") | H55: =IFERROR(IF(VLOOKUP($A55,#REF!,8,0)="","",VLOOKUP($A55,#REF!,8,0)),"") | I55: =IFERROR(IF(VLOOKUP($A55,#REF!,9,0)="","",VLOOKUP($A55,#REF!,9,0)),"") | J55: =IFERROR(IF(VLOOKUP($A55,#REF!,10,0)="","",VLOOKUP($A55,#REF!,10,0)),"") | K55: =IFERROR(IF(VLOOKUP($A55,#REF!,11,0)="","",VLOOKUP($A55,#REF!,11,0)),"") | L55: =IFERROR(IF(VLOOKUP($A55,#REF!,12,0)="","",VLOOKUP($A55,#REF!,12,0)),"") | M55: =IFERROR(IF(VLOOKUP($A55,#REF!,13,0)="","",VLOOKUP($A55,#REF!,13,0)),"") | N55: =IFERROR(IF(VLOOKUP($A55,#REF!,14,0)="","",VLOOKUP($A55,#REF!,14,0)),"") | O55: =IFERROR(IF(VLOOKUP($A55,#REF!,15,0)="","",VLOOKUP($A55,#REF!,15,0)),"")
G56: =IFERROR(IF(VLOOKUP($A56,#REF!,7,0)="","",VLOOKUP($A56,#REF!,7,0)),"") | H56: =IFERROR(IF(VLOOKUP($A56,#REF!,8,0)="","",VLOOKUP($A56,#REF!,8,0)),"") | I56: =IFERROR(IF(VLOOKUP($A56,#REF!,9,0)="","",VLOOKUP($A56,#REF!,9,0)),"") | J56: =IFERROR(IF(VLOOKUP($A56,#REF!,10,0)="","",VLOOKUP($A56,#REF!,10,0)),"") | K56: =IFERROR(IF(VLOOKUP($A56,#REF!,11,0)="","",VLOOKUP($A56,#REF!,11,0)),"") | L56: =IFERROR(IF(VLOOKUP($A56,#REF!,12,0)="","",VLOOKUP($A56,#REF!,12,0)),"") | M56: =IFERROR(IF(VLOOKUP($A56,#REF!,13,0)="","",VLOOKUP($A56,#REF!,13,0)),"") | N56: =IFERROR(IF(VLOOKUP($A56,#REF!,14,0)="","",VLOOKUP($A56,#REF!,14,0)),"") | O56: =IFERROR(IF(VLOOKUP($A56,#REF!,15,0)="","",VLOOKUP($A56,#REF!,15,0)),"")
A57: Titulo | B57: AUXILIAR | D57: Status | E57: Nomes | F57: Horário Sistema | G57: =IFERROR(IF(VLOOKUP($A57,#REF!,7,0)="","",VLOOKUP($A57,#REF!,7,0)),"") | H57: =IFERROR(IF(VLOOKUP($A57,#REF!,8,0)="","",VLOOKUP($A57,#REF!,8,0)),"") | I57: =IFERROR(IF(VLOOKUP($A57,#REF!,9,0)="","",VLOOKUP($A57,#REF!,9,0)),"") | J57: =IFERROR(IF(VLOOKUP($A57,#REF!,10,0)="","",VLOOKUP($A57,#REF!,10,0)),"") | K57: =IFERROR(IF(VLOOKUP($A57,#REF!,11,0)="","",VLOOKUP($A57,#REF!,11,0)),"") | L57: =IFERROR(IF(VLOOKUP($A57,#REF!,12,0)="","",VLOOKUP($A57,#REF!,12,0)),"") | M57: =IFERROR(IF(VLOOKUP($A57,#REF!,13,0)="","",VLOOKUP($A57,#REF!,13,0)),"") | N57: =IFERROR(IF(VLOOKUP($A57,#REF!,14,0)="","",VLOOKUP($A57,#REF!,14,0)),"") | O57: =IFERROR(IF(VLOOKUP($A57,#REF!,15,0)="","",VLOOKUP($A57,#REF!,15,0)),"")
A58: 1.30_DEPOSITO_AUXILIAR | D58: =IFERROR(VLOOKUP($A58,Banco!$A:$D,7,0),"") | E58: =IFERROR(VLOOKUP($A58,Banco!$A:$G,10,0),"-") -> - | F58: =IFERROR(RIGHT(VLOOKUP($E58,Banco!$G:$I,3,0),24),"") | G58: =IFERROR(IF(VLOOKUP($A58,#REF!,7,0)="","",VLOOKUP($A58,#REF!,7,0)),"") | H58: =IFERROR(IF(VLOOKUP($A58,#REF!,8,0)="","",VLOOKUP($A58,#REF!,8,0)),"") | I58: =IFERROR(IF(VLOOKUP($A58,#REF!,9,0)="","",VLOOKUP($A58,#REF!,9,0)),"") | J58: =IFERROR(IF(VLOOKUP($A58,#REF!,10,0)="","",VLOOKUP($A58,#REF!,10,0)),"") | K58: =IFERROR(IF(VLOOKUP($A58,#REF!,11,0)="","",VLOOKUP($A58,#REF!,11,0)),"") | L58: =IFERROR(IF(VLOOKUP($A58,#REF!,12,0)="","",VLOOKUP($A58,#REF!,12,0)),"") | M58: =IFERROR(IF(VLOOKUP($A58,#REF!,13,0)="","",VLOOKUP($A58,#REF!,13,0)),"") | N58: =IFERROR(IF(VLOOKUP($A58,#REF!,14,0)="","",VLOOKUP($A58,#REF!,14,0)),"") | O58: =IFERROR(IF(VLOOKUP($A58,#REF!,15,0)="","",VLOOKUP($A58,#REF!,15,0)),"")
A59: 2.30_DEPOSITO_AUXILIAR | D59: =IFERROR(VLOOKUP($A59,Banco!$A:$D,7,0),"") | E59: =IFERROR(VLOOKUP($A59,Banco!$A:$G,10,0),"-") -> - | F59: =IFERROR(RIGHT(VLOOKUP($E59,Banco!$G:$I,3,0),24),"") | G59: =IFERROR(IF(VLOOKUP($A59,#REF!,7,0)="","",VLOOKUP($A59,#REF!,7,0)),"") | H59: =IFERROR(IF(VLOOKUP($A59,#REF!,8,0)="","",VLOOKUP($A59,#REF!,8,0)),"") | I59: =IFERROR(IF(VLOOKUP($A59,#REF!,9,0)="","",VLOOKUP($A59,#REF!,9,0)),"") | J59: =IFERROR(IF(VLOOKUP($A59,#REF!,10,0)="","",VLOOKUP($A59,#REF!,10,0)),"") | K59: =IFERROR(IF(VLOOKUP($A59,#REF!,11,0)="","",VLOOKUP($A59,#REF!,11,0)),"") | L59: =IFERROR(IF(VLOOKUP($A59,#REF!,12,0)="","",VLOOKUP($A59,#REF!,12,0)),"") | M59: =IFERROR(IF(VLOOKUP($A59,#REF!,13,0)="","",VLOOKUP($A59,#REF!,13,0)),"") | N59: =IFERROR(IF(VLOOKUP($A59,#REF!,14,0)="","",VLOOKUP($A59,#REF!,14,0)),"") | O59: =IFERROR(IF(VLOOKUP($A59,#REF!,15,0)="","",VLOOKUP($A59,#REF!,15,0)),"")
A60: 3.30_DEPOSITO_AUXILIAR | D60: =IFERROR(VLOOKUP($A60,Banco!$A:$D,7,0),"") | E60: =IFERROR(VLOOKUP($A60,Banco!$A:$G,10,0),"-") -> - | F60: =IFERROR(RIGHT(VLOOKUP($E60,Banco!$G:$I,3,0),24),"") | G60: =IFERROR(IF(VLOOKUP($A60,#REF!,7,0)="","",VLOOKUP($A60,#REF!,7,0)),"") | H60: =IFERROR(IF(VLOOKUP($A60,#REF!,8,0)="","",VLOOKUP($A60,#REF!,8,0)),"") | I60: =IFERROR(IF(VLOOKUP($A60,#REF!,9,0)="","",VLOOKUP($A60,#REF!,9,0)),"") | J60: =IFERROR(IF(VLOOKUP($A60,#REF!,10,0)="","",VLOOKUP($A60,#REF!,10,0)),"") | K60: =IFERROR(IF(VLOOKUP($A60,#REF!,11,0)="","",VLOOKUP($A60,#REF!,11,0)),"") | L60: =IFERROR(IF(VLOOKUP($A60,#REF!,12,0)="","",VLOOKUP($A60,#REF!,12,0)),"") | M60: =IFERROR(IF(VLOOKUP($A60,#REF!,13,0)="","",VLOOKUP($A60,#REF!,13,0)),"") | N60: =IFERROR(IF(VLOOKUP($A60,#REF!,14,0)="","",VLOOKUP($A60,#REF!,14,0)),"") | O60: =IFERROR(IF(VLOOKUP($A60,#REF!,15,0)="","",VLOOKUP($A60,#REF!,15,0)),"")
A61: 4.30_DEPOSITO_AUXILIAR | D61: =IFERROR(VLOOKUP($A61,Banco!$A:$D,7,0),"") | E61: =IFERROR(VLOOKUP($A61,Banco!$A:$G,10,0),"-") -> - | F61: =IFERROR(RIGHT(VLOOKUP($E61,Banco!$G:$I,3,0),24),"") | G61: =IFERROR(IF(VLOOKUP($A61,#REF!,7,0)="","",VLOOKUP($A61,#REF!,7,0)),"") | H61: =IFERROR(IF(VLOOKUP($A61,#REF!,8,0)="","",VLOOKUP($A61,#REF!,8,0)),"") | I61: =IFERROR(IF(VLOOKUP($A61,#REF!,9,0)="","",VLOOKUP($A61,#REF!,9,0)),"") | J61: =IFERROR(IF(VLOOKUP($A61,#REF!,10,0)="","",VLOOKUP($A61,#REF!,10,0)),"") | K61: =IFERROR(IF(VLOOKUP($A61,#REF!,11,0)="","",VLOOKUP($A61,#REF!,11,0)),"") | L61: =IFERROR(IF(VLOOKUP($A61,#REF!,12,0)="","",VLOOKUP($A61,#REF!,12,0)),"") | M61: =IFERROR(IF(VLOOKUP($A61,#REF!,13,0)="","",VLOOKUP($A61,#REF!,13,0)),"") | N61: =IFERROR(IF(VLOOKUP($A61,#REF!,14,0)="","",VLOOKUP($A61,#REF!,14,0)),"") | O61: =IFERROR(IF(VLOOKUP($A61,#REF!,15,0)="","",VLOOKUP($A61,#REF!,15,0)),"")
A62: 5.30_DEPOSITO_AUXILIAR | D62: =IFERROR(VLOOKUP($A62,Banco!$A:$D,7,0),"") | E62: =IFERROR(VLOOKUP($A62,Banco!$A:$G,10,0),"-") -> - | F62: =IFERROR(RIGHT(VLOOKUP($E62,Banco!$G:$I,3,0),24),"") | G62: =IFERROR(IF(VLOOKUP($A62,#REF!,7,0)="","",VLOOKUP($A62,#REF!,7,0)),"") | H62: =IFERROR(IF(VLOOKUP($A62,#REF!,8,0)="","",VLOOKUP($A62,#REF!,8,0)),"") | I62: =IFERROR(IF(VLOOKUP($A62,#REF!,9,0)="","",VLOOKUP($A62,#REF!,9,0)),"") | J62: =IFERROR(IF(VLOOKUP($A62,#REF!,10,0)="","",VLOOKUP($A62,#REF!,10,0)),"") | K62: =IFERROR(IF(VLOOKUP($A62,#REF!,11,0)="","",VLOOKUP($A62,#REF!,11,0)),"") | L62: =IFERROR(IF(VLOOKUP($A62,#REF!,12,0)="","",VLOOKUP($A62,#REF!,12,0)),"") | M62: =IFERROR(IF(VLOOKUP($A62,#REF!,13,0)="","",VLOOKUP($A62,#REF!,13,0)),"") | N62: =IFERROR(IF(VLOOKUP($A62,#REF!,14,0)="","",VLOOKUP($A62,#REF!,14,0)),"") | O62: =IFERROR(IF(VLOOKUP($A62,#REF!,15,0)="","",VLOOKUP($A62,#REF!,15,0)),"")
A63: 6.30_DEPOSITO_AUXILIAR | D63: =IFERROR(VLOOKUP($A63,Banco!$A:$D,7,0),"") | E63: =IFERROR(VLOOKUP($A63,Banco!$A:$G,10,0),"-") -> - | F63: =IFERROR(RIGHT(VLOOKUP($E63,Banco!$G:$I,3,0),24),"") | G63: =IFERROR(IF(VLOOKUP($A63,#REF!,7,0)="","",VLOOKUP($A63,#REF!,7,0)),"") | H63: =IFERROR(IF(VLOOKUP($A63,#REF!,8,0)="","",VLOOKUP($A63,#REF!,8,0)),"") | I63: =IFERROR(IF(VLOOKUP($A63,#REF!,9,0)="","",VLOOKUP($A63,#REF!,9,0)),"") | J63: =IFERROR(IF(VLOOKUP($A63,#REF!,10,0)="","",VLOOKUP($A63,#REF!,10,0)),"") | K63: =IFERROR(IF(VLOOKUP($A63,#REF!,11,0)="","",VLOOKUP($A63,#REF!,11,0)),"") | L63: =IFERROR(IF(VLOOKUP($A63,#REF!,12,0)="","",VLOOKUP($A63,#REF!,12,0)),"") | M63: =IFERROR(IF(VLOOKUP($A63,#REF!,13,0)="","",VLOOKUP($A63,#REF!,13,0)),"") | N63: =IFERROR(IF(VLOOKUP($A63,#REF!,14,0)="","",VLOOKUP($A63,#REF!,14,0)),"") | O63: =IFERROR(IF(VLOOKUP($A63,#REF!,15,0)="","",VLOOKUP($A63,#REF!,15,0)),"")
A64: 7.30_DEPOSITO_AUXILIAR | D64: =IFERROR(VLOOKUP($A64,Banco!$A:$D,7,0),"") | E64: =IFERROR(VLOOKUP($A64,Banco!$A:$G,10,0),"-") -> - | F64: =IFERROR(RIGHT(VLOOKUP($E64,Banco!$G:$I,3,0),24),"") | G64: =IFERROR(IF(VLOOKUP($A64,#REF!,7,0)="","",VLOOKUP($A64,#REF!,7,0)),"") | H64: =IFERROR(IF(VLOOKUP($A64,#REF!,8,0)="","",VLOOKUP($A64,#REF!,8,0)),"") | I64: =IFERROR(IF(VLOOKUP($A64,#REF!,9,0)="","",VLOOKUP($A64,#REF!,9,0)),"") | J64: =IFERROR(IF(VLOOKUP($A64,#REF!,10,0)="","",VLOOKUP($A64,#REF!,10,0)),"") | K64: =IFERROR(IF(VLOOKUP($A64,#REF!,11,0)="","",VLOOKUP($A64,#REF!,11,0)),"") | L64: =IFERROR(IF(VLOOKUP($A64,#REF!,12,0)="","",VLOOKUP($A64,#REF!,12,0)),"") | M64: =IFERROR(IF(VLOOKUP($A64,#REF!,13,0)="","",VLOOKUP($A64,#REF!,13,0)),"") | N64: =IFERROR(IF(VLOOKUP($A64,#REF!,14,0)="","",VLOOKUP($A64,#REF!,14,0)),"") | O64: =IFERROR(IF(VLOOKUP($A64,#REF!,15,0)="","",VLOOKUP($A64,#REF!,15,0)),"")
A65: 8.30_DEPOSITO_AUXILIAR | D65: =IFERROR(VLOOKUP($A65,Banco!$A:$D,7,0),"") | E65: =IFERROR(VLOOKUP($A65,Banco!$A:$G,10,0),"-") -> - | F65: =IFERROR(RIGHT(VLOOKUP($E65,Banco!$G:$I,3,0),24),"") | G65: =IFERROR(IF(VLOOKUP($A65,#REF!,7,0)="","",VLOOKUP($A65,#REF!,7,0)),"") | H65: =IFERROR(IF(VLOOKUP($A65,#REF!,8,0)="","",VLOOKUP($A65,#REF!,8,0)),"") | I65: =IFERROR(IF(VLOOKUP($A65,#REF!,9,0)="","",VLOOKUP($A65,#REF!,9,0)),"") | J65: =IFERROR(IF(VLOOKUP($A65,#REF!,10,0)="","",VLOOKUP($A65,#REF!,10,0)),"") | K65: =IFERROR(IF(VLOOKUP($A65,#REF!,11,0)="","",VLOOKUP($A65,#REF!,11,0)),"") | L65: =IFERROR(IF(VLOOKUP($A65,#REF!,12,0)="","",VLOOKUP($A65,#REF!,12,0)),"") | M65: =IFERROR(IF(VLOOKUP($A65,#REF!,13,0)="","",VLOOKUP($A65,#REF!,13,0)),"") | N65: =IFERROR(IF(VLOOKUP($A65,#REF!,14,0)="","",VLOOKUP($A65,#REF!,14,0)),"") | O65: =IFERROR(IF(VLOOKUP($A65,#REF!,15,0)="","",VLOOKUP($A65,#REF!,15,0)),"")
A66: 9.30_DEPOSITO_AUXILIAR | D66: =IFERROR(VLOOKUP($A66,Banco!$A:$D,7,0),"") | E66: =IFERROR(VLOOKUP($A66,Banco!$A:$G,10,0),"-") -> - | F66: =IFERROR(RIGHT(VLOOKUP($E66,Banco!$G:$I,3,0),24),"") | G66: =IFERROR(IF(VLOOKUP($A66,#REF!,7,0)="","",VLOOKUP($A66,#REF!,7,0)),"") | H66: =IFERROR(IF(VLOOKUP($A66,#REF!,8,0)="","",VLOOKUP($A66,#REF!,8,0)),"") | I66: =IFERROR(IF(VLOOKUP($A66,#REF!,9,0)="","",VLOOKUP($A66,#REF!,9,0)),"") | J66: =IFERROR(IF(VLOOKUP($A66,#REF!,10,0)="","",VLOOKUP($A66,#REF!,10,0)),"") | K66: =IFERROR(IF(VLOOKUP($A66,#REF!,11,0)="","",VLOOKUP($A66,#REF!,11,0)),"") | L66: =IFERROR(IF(VLOOKUP($A66,#REF!,12,0)="","",VLOOKUP($A66,#REF!,12,0)),"") | M66: =IFERROR(IF(VLOOKUP($A66,#REF!,13,0)="","",VLOOKUP($A66,#REF!,13,0)),"") | N66: =IFERROR(IF(VLOOKUP($A66,#REF!,14,0)="","",VLOOKUP($A66,#REF!,14,0)),"") | O66: =IFERROR(IF(VLOOKUP($A66,#REF!,15,0)="","",VLOOKUP($A66,#REF!,15,0)),"")
A67: 10.30_DEPOSITO_AUXILIAR | D67: =IFERROR(VLOOKUP($A67,Banco!$A:$D,7,0),"") | E67: =IFERROR(VLOOKUP($A67,Banco!$A:$G,10,0),"-") -> - | F67: =IFERROR(RIGHT(VLOOKUP($E67,Banco!$G:$I,3,0),24),"") | G67: =IFERROR(IF(VLOOKUP($A67,#REF!,7,0)="","",VLOOKUP($A67,#REF!,7,0)),"") | H67: =IFERROR(IF(VLOOKUP($A67,#REF!,8,0)="","",VLOOKUP($A67,#REF!,8,0)),"") | I67: =IFERROR(IF(VLOOKUP($A67,#REF!,9,0)="","",VLOOKUP($A67,#REF!,9,0)),"") | J67: =IFERROR(IF(VLOOKUP($A67,#REF!,10,0)="","",VLOOKUP($A67,#REF!,10,0)),"") | K67: =IFERROR(IF(VLOOKUP($A67,#REF!,11,0)="","",VLOOKUP($A67,#REF!,11,0)),"") | L67: =IFERROR(IF(VLOOKUP($A67,#REF!,12,0)="","",VLOOKUP($A67,#REF!,12,0)),"") | M67: =IFERROR(IF(VLOOKUP($A67,#REF!,13,0)="","",VLOOKUP($A67,#REF!,13,0)),"") | N67: =IFERROR(IF(VLOOKUP($A67,#REF!,14,0)="","",VLOOKUP($A67,#REF!,14,0)),"") | O67: =IFERROR(IF(VLOOKUP($A67,#REF!,15,0)="","",VLOOKUP($A67,#REF!,15,0)),"")
A68: 11.30_DEPOSITO_AUXILIAR | D68: =IFERROR(VLOOKUP($A68,Banco!$A:$D,7,0),"") | E68: =IFERROR(VLOOKUP($A68,Banco!$A:$G,10,0),"-") -> - | F68: =IFERROR(RIGHT(VLOOKUP($E68,Banco!$G:$I,3,0),24),"") | G68: =IFERROR(IF(VLOOKUP($A68,#REF!,7,0)="","",VLOOKUP($A68,#REF!,7,0)),"") | H68: =IFERROR(IF(VLOOKUP($A68,#REF!,8,0)="","",VLOOKUP($A68,#REF!,8,0)),"") | I68: =IFERROR(IF(VLOOKUP($A68,#REF!,9,0)="","",VLOOKUP($A68,#REF!,9,0)),"") | J68: =IFERROR(IF(VLOOKUP($A68,#REF!,10,0)="","",VLOOKUP($A68,#REF!,10,0)),"") | K68: =IFERROR(IF(VLOOKUP($A68,#REF!,11,0)="","",VLOOKUP($A68,#REF!,11,0)),"") | L68: =IFERROR(IF(VLOOKUP($A68,#REF!,12,0)="","",VLOOKUP($A68,#REF!,12,0)),"") | M68: =IFERROR(IF(VLOOKUP($A68,#REF!,13,0)="","",VLOOKUP($A68,#REF!,13,0)),"") | N68: =IFERROR(IF(VLOOKUP($A68,#REF!,14,0)="","",VLOOKUP($A68,#REF!,14,0)),"") | O68: =IFERROR(IF(VLOOKUP($A68,#REF!,15,0)="","",VLOOKUP($A68,#REF!,15,0)),"")
A69: 12.30_DEPOSITO_AUXILIAR | D69: =IFERROR(VLOOKUP($A69,Banco!$A:$D,7,0),"") | E69: =IFERROR(VLOOKUP($A69,Banco!$A:$G,10,0),"-") -> - | F69: =IFERROR(RIGHT(VLOOKUP($E69,Banco!$G:$I,3,0),24),"") | G69: =IFERROR(IF(VLOOKUP($A69,#REF!,7,0)="","",VLOOKUP($A69,#REF!,7,0)),"") | H69: =IFERROR(IF(VLOOKUP($A69,#REF!,8,0)="","",VLOOKUP($A69,#REF!,8,0)),"") | I69: =IFERROR(IF(VLOOKUP($A69,#REF!,9,0)="","",VLOOKUP($A69,#REF!,9,0)),"") | J69: =IFERROR(IF(VLOOKUP($A69,#REF!,10,0)="","",VLOOKUP($A69,#REF!,10,0)),"") | K69: =IFERROR(IF(VLOOKUP($A69,#REF!,11,0)="","",VLOOKUP($A69,#REF!,11,0)),"") | L69: =IFERROR(IF(VLOOKUP($A69,#REF!,12,0)="","",VLOOKUP($A69,#REF!,12,0)),"") | M69: =IFERROR(IF(VLOOKUP($A69,#REF!,13,0)="","",VLOOKUP($A69,#REF!,13,0)),"") | N69: =IFERROR(IF(VLOOKUP($A69,#REF!,14,0)="","",VLOOKUP($A69,#REF!,14,0)),"") | O69: =IFERROR(IF(VLOOKUP($A69,#REF!,15,0)="","",VLOOKUP($A69,#REF!,15,0)),"")
... A95: 38.30_DEPOSITO_AUXILIAR | D95: =IFERROR(VLOOKUP($A95,Banco!$A:$D,7,0),"") | E95: =IFERROR(VLOOKUP($A95,Banco!$A:$G,10,0),"-") -> - | F95: =IFERROR(RIGHT(VLOOKUP($E95,Banco!$G:$I,3,0),24),"") | G95: =IFERROR(IF(VLOOKUP($A95,#REF!,7,0)="","",VLOOKUP($A95,#REF!,7,0)),"") | H95: =IFERROR(IF(VLOOKUP($A95,#REF!,8,0)="","",VLOOKUP($A95,#REF!,8,0)),"") | I95: =IFERROR(IF(VLOOKUP($A95,#REF!,9,0)="","",VLOOKUP($A95,#REF!,9,0)),"") | J95: =IFERROR(IF(VLOOKUP($A95,#REF!,10,0)="","",VLOOKUP($A95,#REF!,10,0)),"") | K95: =IFERROR(IF(VLOOKUP($A95,#REF!,11,0)="","",VLOOKUP($A95,#REF!,11,0)),"") | L95: =IFERROR(IF(VLOOKUP($A95,#REF!,12,0)="","",VLOOKUP($A95,#REF!,12,0)),"") | M95: =IFERROR(IF(VLOOKUP($A95,#REF!,13,0)="","",VLOOKUP($A95,#REF!,13,0)),"") | N95: =IFERROR(IF(VLOOKUP($A95,#REF!,14,0)="","",VLOOKUP($A95,#REF!,14,0)),"") | O95: =IFERROR(IF(VLOOKUP($A95,#REF!,15,0)="","",VLOOKUP($A95,#REF!,15,0)),"")
A96: 39.30_DEPOSITO_AUXILIAR | B96: Autorizado | C96: ='PLJ30'!H15 -> 30 | D96: =IFERROR(VLOOKUP($A96,Banco!$A:$D,7,0),"") | E96: =IFERROR(VLOOKUP($A96,Banco!$A:$G,10,0),"-") -> - | F96: =IFERROR(RIGHT(VLOOKUP($E96,Banco!$G:$I,3,0),24),"") | G96: =IFERROR(IF(VLOOKUP($A96,#REF!,7,0)="","",VLOOKUP($A96,#REF!,7,0)),"") | H96: =IFERROR(IF(VLOOKUP($A96,#REF!,8,0)="","",VLOOKUP($A96,#REF!,8,0)),"") | I96: =IFERROR(IF(VLOOKUP($A96,#REF!,9,0)="","",VLOOKUP($A96,#REF!,9,0)),"") | J96: =IFERROR(IF(VLOOKUP($A96,#REF!,10,0)="","",VLOOKUP($A96,#REF!,10,0)),"") | K96: =IFERROR(IF(VLOOKUP($A96,#REF!,11,0)="","",VLOOKUP($A96,#REF!,11,0)),"") | L96: =IFERROR(IF(VLOOKUP($A96,#REF!,12,0)="","",VLOOKUP($A96,#REF!,12,0)),"") | M96: =IFERROR(IF(VLOOKUP($A96,#REF!,13,0)="","",VLOOKUP($A96,#REF!,13,0)),"") | N96: =IFERROR(IF(VLOOKUP($A96,#REF!,14,0)="","",VLOOKUP($A96,#REF!,14,0)),"") | O96: =IFERROR(IF(VLOOKUP($A96,#REF!,15,0)="","",VLOOKUP($A96,#REF!,15,0)),"")
B97: Ativos ---> | E97: =COUNTIFS(E58:E92,"<>-")-COUNTIFS(D58:D92,"Afastamento")-COUNTIFS(D58:D92,"Demitido") -> 0 | F97: =E97-C92 -> 0 | G97: =IFERROR(IF(VLOOKUP($A97,#REF!,7,0)="","",VLOOKUP($A97,#REF!,7,0)),"") | H97: =IFERROR(IF(VLOOKUP($A97,#REF!,8,0)="","",VLOOKUP($A97,#REF!,8,0)),"") | I97: =IFERROR(IF(VLOOKUP($A97,#REF!,9,0)="","",VLOOKUP($A97,#REF!,9,0)),"") | J97: =IFERROR(IF(VLOOKUP($A97,#REF!,10,0)="","",VLOOKUP($A97,#REF!,10,0)),"") | K97: =IFERROR(IF(VLOOKUP($A97,#REF!,11,0)="","",VLOOKUP($A97,#REF!,11,0)),"") | L97: =IFERROR(IF(VLOOKUP($A97,#REF!,12,0)="","",VLOOKUP($A97,#REF!,12,0)),"") | M97: =IFERROR(IF(VLOOKUP($A97,#REF!,13,0)="","",VLOOKUP($A97,#REF!,13,0)),"") | N97: =IFERROR(IF(VLOOKUP($A97,#REF!,14,0)="","",VLOOKUP($A97,#REF!,14,0)),"") | O97: =IFERROR(IF(VLOOKUP($A97,#REF!,15,0)="","",VLOOKUP($A97,#REF!,15,0)),"")
G98: =IFERROR(IF(VLOOKUP($A98,#REF!,7,0)="","",VLOOKUP($A98,#REF!,7,0)),"") | H98: =IFERROR(IF(VLOOKUP($A98,#REF!,8,0)="","",VLOOKUP($A98,#REF!,8,0)),"") | I98: =IFERROR(IF(VLOOKUP($A98,#REF!,9,0)="","",VLOOKUP($A98,#REF!,9,0)),"") | J98: =IFERROR(IF(VLOOKUP($A98,#REF!,10,0)="","",VLOOKUP($A98,#REF!,10,0)),"") | K98: =IFERROR(IF(VLOOKUP($A98,#REF!,11,0)="","",VLOOKUP($A98,#REF!,11,0)),"") | L98: =IFERROR(IF(VLOOKUP($A98,#REF!,12,0)="","",VLOOKUP($A98,#REF!,12,0)),"") | M98: =IFERROR(IF(VLOOKUP($A98,#REF!,13,0)="","",VLOOKUP($A98,#REF!,13,0)),"") | N98: =IFERROR(IF(VLOOKUP($A98,#REF!,14,0)="","",VLOOKUP($A98,#REF!,14,0)),"") | O98: =IFERROR(IF(VLOOKUP($A98,#REF!,15,0)="","",VLOOKUP($A98,#REF!,15,0)),"")
A99: Titulo | B99: ENTREGADOR | D99: Status | E99: Nomes | F99: Horário Sistema | G99: =IFERROR(IF(VLOOKUP($A99,#REF!,7,0)="","",VLOOKUP($A99,#REF!,7,0)),"") | H99: =IFERROR(IF(VLOOKUP($A99,#REF!,8,0)="","",VLOOKUP($A99,#REF!,8,0)),"") | I99: =IFERROR(IF(VLOOKUP($A99,#REF!,9,0)="","",VLOOKUP($A99,#REF!,9,0)),"") | J99: =IFERROR(IF(VLOOKUP($A99,#REF!,10,0)="","",VLOOKUP($A99,#REF!,10,0)),"") | K99: =IFERROR(IF(VLOOKUP($A99,#REF!,11,0)="","",VLOOKUP($A99,#REF!,11,0)),"") | L99: =IFERROR(IF(VLOOKUP($A99,#REF!,12,0)="","",VLOOKUP($A99,#REF!,12,0)),"") | M99: =IFERROR(IF(VLOOKUP($A99,#REF!,13,0)="","",VLOOKUP($A99,#REF!,13,0)),"") | N99: =IFERROR(IF(VLOOKUP($A99,#REF!,14,0)="","",VLOOKUP($A99,#REF!,14,0)),"") | O99: =IFERROR(IF(VLOOKUP($A99,#REF!,15,0)="","",VLOOKUP($A99,#REF!,15,0)),"")
A100: 1.30_ENTREGA_ENTREGADOR | D100: =IFERROR(VLOOKUP($A100,Banco!$A:$D,7,0),"") | E100: =IFERROR(VLOOKUP($A100,Banco!$A:$G,10,0),"-") -> - | F100: =IFERROR(RIGHT(VLOOKUP($E100,Banco!$G:$I,3,0),24),"") | G100: =IFERROR(IF(VLOOKUP($A100,#REF!,7,0)="","",VLOOKUP($A100,#REF!,7,0)),"") | H100: =IFERROR(IF(VLOOKUP($A100,#REF!,8,0)="","",VLOOKUP($A100,#REF!,8,0)),"") | I100: =IFERROR(IF(VLOOKUP($A100,#REF!,9,0)="","",VLOOKUP($A100,#REF!,9,0)),"") | J100: =IFERROR(IF(VLOOKUP($A100,#REF!,10,0)="","",VLOOKUP($A100,#REF!,10,0)),"") | K100: =IFERROR(IF(VLOOKUP($A100,#REF!,11,0)="","",VLOOKUP($A100,#REF!,11,0)),"") | L100: =IFERROR(IF(VLOOKUP($A100,#REF!,12,0)="","",VLOOKUP($A100,#REF!,12,0)),"") | M100: =IFERROR(IF(VLOOKUP($A100,#REF!,13,0)="","",VLOOKUP($A100,#REF!,13,0)),"") | N100: =IFERROR(IF(VLOOKUP($A100,#REF!,14,0)="","",VLOOKUP($A100,#REF!,14,0)),"") | O100: =IFERROR(IF(VLOOKUP($A100,#REF!,15,0)="","",VLOOKUP($A100,#REF!,15,0)),"")
A101: 2.30_ENTREGA_ENTREGADOR | D101: =IFERROR(VLOOKUP($A101,Banco!$A:$D,7,0),"") | E101: =IFERROR(VLOOKUP($A101,Banco!$A:$G,10,0),"-") -> - | F101: =IFERROR(RIGHT(VLOOKUP($E101,Banco!$G:$I,3,0),24),"") | G101: =IFERROR(IF(VLOOKUP($A101,#REF!,7,0)="","",VLOOKUP($A101,#REF!,7,0)),"") | H101: =IFERROR(IF(VLOOKUP($A101,#REF!,8,0)="","",VLOOKUP($A101,#REF!,8,0)),"") | I101: =IFERROR(IF(VLOOKUP($A101,#REF!,9,0)="","",VLOOKUP($A101,#REF!,9,0)),"") | J101: =IFERROR(IF(VLOOKUP($A101,#REF!,10,0)="","",VLOOKUP($A101,#REF!,10,0)),"") | K101: =IFERROR(IF(VLOOKUP($A101,#REF!,11,0)="","",VLOOKUP($A101,#REF!,11,0)),"") | L101: =IFERROR(IF(VLOOKUP($A101,#REF!,12,0)="","",VLOOKUP($A101,#REF!,12,0)),"") | M101: =IFERROR(IF(VLOOKUP($A101,#REF!,13,0)="","",VLOOKUP($A101,#REF!,13,0)),"") | N101: =IFERROR(IF(VLOOKUP($A101,#REF!,14,0)="","",VLOOKUP($A101,#REF!,14,0)),"") | O101: =IFERROR(IF(VLOOKUP($A101,#REF!,15,0)="","",VLOOKUP($A101,#REF!,15,0)),"")
A102: 3.30_ENTREGA_ENTREGADOR | D102: =IFERROR(VLOOKUP($A102,Banco!$A:$D,7,0),"") | E102: =IFERROR(VLOOKUP($A102,Banco!$A:$G,10,0),"-") -> - | F102: =IFERROR(RIGHT(VLOOKUP($E102,Banco!$G:$I,3,0),24),"") | G102: =IFERROR(IF(VLOOKUP($A102,#REF!,7,0)="","",VLOOKUP($A102,#REF!,7,0)),"") | H102: =IFERROR(IF(VLOOKUP($A102,#REF!,8,0)="","",VLOOKUP($A102,#REF!,8,0)),"") | I102: =IFERROR(IF(VLOOKUP($A102,#REF!,9,0)="","",VLOOKUP($A102,#REF!,9,0)),"") | J102: =IFERROR(IF(VLOOKUP($A102,#REF!,10,0)="","",VLOOKUP($A102,#REF!,10,0)),"") | K102: =IFERROR(IF(VLOOKUP($A102,#REF!,11,0)="","",VLOOKUP($A102,#REF!,11,0)),"") | L102: =IFERROR(IF(VLOOKUP($A102,#REF!,12,0)="","",VLOOKUP($A102,#REF!,12,0)),"") | M102: =IFERROR(IF(VLOOKUP($A102,#REF!,13,0)="","",VLOOKUP($A102,#REF!,13,0)),"") | N102: =IFERROR(IF(VLOOKUP($A102,#REF!,14,0)="","",VLOOKUP($A102,#REF!,14,0)),"") | O102: =IFERROR(IF(VLOOKUP($A102,#REF!,15,0)="","",VLOOKUP($A102,#REF!,15,0)),"")
A103: 4.30_ENTREGA_ENTREGADOR | D103: =IFERROR(VLOOKUP($A103,Banco!$A:$D,7,0),"") | E103: =IFERROR(VLOOKUP($A103,Banco!$A:$G,10,0),"-") -> - | F103: =IFERROR(RIGHT(VLOOKUP($E103,Banco!$G:$I,3,0),24),"") | G103: =IFERROR(IF(VLOOKUP($A103,#REF!,7,0)="","",VLOOKUP($A103,#REF!,7,0)),"") | H103: =IFERROR(IF(VLOOKUP($A103,#REF!,8,0)="","",VLOOKUP($A103,#REF!,8,0)),"") | I103: =IFERROR(IF(VLOOKUP($A103,#REF!,9,0)="","",VLOOKUP($A103,#REF!,9,0)),"") | J103: =IFERROR(IF(VLOOKUP($A103,#REF!,10,0)="","",VLOOKUP($A103,#REF!,10,0)),"") | K103: =IFERROR(IF(VLOOKUP($A103,#REF!,11,0)="","",VLOOKUP($A103,#REF!,11,0)),"") | L103: =IFERROR(IF(VLOOKUP($A103,#REF!,12,0)="","",VLOOKUP($A103,#REF!,12,0)),"") | M103: =IFERROR(IF(VLOOKUP($A103,#REF!,13,0)="","",VLOOKUP($A103,#REF!,13,0)),"") | N103: =IFERROR(IF(VLOOKUP($A103,#REF!,14,0)="","",VLOOKUP($A103,#REF!,14,0)),"") | O103: =IFERROR(IF(VLOOKUP($A103,#REF!,15,0)="","",VLOOKUP($A103,#REF!,15,0)),"")
A104: 5.30_ENTREGA_ENTREGADOR | B104: Autorizado | C104: ='PLJ30'!J15 -> 4 | D104: =IFERROR(VLOOKUP($A104,Banco!$A:$D,7,0),"") | E104: =IFERROR(VLOOKUP($A104,Banco!$A:$G,10,0),"-") -> - | F104: =IFERROR(RIGHT(VLOOKUP($E104,Banco!$G:$I,3,0),24),"") | G104: =IFERROR(IF(VLOOKUP($A104,#REF!,7,0)="","",VLOOKUP($A104,#REF!,7,0)),"") | H104: =IFERROR(IF(VLOOKUP($A104,#REF!,8,0)="","",VLOOKUP($A104,#REF!,8,0)),"") | I104: =IFERROR(IF(VLOOKUP($A104,#REF!,9,0)="","",VLOOKUP($A104,#REF!,9,0)),"") | J104: =IFERROR(IF(VLOOKUP($A104,#REF!,10,0)="","",VLOOKUP($A104,#REF!,10,0)),"") | K104: =IFERROR(IF(VLOOKUP($A104,#REF!,11,0)="","",VLOOKUP($A104,#REF!,11,0)),"") | L104: =IFERROR(IF(VLOOKUP($A104,#REF!,12,0)="","",VLOOKUP($A104,#REF!,12,0)),"") | M104: =IFERROR(IF(VLOOKUP($A104,#REF!,13,0)="","",VLOOKUP($A104,#REF!,13,0)),"") | N104: =IFERROR(IF(VLOOKUP($A104,#REF!,14,0)="","",VLOOKUP($A104,#REF!,14,0)),"") | O104: =IFERROR(IF(VLOOKUP($A104,#REF!,15,0)="","",VLOOKUP($A104,#REF!,15,0)),"")
B105: Ativos ---> | E105: =COUNTIFS(E100:E104,"<>-")-COUNTIFS(D100:D104,"Afastamento")-COUNTIFS(D100:D104,"Demitido") -> 0 | F105: =E105-C104 -> -4 | G105: =IFERROR(IF(VLOOKUP($A105,#REF!,7,0)="","",VLOOKUP($A105,#REF!,7,0)),"") | H105: =IFERROR(IF(VLOOKUP($A105,#REF!,8,0)="","",VLOOKUP($A105,#REF!,8,0)),"") | I105: =IFERROR(IF(VLOOKUP($A105,#REF!,9,0)="","",VLOOKUP($A105,#REF!,9,0)),"") | J105: =IFERROR(IF(VLOOKUP($A105,#REF!,10,0)="","",VLOOKUP($A105,#REF!,10,0)),"") | K105: =IFERROR(IF(VLOOKUP($A105,#REF!,11,0)="","",VLOOKUP($A105,#REF!,11,0)),"") | L105: =IFERROR(IF(VLOOKUP($A105,#REF!,12,0)="","",VLOOKUP($A105,#REF!,12,0)),"") | M105: =IFERROR(IF(VLOOKUP($A105,#REF!,13,0)="","",VLOOKUP($A105,#REF!,13,0)),"") | N105: =IFERROR(IF(VLOOKUP($A105,#REF!,14,0)="","",VLOOKUP($A105,#REF!,14,0)),"") | O105: =IFERROR(IF(VLOOKUP($A105,#REF!,15,0)="","",VLOOKUP($A105,#REF!,15,0)),"")
G106: =IFERROR(IF(VLOOKUP($A106,#REF!,7,0)="","",VLOOKUP($A106,#REF!,7,0)),"") | H106: =IFERROR(IF(VLOOKUP($A106,#REF!,8,0)="","",VLOOKUP($A106,#REF!,8,0)),"") | I106: =IFERROR(IF(VLOOKUP($A106,#REF!,9,0)="","",VLOOKUP($A106,#REF!,9,0)),"") | J106: =IFERROR(IF(VLOOKUP($A106,#REF!,10,0)="","",VLOOKUP($A106,#REF!,10,0)),"") | K106: =IFERROR(IF(VLOOKUP($A106,#REF!,11,0)="","",VLOOKUP($A106,#REF!,11,0)),"") | L106: =IFERROR(IF(VLOOKUP($A106,#REF!,12,0)="","",VLOOKUP($A106,#REF!,12,0)),"") | M106: =IFERROR(IF(VLOOKUP($A106,#REF!,13,0)="","",VLOOKUP($A106,#REF!,13,0)),"") | N106: =IFERROR(IF(VLOOKUP($A106,#REF!,14,0)="","",VLOOKUP($A106,#REF!,14,0)),"") | O106: =IFERROR(IF(VLOOKUP($A106,#REF!,15,0)="","",VLOOKUP($A106,#REF!,15,0)),"")
A107: Titulo | B107: CAMARA FRIA | D107: Status | E107: Nomes | F107: Horário Sistema | G107: =IFERROR(IF(VLOOKUP($A107,#REF!,7,0)="","",VLOOKUP($A107,#REF!,7,0)),"") | H107: =IFERROR(IF(VLOOKUP($A107,#REF!,8,0)="","",VLOOKUP($A107,#REF!,8,0)),"") | I107: =IFERROR(IF(VLOOKUP($A107,#REF!,9,0)="","",VLOOKUP($A107,#REF!,9,0)),"") | J107: =IFERROR(IF(VLOOKUP($A107,#REF!,10,0)="","",VLOOKUP($A107,#REF!,10,0)),"") | K107: =IFERROR(IF(VLOOKUP($A107,#REF!,11,0)="","",VLOOKUP($A107,#REF!,11,0)),"") | L107: =IFERROR(IF(VLOOKUP($A107,#REF!,12,0)="","",VLOOKUP($A107,#REF!,12,0)),"") | M107: =IFERROR(IF(VLOOKUP($A107,#REF!,13,0)="","",VLOOKUP($A107,#REF!,13,0)),"") | N107: =IFERROR(IF(VLOOKUP($A107,#REF!,14,0)="","",VLOOKUP($A107,#REF!,14,0)),"") | O107: =IFERROR(IF(VLOOKUP($A107,#REF!,15,0)="","",VLOOKUP($A107,#REF!,15,0)),"")
A108: 1.30_DEPOSITO_CAMARA FRIA | D108: =IFERROR(VLOOKUP($A108,Banco!$A:$D,7,0),"") | E108: =IFERROR(VLOOKUP($A108,Banco!$A:$G,10,0),"-") -> - | F108: =IFERROR(RIGHT(VLOOKUP($E108,Banco!$G:$I,3,0),24),"") | G108: =IFERROR(IF(VLOOKUP($A108,#REF!,7,0)="","",VLOOKUP($A108,#REF!,7,0)),"") | H108: =IFERROR(IF(VLOOKUP($A108,#REF!,8,0)="","",VLOOKUP($A108,#REF!,8,0)),"") | I108: =IFERROR(IF(VLOOKUP($A108,#REF!,9,0)="","",VLOOKUP($A108,#REF!,9,0)),"") | J108: =IFERROR(IF(VLOOKUP($A108,#REF!,10,0)="","",VLOOKUP($A108,#REF!,10,0)),"") | K108: =IFERROR(IF(VLOOKUP($A108,#REF!,11,0)="","",VLOOKUP($A108,#REF!,11,0)),"") | L108: =IFERROR(IF(VLOOKUP($A108,#REF!,12,0)="","",VLOOKUP($A108,#REF!,12,0)),"") | M108: =IFERROR(IF(VLOOKUP($A108,#REF!,13,0)="","",VLOOKUP($A108,#REF!,13,0)),"") | N108: =IFERROR(IF(VLOOKUP($A108,#REF!,14,0)="","",VLOOKUP($A108,#REF!,14,0)),"") | O108: =IFERROR(IF(VLOOKUP($A108,#REF!,15,0)="","",VLOOKUP($A108,#REF!,15,0)),"")
A109: 2.30_DEPOSITO_CAMARA FRIA | D109: =IFERROR(VLOOKUP($A109,Banco!$A:$D,7,0),"") | E109: =IFERROR(VLOOKUP($A109,Banco!$A:$G,10,0),"-") -> - | F109: =IFERROR(RIGHT(VLOOKUP($E109,Banco!$G:$I,3,0),24),"") | G109: =IFERROR(IF(VLOOKUP($A109,#REF!,7,0)="","",VLOOKUP($A109,#REF!,7,0)),"") | H109: =IFERROR(IF(VLOOKUP($A109,#REF!,8,0)="","",VLOOKUP($A109,#REF!,8,0)),"") | I109: =IFERROR(IF(VLOOKUP($A109,#REF!,9,0)="","",VLOOKUP($A109,#REF!,9,0)),"") | J109: =IFERROR(IF(VLOOKUP($A109,#REF!,10,0)="","",VLOOKUP($A109,#REF!,10,0)),"") | K109: =IFERROR(IF(VLOOKUP($A109,#REF!,11,0)="","",VLOOKUP($A109,#REF!,11,0)),"") | L109: =IFERROR(IF(VLOOKUP($A109,#REF!,12,0)="","",VLOOKUP($A109,#REF!,12,0)),"") | M109: =IFERROR(IF(VLOOKUP($A109,#REF!,13,0)="","",VLOOKUP($A109,#REF!,13,0)),"") | N109: =IFERROR(IF(VLOOKUP($A109,#REF!,14,0)="","",VLOOKUP($A109,#REF!,14,0)),"") | O109: =IFERROR(IF(VLOOKUP($A109,#REF!,15,0)="","",VLOOKUP($A109,#REF!,15,0)),"")
A110: 3.30_DEPOSITO_CAMARA FRIA | D110: =IFERROR(VLOOKUP($A110,Banco!$A:$D,7,0),"") | E110: =IFERROR(VLOOKUP($A110,Banco!$A:$G,10,0),"-") -> - | F110: =IFERROR(RIGHT(VLOOKUP($E110,Banco!$G:$I,3,0),24),"") | G110: =IFERROR(IF(VLOOKUP($A110,#REF!,7,0)="","",VLOOKUP($A110,#REF!,7,0)),"") | H110: =IFERROR(IF(VLOOKUP($A110,#REF!,8,0)="","",VLOOKUP($A110,#REF!,8,0)),"") | I110: =IFERROR(IF(VLOOKUP($A110,#REF!,9,0)="","",VLOOKUP($A110,#REF!,9,0)),"") | J110: =IFERROR(IF(VLOOKUP($A110,#REF!,10,0)="","",VLOOKUP($A110,#REF!,10,0)),"") | K110: =IFERROR(IF(VLOOKUP($A110,#REF!,11,0)="","",VLOOKUP($A110,#REF!,11,0)),"") | L110: =IFERROR(IF(VLOOKUP($A110,#REF!,12,0)="","",VLOOKUP($A110,#REF!,12,0)),"") | M110: =IFERROR(IF(VLOOKUP($A110,#REF!,13,0)="","",VLOOKUP($A110,#REF!,13,0)),"") | N110: =IFERROR(IF(VLOOKUP($A110,#REF!,14,0)="","",VLOOKUP($A110,#REF!,14,0)),"") | O110: =IFERROR(IF(VLOOKUP($A110,#REF!,15,0)="","",VLOOKUP($A110,#REF!,15,0)),"")
A111: 4.30_DEPOSITO_CAMARA FRIA | B111: Autorizado | C111: ='PLJ30'!L15 -> 1 | D111: =IFERROR(VLOOKUP($A111,Banco!$A:$D,7,0),"") | E111: =IFERROR(VLOOKUP($A111,Banco!$A:$G,10,0),"-") -> - | F111: =IFERROR(RIGHT(VLOOKUP($E111,Banco!$G:$I,3,0),24),"") | G111: =IFERROR(IF(VLOOKUP($A111,#REF!,7,0)="","",VLOOKUP($A111,#REF!,7,0)),"") | H111: =IFERROR(IF(VLOOKUP($A111,#REF!,8,0)="","",VLOOKUP($A111,#REF!,8,0)),"") | I111: =IFERROR(IF(VLOOKUP($A111,#REF!,9,0)="","",VLOOKUP($A111,#REF!,9,0)),"") | J111: =IFERROR(IF(VLOOKUP($A111,#REF!,10,0)="","",VLOOKUP($A111,#REF!,10,0)),"") | K111: =IFERROR(IF(VLOOKUP($A111,#REF!,11,0)="","",VLOOKUP($A111,#REF!,11,0)),"") | L111: =IFERROR(IF(VLOOKUP($A111,#REF!,12,0)="","",VLOOKUP($A111,#REF!,12,0)),"") | M111: =IFERROR(IF(VLOOKUP($A111,#REF!,13,0)="","",VLOOKUP($A111,#REF!,13,0)),"") | N111: =IFERROR(IF(VLOOKUP($A111,#REF!,14,0)="","",VLOOKUP($A111,#REF!,14,0)),"") | O111: =IFERROR(IF(VLOOKUP($A111,#REF!,15,0)="","",VLOOKUP($A111,#REF!,15,0)),"")
B112: Ativos ---> | E112: =COUNTIFS(E108:E110,"<>-")-COUNTIFS(D108:D110,"Afastamento")-COUNTIFS(D108:D110,"Demitido") -> 0 | F112: =E112-C110 -> 0 | G112: =IFERROR(IF(VLOOKUP($A112,#REF!,7,0)="","",VLOOKUP($A112,#REF!,7,0)),"") | H112: =IFERROR(IF(VLOOKUP($A112,#REF!,8,0)="","",VLOOKUP($A112,#REF!,8,0)),"") | I112: =IFERROR(IF(VLOOKUP($A112,#REF!,9,0)="","",VLOOKUP($A112,#REF!,9,0)),"") | J112: =IFERROR(IF(VLOOKUP($A112,#REF!,10,0)="","",VLOOKUP($A112,#REF!,10,0)),"") | K112: =IFERROR(IF(VLOOKUP($A112,#REF!,11,0)="","",VLOOKUP($A112,#REF!,11,0)),"") | L112: =IFERROR(IF(VLOOKUP($A112,#REF!,12,0)="","",VLOOKUP($A112,#REF!,12,0)),"") | M112: =IFERROR(IF(VLOOKUP($A112,#REF!,13,0)="","",VLOOKUP($A112,#REF!,13,0)),"") | N112: =IFERROR(IF(VLOOKUP($A112,#REF!,14,0)="","",VLOOKUP($A112,#REF!,14,0)),"") | O112: =IFERROR(IF(VLOOKUP($A112,#REF!,15,0)="","",VLOOKUP($A112,#REF!,15,0)),"")

Sheet PLJ30
C3: Loja 30 | U3: 2025 | X3: Açougue
U4: Janeiro | V4: ='Hist LJ08'!B20 -> 3219511.4 | X4: Venda Ano 2025 | Y4: =SUMIFS('Hist LJ08'!$N:$N,'Hist LJ08'!$P:$P,"Açougue") -> 5763222.3
C5: Venda 2025 | E5: Venda R$ Funcionarios | H5: Gerente | P5: Abertura da loja | U5: Fevereiro | V5: ='Hist LJ08'!C20 -> 3101720.3 | X5: Media mês | Y5: =Y4/12 -> 480268.53
C6: =V16 -> 40395067 | E6: 43000 | U6: Março | V6: ='Hist LJ08'!D20 -> 3370344.1 | X6: Venda Por QL | Y6: =Y5/H35 -> #DIV/0!
H7: 2 | U7: Abril | V7: ='Hist LJ08'!E20 -> 3379026.8 | X7: Meta | Y7: 75000
C8: Media 12 mêses | E8: Proposta Quant | P8: Seg a Sab | R8: Domingos | U8: Maio | V8: ='Hist LJ08'!F20 -> 3349745.2
C9: =C6/12 -> 3366255.5 | E9: =C9/E6 -> 78.285013 | H9: ENCARREGADO | P9: 08:00 as 21:00 | R9: 08:00 as 20:00 | U9: Junho | V9: ='Hist LJ08'!G20 -> 3073146 | X9: Hortifrut
U10: Julho | V10: ='Hist LJ08'!H20 -> 3277172.2 | X10: Venda Ano 2025 | Y10: =SUMIFS('Hist LJ08'!$N:$N,'Hist LJ08'!$P:$P,"Hortifruti") -> 4834607.6
H11: 1 | U11: Agosto | V11: ='Hist LJ08'!I20 -> 3265256.8 | X11: Media mês | Y11: =Y10/12 -> 402883.97
U12: Setembro | V12: ='Hist LJ08'!J20 -> 3058804 | X12: Venda Por QL | Y12: =Y11/J35 -> #DIV/0!
U13: Outubro | V13: ='Hist LJ08'!K20 -> 3373792.9 | X13: Meta | Y13: 80000
H14: AUXILIAR | J14: ENTREGADOR | L14: CAMARA FRIA | N14: EMPILHADEIRA | U14: Novembro | V14: ='Hist LJ08'!L20 -> 3601251.9
H15: 30 | J15: 4 | L15: 1 | N15: 4 | U15: Dezenbro | V15: ='Hist LJ08'!M20 -> 4325295.1 | X15: Confeitaria
U16: Total | V16: ='Hist LJ08'!N20 -> 40395067 | X16: Venda Ano 2025 | Y16: =SUMIFS('Hist LJ08'!$N:$N,'Hist LJ08'!$P:$P,"Confeitaria") -> 608704.17
H17: CONFERENTE | J17: TROCAS | L17: TROCAS | U17: Media 12 meses | V17: =V16/12 -> 3366255.5 | X17: Media mês | Y17: =Y16/12 -> 50725.347
H18: 15 | J18: 3 | L18: 3 | U18: Media por QL | V18: =V17/43000 -> 78.285013 | X18: Venda Por QL | Y18: =Y17/O35 -> #DIV/0!
X19: Meta | Y19: 26000
U21: Frios / Congelados / Laticinios / Peix | X21: Padaria
U22: Venda Ano 2025 | V22: =SUMIFS('Hist LJ08'!$N:$N,'Hist LJ08'!$P:$P,"Frios") -> 5713222.6 | X22: Venda Ano 2025 | Y22: =SUMIFS('Hist LJ08'!$N:$N,'Hist LJ08'!$P:$P,"Padaria") -> 1850270.9
U23: Media mês | V23: =V22/12 -> 476101.89 | X23: Media mês | Y23: =Y22/12 -> 154189.24
U24: Venda Por QL | V24: =V23/L35 -> #DIV/0! | X24: Venda Por QL | Y24: =Y23/N35 -> #DIV/0!
U25: Meta | V25: 80000 | X25: Meta | Y25: 16000
U27: Loja Total | X27: Rotisseria
U28: Venda Ano 2025 | V28: =SUMIFS('Hist LJ08'!$N:$N,'Hist LJ08'!$P:$P,"Loja") -> 20800045 | X28: Venda Ano 2025 | Y28: =SUMIFS('Hist LJ08'!$N:$N,'Hist LJ08'!$P:$P,"Rotisseria") -> 824993.41
U29: Media mês | V29: =V28/12 -> 1733337.1 | X29: Media mês | Y29: =Y28/12 -> 68749.451
U30: Venda Por QL | V30: =V29/(E35+R35) -> #DIV/0! | X30: Venda Por QL | Y30: =IFERROR(Y29/P35,0) -> 0
U31: Meta | V31: 160000 | X31: Meta | Y31: 25000
U33: Frente Caixa | X33: Prod Alimentos
U34: Venda Ano 2025 | V34: =SUMIFS('Hist LJ08'!$N:$N,'Hist LJ08'!$P:$P,"Loja") -> 20800045 | X34: Venda Ano 2025 | Y34: =Y28+Y22+Y16 -> 3283968.5
U35: Media mês | V35: =V34/12 -> 1733337.1 | X35: Media mês | Y35: =Y34/12 -> 273664.04
U36: Venda Por QL | V36: =V35/C35 -> #DIV/0! | X36: Venda Por QL | Y36: =Y35/SUM(N35:P35) -> #DIV/0!
U37: Meta | V37: 138000 | X37: Meta | Y37: 21000

Sheet Banco
A1: Loja | B1: Dept | C1: Função | D1: Situação | E1: Filial | F1: Cadastro | G1: Nome | H1: Escala | I1: Descrição (Escala) | J1: Situação | K1: Data Afastamento | L1: Nascimento | M1: Admissão | N1: CPF | O1: Gestão do Ponto Lite | P1: Descrição (Gestão do Ponto Lite) | Q1: Cód. Operação | R1: Código Local | S1: Descrição do Local | T1: Posição do Local
A2: =IFERROR(VLOOKUP($G2,Conf!$B:$C,2,0),E2) -> 1 | B2: =IF(D2="Inativo","Inativo",IFERROR(VLOOKUP($G2,Conf!$O:$Q,2,0),VLOOKUP($S2,Conf!$K:$M,2,0))) -> AÇOUGUE | C2: =IF(D2="Inativo","Inativo",IFERROR(VLOOKUP($G2,Conf!$O:$Q,3,0),IFERROR(VLOOKUP($G2,Conf!$E:$F,2,0),VLOOKUP($S2,Conf!$K:$M,3,0)))) -> AÇOUGUEIRO | D2: =IFERROR(IF(TODAY()-K2>365,"Inativo",IF(J2=2,"Férias",IF(J2=7,"Demitido","Afastamento"))),VLOOKUP(J2,Conf!$H:$I,2,0)) -> Ativos | E2: 1 | F2: 1800 | G2: DAIANE CONCEICAO DOS SANTOS | I2: SG-SB 07:00-12:00 14:00-16:20 | J2: 1 | K2: - | M2: 44629 | S2: ACOUGUEIRO (A) - ACOUGUE
A3: =IFERROR(VLOOKUP($G3,Conf!$B:$C,2,0),E3) -> 1 | B3: =IF(D3="Inativo","Inativo",IFERROR(VLOOKUP($G3,Conf!$O:$Q,2,0),VLOOKUP($S3,Conf!$K:$M,2,0))) -> AÇOUGUE | C3: =IF(D3="Inativo","Inativo",IFERROR(VLOOKUP($G3,Conf!$O:$Q,3,0),IFERROR(VLOOKUP($G3,Conf!$E:$F,2,0),VLOOKUP($S3,Conf!$K:$M,3,0)))) -> AÇOUGUEIRO | D3: =IFERROR(IF(TODAY()-K3>365,"Inativo",IF(J3=2,"Férias",IF(J3=7,"Demitido","Afastamento"))),VLOOKUP(J3,Conf!$H:$I,2,0)) -> Férias | E3: 1 | F3: 1649 | G3: DOUGLAS DA SILVA FERREIRA | I3: SG-SB 07:50-11:30 13:30-17:10 | J3: 2 | K3: 01/10/2026 | M3: 44186 | S3: ACOUGUEIRO (A) - ACOUGUE
A4: =IFERROR(VLOOKUP($G4,Conf!$B:$C,2,0),E4) -> 1 | B4: =IF(D4="Inativo","Inativo",IFERROR(VLOOKUP($G4,Conf!$O:$Q,2,0),VLOOKUP($S4,Conf!$K:$M,2,0))) -> AÇOUGUE | C4: =IF(D4="Inativo","Inativo",IFERROR(VLOOKUP($G4,Conf!$O:$Q,3,0),IFERROR(VLOOKUP($G4,Conf!$E:$F,2,0),VLOOKUP($S4,Conf!$K:$M,3,0)))) -> AÇOUGUEIRO | D4: =IFERROR(IF(TODAY()-K4>365,"Inativo",IF(J4=2,"Férias",IF(J4=7,"Demitido","Afastamento"))),VLOOKUP(J4,Conf!$H:$I,2,0)) -> Ativos | E4: 1 | F4: 58 | G4: ILSON RIBEIRO | I4: SG-SB 12:00-15:00 17:00-21:20 | J4: 1 | K4: - | M4: 46303 | S4: ACOUGUEIRO (A) - PEREC E FIAMB - LOJA 1
A5: =IFERROR(VLOOKUP($G5,Conf!$B:$C,2,0),E5) -> 1 | B5: =IF(D5="Inativo","Inativo",IFERROR(VLOOKUP($G5,Conf!$O:$Q,2,0),VLOOKUP($S5,Conf!$K:$M,2,0))) -> AÇOUGUE | C5: =IF(D5="Inativo","Inativo",IFERROR(VLOOKUP($G5,Conf!$O:$Q,3,0),IFERROR(VLOOKUP($G5,Conf!$E:$F,2,0),VLOOKUP($S5,Conf!$K:$M,3,0)))) -> AÇOUGUEIRO | D5: =IFERROR(IF(TODAY()-K5>365,"Inativo",IF(J5=2,"Férias",IF(J5=7,"Demitido","Afastamento"))),VLOOKUP(J5,Conf!$H:$I,2,0)) -> Demitido | E5: 1 | F5: 127 | G5: MARIANA DIAS BERGAMIN GONCALVES | I5: SG-SB 07:00-12:00 14:00-16:20 | J5: 7 | K5: 01/10/2026 | M5: 45511 | S5: ACOUGUEIRO (A) - PEREC E FIAMB - LOJA 1
A6: =IFERROR(VLOOKUP($G6,Conf!$B:$C,2,0),E6) -> 1 | B6: =IF(D6="Inativo","Inativo",IFERROR(VLOOKUP($G6,Conf!$O:$Q,2,0),VLOOKUP($S6,Conf!$K:$M,2,0))) -> AÇOUGUE | C6: =IF(D6="Inativo","Inativo",IFERROR(VLOOKUP($G6,Conf!$O:$Q,3,0),IFERROR(VLOOKUP($G6,Conf!$E:$F,2,0),VLOOKUP($S6,Conf!$K:$M,3,0)))) -> AÇOUGUEIRO | D6: =IFERROR(IF(TODAY()-K6>365,"Inativo",IF(J6=2,"Férias",IF(J6=7,"Demitido","Afastamento"))),VLOOKUP(J6,Conf!$H:$I,2,0)) -> Ativos | E6: 1 | F6: 187 | G6: SONIA ALVES BARRETO BARBALARGA | I6: SG-SB 07:50-11:30 13:30-17:10 | J6: 1 | K6: - | M6: 39412 | S6: ACOUGUEIRO (A) - ACOUGUE
A7: =IFERROR(VLOOKUP($G7,Conf!$B:$C,2,0),E7) -> 1 | B7: =IF(D7="Inativo","Inativo",IFERROR(VLOOKUP($G7,Conf!$O:$Q,2,0),VLOOKUP($S7,Conf!$K:$M,2,0))) -> AÇOUGUE | C7: =IF(D7="Inativo","Inativo",IFERROR(VLOOKUP($G7,Conf!$O:$Q,3,0),IFERROR(VLOOKUP($G7,Conf!$E:$F,2,0),VLOOKUP($S7,Conf!$K:$M,3,0)))) -> AÇOUGUEIRO | D7: =IFERROR(IF(TODAY()-K7>365,"Inativo",IF(J7=2,"Férias",IF(J7=7,"Demitido","Afastamento"))),VLOOKUP(J7,Conf!$H:$I,2,0)) -> Ativos | E7: 1 | F7: 23 | G7: VANDERSON MELO DE AZEVEDO | I7: SG-SB 12:00-15:00 17:00-21:20 | J7: 1 | K7: - | M7: 46178 | S7: ACOUGUEIRO (A) - PEREC E FIAMB - LOJA 1
A8: =IFERROR(VLOOKUP($G8,Conf!$B:$C,2,0),E8) -> 1 | B8: =IF(D8="Inativo","Inativo",IFERROR(VLOOKUP($G8,Conf!$O:$Q,2,0),VLOOKUP($S8,Conf!$K:$M,2,0))) -> AÇOUGUE | C8: =IF(D8="Inativo","Inativo",IFERROR(VLOOKUP($G8,Conf!$O:$Q,3,0),IFERROR(VLOOKUP($G8,Conf!$E:$F,2,0),VLOOKUP($S8,Conf!$K:$M,3,0)))) -> BALCONISTA | D8: =IFERROR(IF(TODAY()-K8>365,"Inativo",IF(J8=2,"Férias",IF(J8=7,"Demitido","Afastamento"))),VLOOKUP(J8,Conf!$H:$I,2,0)) -> Demitido | E8: 1 | F8: 46 | G8: ALEXANDRE AFONSO DA SILVA | I8: SG-SB 12:00-15:00 17:00-21:20 | J8: 7 | K8: 08/10/2026 | M8: 46274 | S8: BALCONISTA DE ACOUGUE - PEREC E FIAMB - LOJA 1
A9: =IFERROR(VLOOKUP($G9,Conf!$B:$C,2,0),E9) -> 1 | B9: =IF(D9="Inativo","Inativo",IFERROR(VLOOKUP($G9,Conf!$O:$Q,2,0),VLOOKUP($S9,Conf!$K:$M,2,0))) -> AÇOUGUE | C9: =IF(D9="Inativo","Inativo",IFERROR(VLOOKUP($G9,Conf!$O:$Q,3,0),IFERROR(VLOOKUP($G9,Conf!$E:$F,2,0),VLOOKUP($S9,Conf!$K:$M,3,0)))) -> BALCONISTA | D9: =IFERROR(IF(TODAY()-K9>365,"Inativo",IF(J9=2,"Férias",IF(J9=7,"Demitido","Afastamento"))),VLOOKUP(J9,Conf!$H:$I,2,0)) -> Demitido | E9: 1 | F9: 35 | G9: GABRIEL RODRIGO FRANCISCO DE LIMA | I9: SG-SB 12:00-15:00 17:00-21:20 | J9: 7 | K9: 09/09/2026 | M9: 46245 | S9: BALCONISTA DE ACOUGUE - PEREC E FIAMB - LOJA 1
A10: =IFERROR(VLOOKUP($G10,Conf!$B:$C,2,0),E10) -> 1 | B10: =IF(D10="Inativo","Inativo",IFERROR(VLOOKUP($G10,Conf!$O:$Q,2,0),VLOOKUP($S10,Conf!$K:$M,2,0))) -> AÇOUGUE | C10: =IF(D10="Inativo","Inativo",IFERROR(VLOOKUP($G10,Conf!$O:$Q,3,0),IFERROR(VLOOKUP($G10,Conf!$E:$F,2,0),VLOOKUP($S10,Conf!$K:$M,3,0)))) -> BALCONISTA | D10: =IFERROR(IF(TODAY()-K10>365,"Inativo",IF(J10=2,"Férias",IF(J10=7,"Demitido","Afastamento"))),VLOOKUP(J10,Conf!$H:$I,2,0)) -> Ativos | E10: 1 | F10: 41 | G10: MOISES ALBERTO FLORES TOVAR | I10: SG-SB 12:00-15:00 17:00-21:20 | J10: 1 | K10: - | M10: 46252 | S10: BALCONISTA DE ACOUGUE - PEREC E FIAMB - LOJA 1
A11: =IFERROR(VLOOKUP($G11,Conf!$B:$C,2,0),E11) -> 1 | B11: =IF(D11="Inativo","Inativo",IFERROR(VLOOKUP($G11,Conf!$O:$Q,2,0),VLOOKUP($S11,Conf!$K:$M,2,0))) -> AÇOUGUE | C11: =IF(D11="Inativo","Inativo",IFERROR(VLOOKUP($G11,Conf!$O:$Q,3,0),IFERROR(VLOOKUP($G11,Conf!$E:$F,2,0),VLOOKUP($S11,Conf!$K:$M,3,0)))) -> BALCONISTA | D11: =IFERROR(IF(TODAY()-K11>365,"Inativo",IF(J11=2,"Férias",IF(J11=7,"Demitido","Afastamento"))),VLOOKUP(J11,Conf!$H:$I,2,0)) -> Ativos | E11: 1 | F11: 51 | G11: NIXON THOMAS | I11: SG-SB 13:00-16:00 17:10-21:30 | J11: 1 | K11: - | M11: 46287 | S11: BALCONISTA DE ACOUGUE - PEREC E FIAMB - LOJA 1
A12: =IFERROR(VLOOKUP($G12,Conf!$B:$C,2,0),E12) -> 1 | B12: =IF(D12="Inativo","Inativo",IFERROR(VLOOKUP($G12,Conf!$O:$Q,2,0),VLOOKUP($S12,Conf!$K:$M,2,0))) -> AÇOUGUE | C12: =IF(D12="Inativo","Inativo",IFERROR(VLOOKUP($G12,Conf!$O:$Q,3,0),IFERROR(VLOOKUP($G12,Conf!$E:$F,2,0),VLOOKUP($S12,Conf!$K:$M,3,0)))) -> DESOSSADOR | D12: =IFERROR(IF(TODAY()-K12>365,"Inativo",IF(J12=2,"Férias",IF(J12=7,"Demitido","Afastamento"))),VLOOKUP(J12,Conf!$H:$I,2,0)) -> Ativos | E12: 1 | F12: 43 | G12: FLAVIO DE SOUZA NOGUEIRA | I12: SG-SB 12:00-15:00 17:00-21:20 | J12: 1 | K12: - | M12: 46258 | S12: ACOUGUEIRO (A) DESOSSADOR - PEREC E FIAMB - LOJA 1
A13: =IFERROR(VLOOKUP($G13,Conf!$B:$C,2,0),E13) -> 1 | B13: =IF(D13="Inativo","Inativo",IFERROR(VLOOKUP($G13,Conf!$O:$Q,2,0),VLOOKUP($S13,Conf!$K:$M,2,0))) -> AÇOUGUE | C13: =IF(D13="Inativo","Inativo",IFERROR(VLOOKUP($G13,Conf!$O:$Q,3,0),IFERROR(VLOOKUP($G13,Conf!$E:$F,2,0),VLOOKUP($S13,Conf!$K:$M,3,0)))) -> DESOSSADOR | D13: =IFERROR(IF(TODAY()-K13>365,"Inativo",IF(J13=2,"Férias",IF(J13=7,"Demitido","Afastamento"))),VLOOKUP(J13,Conf!$H:$I,2,0)) -> Ativos | E13: 1 | F13: 633 | G13: JOSE ANTONIO DE ALMEIDA | I13: SG-SB 12:00-15:00 17:00-21:20 | J13: 1 | K13: - | M13: 41229 | S13: ACOUGUEIRO (A) DESOSSADOR - ACOUGUE
... A943: =IFERROR(VLOOKUP($G943,Conf!$B:$C,2,0),E943) -> 50 | B943: =IF(D943="Inativo","Inativo",IFERROR(VLOOKUP($G943,Conf!$O:$Q,2,0),VLOOKUP($S943,Conf!$K:$M,2,0))) -> VENDAS | C943: =IF(D943="Inativo","Inativo",IFERROR(VLOOKUP($G943,Conf!$O:$Q,3,0),IFERROR(VLOOKUP($G943,Conf!$E:$F,2,0),VLOOKUP($S943,Conf!$K:$M,3,0)))) -> VENDEDOR | D943: =IFERROR(IF(TODAY()-K943>365,"Inativo",IF(J943=2,"Férias",IF(J943=7,"Demitido","Afastamento"))),VLOOKUP(J943,Conf!$H:$I,2,0)) -> Ativos | E943: 50 | F943: 10 | G943: SILVIO TELLES DA SILVA NETTO | I943: SG,QA,SX 02-10:30 TR,QI,SB... | J943: 1 | K943: - | M943: 44593 | S943: VENDEDOR INTERNO - VENDAS

Sheet Conf
B2: Exceções Loja | E2: Exceções Subgerente | O2: Exceções Cargo
B3: Nome | C3: Loja | E3: Nome | F3: Função | H3: Cód | I3: Legenda | K3: Descrição Cargo | L3: Dept | M3: Função | O3: Nome | P3: Dept | Q3: Função
B4: ANDREIA QUINTANA BERTALLIA | C4: 1 | E4: DIEGO UMBERTO DE MARI | F4: SUBGERENTE | H4: 1 | I4: Ativos | K4: ACOUGUEIRO - ACOUGUE | L4: AÇOUGUE | M4: AÇOUGUEIRO | O4: WILDES VIEIRA DA SILVA | P4: HORTIFRUTI | Q4: REPOSITOR
B5: JOSE AUGUSTO DA ROSA | C5: 7 | E5: CRISTIANO VALLE AFONSO | F5: SUBGERENTE | H5: 2 | I5: Férias | K5: ACOUGUEIRO (A) - ACOUGUE | L5: AÇOUGUE | M5: AÇOUGUEIRO | O5: SERGIO RAUL GONZALEZ ALARCON | P5: HORTIFRUTI | Q5: REPOSITOR
B6: FERNANDO CARLOS SIAM | C6: 3 | E6: WANDO DE SOUZA MARTINS | F6: SUBGERENTE | H6: 3 | I6: Auxilio Doença | K6: ACOUGUEIRO (A) - PEREC E FIAMB - LOJA 1 | L6: AÇOUGUE | M6: AÇOUGUEIRO | O6: REINEL VERA PERIANA | P6: HORTIFRUTI | Q6: REPOSITOR
B7: CRISTIANO VALLE AFONSO | C7: 1 | E7: ANDREIA QUINTANA BERTALLIA | F7: SUBGERENTE | H7: 4 | I7: Afastamento Acidente Trabaho | K7: ACOUGUEIRO (A) - PEREC E FIAMB - LOJA 2 | L7: AÇOUGUE | M7: AÇOUGUEIRO | O7: YONERKI ALBERTO GONZALEZ GUIROLA | P7: FRIOS | Q7: REPOSITOR
B8: CEZAR PESSOA DA SILVA | C8: 2 | E8: CATIA ROSANA DE OLIVEIRA | F8: SUBGERENTE | H8: 5 | I8: Afastamento Serviço Militar | K8: ACOUGUEIRO (A) - PEREC E FIAMB - LOJA 3 | L8: AÇOUGUE | M8: AÇOUGUEIRO | O8: ADRIANA BEATRIZ LOPEZ | P8: ROTISSERIA | Q8: AUXILIAR
B9: FABIO MILAN | C9: 2 | E9: CEZAR PESSOA DA SILVA | F9: SUBGERENTE | H9: 6 | I9: Licença Maternidade | K9: ACOUGUEIRO (A) - PEREC E FIAMB - LOJA 4 | L9: AÇOUGUE | M9: AÇOUGUEIRO | O9: JOSILAINE APARECIDA MARCIA DA SILVA | P9: ROTISSERIA | Q9: AUXILIAR
B10: NIVALDO DA SILVA PEREIRA NETO | C10: 3 | E10: ERITON BARBOSA | F10: SUBGERENTE | H10: 7 | I10: Demitido | K10: ACOUGUEIRO (A) - PERECIVEIS E FIAMBRERIA - LOJA 07 | L10: AÇOUGUE | M10: AÇOUGUEIRO | O10: GUVELINE CLAIRILUS | P10: CONFEITARIA | Q10: AUXILIAR
B11: GUSTAVO FANTINI MOLINARI | C11: 30 | E11: RICARDO BISPO FERREIRA | F11: SUBGERENTE | H11: 14 | I11: Atestado | K11: ACOUGUEIRO (A) - PERECIVEIS E FIAMBRERIA - LOJA 08 | L11: AÇOUGUE | M11: AÇOUGUEIRO | O11: INES ALYPIO DA SILVA | P11: CONFEITARIA | Q11: AUXILIAR
B12: ANA PAULA PIEROBOM DELPHINO | C12: 30 | E12: JOSE AUGUSTO DA ROSA | F12: SUBGERENTE | H12: 22 | I12: Aposentadoria | K12: ACOUGUEIRO (A) DESOSSADOR - ACOUGUE | L12: AÇOUGUE | M12: DESOSSADOR | O12: MARINES ALVES PEREIRA | P12: CONFEITARIA | Q12: CONFEITEIRO(A)
B13: ADEMILTO MOLINARI | C13: 30 | E13: JOSE MANUEL RENGEL QUINTANA | F13: SUBGERENTE | H13: 109 | I13: Acompanhamento Filho Menor | K13: ACOUGUEIRO (A) DESOSSADOR - PEREC E FIAMB - LOJA 1 | L13: AÇOUGUE | M13: DESOSSADOR | O13: CLEUNICE DA SILVA | P13: HORTIFRUTI | Q13: REPOSITOR
B14: ADEMIR MOLINARI | C14: 30 | E14: VAGNER GALLINA | F14: SUPERVISOR | H14: 318 | I14: Saída Autorizada | K14: ACOUGUEIRO (A) DESOSSADOR - PEREC E FIAMB - LOJA 2 | L14: AÇOUGUE | M14: DESOSSADOR | O14: PAULO CESAR RAMOS DIAS | P14: LOJA | Q14: REPOSITOR
B15: ADRIANO MOLINARI | C15: 30 | E15: VINICIUS DE OLIVEIRA | F15: SUBGERENTE | K15: ACOUGUEIRO (A) DESOSSADOR - PEREC E FIAMB - LOJA 3 | L15: AÇOUGUE | M15: DESOSSADOR | O15: CLAUSE MARY DUARTE | P15: PADARIA | Q15: ATENDENTE
B16: ELAINE MOLINARI | C16: 30 | K16: ACOUGUEIRO (A) DESOSSADOR - PEREC E FIAMB - LOJA 4 | L16: AÇOUGUE | M16: DESOSSADOR | O16: CLAUDINEIA GONÇALVES DOS SANTOS | P16: VENDAS | Q16: VENDEDOR
B17: ELIANE MOLINARI SILVEIRA | C17: 30 | K17: ACOUGUEIRO (A) DESOSSADOR - PERECIVEIS E FIAMBRERIA - LJ 07 | L17: AÇOUGUE | M17: DESOSSADOR | O17: LUCIANA DEL CONTI BRANCO | P17: ADMINISTRATIVO | Q17: FATURISTA
B18: NEIMAR MOLINARI | C18: 30 | K18: ACOUGUEIRO (A) DESOSSADOR - PERECIVEIS E FIAMBRERIA - LOJA 0 | L18: AÇOUGUE | M18: DESOSSADOR | O18: MARIA APARECIDA BATISTA DOS SANTOS | P18: PADARIA | Q18: AUXILIAR
B19: VAGNER GALLINA | C19: 30 | K19: ACOUGUEIRO DESOSSADOR - ACOUGUE | L19: AÇOUGUE | M19: DESOSSADOR | O19: VALDINEI TEIXEIRA | P19: FRENTE DE CAIXA | Q19: EMPACOTADOR
B20: FRANCIELE RODRIGUES DOMINGUES | C20: 30 | K20: AGENTE DE PREVENCAO DE PERDAS | L20: ADMINISTRATIVO | M20: PREVENÇÃO | O20: LUCAS GRACIANO BARBOZA | P20: FRENTE DE CAIXA | Q20: EMPACOTADOR
B21: PABLO MOLINARI | C21: 30 | K21: AGENTE DE PREVENCAO DE PERDAS - LOJA - LOJA 08 | L21: ADMINISTRATIVO | M21: PREVENÇÃO | O21: ADRIANA APARECIDA SABINO | P21: ROTISSERIA | Q21: AUXILIAR
B22: MATHEUS SANTOS MOURA | C22: 5 | K22: AGENTE DE PREVENCAO EM PERDAS | L22: ADMINISTRATIVO | M22: PREVENÇÃO
B23: MAURICIO VALLE AFONSO | C23: 4 | K23: AGENTE EM PREVENCAO DE PERDAS | L23: ADMINISTRATIVO | M23: PREVENÇÃO
B24: JOSÉ MARCIO | C24: 6 | K24: AGENTE EM PREVENCAO DE PERDAS - LOJA 1 | L24: ADMINISTRATIVO | M24: PREVENÇÃO
B25: JOSÉ INACIO | C25: 30 | K25: AGENTE EM PREVENÇAO DE PERDAS - LOJA 1 | L25: ADMINISTRATIVO | M25: PREVENÇÃO
B26: MATHEUS ABRANTES | C26: 30 | K26: AJUDANTE DE PINTOR | L26: OPERACIONAL | M26: PINTOR
B27: ADRIANA WEIZEL | C27: 30 | K27: ANALISTA DE DESEMPENHO | L27: ADMINISTRATIVO | M27: ANALISTA
K28: ANALISTA DE RECURSOS HUMANOS | L28: ADMINISTRATIVO | M28: GESTÃO PESSOAS
K29: APRENDIZ | L29: ADMINISTRATIVO | M29: APRENDIZ
K30: APRENDIZ - DEPOSITO TROCAS | L30: ADMINISTRATIVO | M30: APRENDIZ
K31: APRENDIZ - FRENTE DE CAIXA | L31: ADMINISTRATIVO | M31: APRENDIZ
K32: APRENDIZ -LOJA | L32: ADMINISTRATIVO | M32: APRENDIZ
K33: APRENDIZ -LOJA - LOJA 2 | L33: ADMINISTRATIVO | M33: APRENDIZ
K34: APRENDIZ -LOJA - LOJA 3 | L34: ADMINISTRATIVO | M34: APRENDIZ
K35: APRENDIZ- LOJA 4 | L35: ADMINISTRATIVO | M35: APRENDIZ
K36: ASSISTENTE ADMINISTRATIVO - ADM | L36: ADMINISTRATIVO | M36: ASSISTENTE
K37: ASSISTENTE ADMINISTRATIVO - CD | L37: ADMINISTRATIVO | M37: ASSISTENTE
K38: ASSISTENTE ADMINISTRATIVO - COBRANCA | L38: ADMINISTRATIVO | M38: ASSISTENTE
K39: ASSISTENTE ADMINISTRATIVO - ESCRITORIO - CD | L39: ADMINISTRATIVO | M39: ASSISTENTE
... K302: ZELADOR(A) - LIMPEZA - LOJA 4 | L302: ADMINISTRATIVO | M302: LIMPEZA

Sheet Extras
A1: 30 | B1: 901 | C1: MATHEUS ABRANTE MACHADO SILVA | E1: SG-SX 8:00-18:00 SB 8:00-12:00 | F1: 1 | G1: - | I1: 46174 | O1: COMPRADOR - COMPRAS
A2: 30 | B2: 902 | C2: ADRIANA ARRUDA WAISEL | E2: SG-SX 8:00-18:00 SB 8:00-12:00 | F2: 1 | G2: - | I2: 43983 | O2: COMPRADOR - COMPRAS
A3: 30 | B3: 903 | C3: JOÃO INACIO DA SILVA | E3: SG-SX 8:00-18:00 SB 8:00-12:00 | F3: 1 | G3: - | I3: 43983 | O3: COMPRADOR - COMPRAS
A4: 6 | B4: 9004 | C4: JOSÉ MARCIO BARBOSA | E4: SG-SB 08:00-12:00 14:00-17:20 | F4: 1 | G4: - | I4: 46156 | O4: GERENTE DE LOJA - SUPERVISAO

Sheet Hist LJ01
A1: SubEmpresa | B1: Jan | C1: Fev | D1: Mar | E1: Abr | F1: Mai | G1: Jun | H1: Jul | I1: Ago | J1: Set | K1: Out | L1: Nov | M1: Dez | N1: Ano | P1: Dep
A2: Açougue | B2: 824591.85 | C2: 814188.23 | D2: 873310.75 | E2: 879927.83 | F2: 917257.09 | G2: 870638.73 | H2: 908816.18 | I2: 941156.19 | J2: 867551.85 | K2: 995231.14 | L2: 1006286.6 | M2: 1229800.6 | N2: 11128757 | P2: Açougue
A3: Alimento Basico | B3: 533307.85 | C3: 483833.97 | D3: 532642.84 | E3: 531607.05 | F3: 612791.27 | G3: 599324.83 | H3: 581748.04 | I3: 546775.48 | J3: 503107.66 | K3: 550545.02 | L3: 528270.39 | M3: 487534.92 | N3: 6491489.3 | P3: Loja
A4: Alimento Industrializado | B4: 528074.68 | C4: 498212.08 | D4: 556223.7 | E4: 563445.92 | F4: 598843.72 | G4: 620546.6 | H4: 637391.61 | I4: 612067.25 | J4: 566089.33 | K4: 595456.08 | L4: 639767.97 | M4: 870224.97 | N4: 7286343.9 | P4: Loja
A5: Bazar Geral | B5: 123074.29 | C5: 110910.7 | D5: 128395.05 | E5: 123047.17 | F5: 132107.83 | G5: 122967.53 | H5: 119955.52 | I5: 126992.24 | J5: 119072.67 | K5: 135760.74 | L5: 131818.65 | M5: 161573.38 | N5: 1535675.8 | P5: Loja
A6: Bebidas | B6: 423285.55 | C6: 426072.56 | D6: 527288.02 | E6: 440892.81 | F6: 450737.58 | G6: 393009.15 | H6: 391397.72 | I6: 441713.53 | J6: 409801.33 | K6: 421241.62 | L6: 467556.59 | M6: 722886.71 | N6: 5515883.2 | P6: Loja
A7: Bomboniere | B7: 134850.38 | C7: 135401.64 | D7: 172595.08 | E7: 398563.53 | F7: 148431.09 | G7: 154657.96 | H7: 157195.2 | I7: 152005.89 | J7: 134169.74 | K7: 146717.18 | L7: 147751.58 | M7: 216502.09 | N7: 2098841.4 | P7: Loja
A8: Confeitaria | B8: 106165.85 | C8: 101798.49 | D8: 114544.13 | E8: 101867.91 | F8: 124543.44 | G8: 117009.51 | H8: 115168.42 | I8: 133703.74 | J8: 117049.86 | K8: 118688.27 | L8: 114262.38 | M8: 112397.09 | N8: 1377199.1 | P8: Confeitaria
A9: Flores | B9: 9624.04 | C9: 10290.74 | D9: 12220.59 | E9: 7004.51 | F9: 30375.75 | G9: 11555.79 | H9: 7990.36 | I9: 12933.3 | J9: 15780.12 | K9: 15268.88 | L9: 15328.39 | M9: 5012.88 | N9: 153385.35 | P9: Loja
A10: Frios e Congelados | B10: 250299.31 | C10: 231736.2 | D10: 265217.88 | E10: 258979.67 | F10: 293139.32 | G10: 284419.88 | H10: 277582.99 | I10: 260527.83 | J10: 239931.87 | K10: 249799.64 | L10: 249988.08 | M10: 313883.82 | N10: 3175506.5 | P10: Frios
A11: Higiene e Perfumaria | B11: 225501.53 | C11: 216388.8 | D11: 238253.62 | E11: 225867.17 | F11: 236503.57 | G11: 220136.54 | H11: 231083.17 | I11: 236365.95 | J11: 223425.49 | K11: 235878.83 | L11: 241778.6 | M11: 253367.24 | N11: 2784550.5 | P11: Loja
A12: Hortifruti | B12: 648037.77 | C12: 573054.11 | D12: 660746.75 | E12: 666149.26 | F12: 642863.3 | G12: 573183.95 | H12: 689454.8 | I12: 681174.42 | J12: 700443.18 | K12: 650068.87 | L12: 650165.78 | M12: 755275.06 | N12: 7890617.3 | P12: Hortifruti
A13: Laticinios | B13: 240678.8 | C13: 223752.61 | D13: 242392.14 | E13: 225964.19 | F13: 226717.42 | G13: 224785.68 | H13: 245678.58 | I13: 237217.69 | J13: 240902.39 | K13: 249460.04 | L13: 250142.78 | M13: 264807.8 | N13: 2872500.1 | P13: Frios
... A19: Rotisseria | B19: 88975.07 | C19: 90874.57 | D19: 101072.24 | E19: 82499.61 | F19: 99406.94 | G19: 97410.02 | H19: 95174.57 | I19: 100833.84 | J19: 97801.59 | K19: 100742.55 | L19: 101118.45 | M19: 102671.55 | N19: 1158581 | P19: Rotisseria
A20: Total | B20: 4672168.2 | C20: 4395175.2 | D20: 5003146.9 | E20: 5068465.7 | F20: 5058912.5 | G20: 4808087.7 | H20: 5011604.6 | I20: 5020870.9 | J20: 4777027.7 | K20: 5009122.2 | L20: 5078982.2 | M20: 6042576.6 | N20: 59946140
B21: =B19+B16+B8 -> 406142.98 | C21: =C19+C16+C8 -> 377199.9 | D21: =D19+D16+D8 -> 415279.2 | E21: =E19+E16+E8 -> 379950.35 | F21: =F19+F16+F8 -> 450932.81 | G21: =G19+G16+G8 -> 441434.64 | H21: =H19+H16+H8 -> 461056.96 | I21: =I19+I16+I8 -> 486591.2 | ... N21: =N19+N16+N8 -> 5267552.6

Sheet Hist LJ02
A1: SubEmpresa | B1: Jan | C1: Fev | D1: Mar | E1: Abr | F1: Mai | G1: Jun | H1: Jul | I1: Ago | J1: Set | K1: Out | L1: Nov | M1: Dez | N1: Ano | P1: Dep
A2: Açougue | B2: 472296.93 | C2: 445331.34 | D2: 483643.46 | E2: 493821.77 | F2: 519102.59 | G2: 477297.45 | H2: 517494.6 | I2: 495395.7 | J2: 454508.26 | K2: 480000.14 | L2: 449350.79 | M2: 530708.89 | N2: 5818951.9 | P2: Açougue
A3: Alimento Basico | B3: 275558.82 | C3: 256559.35 | D3: 287097.73 | E3: 291862.45 | F3: 326613.63 | G3: 325953.08 | H3: 322388.13 | I3: 295989.22 | J3: 256545.92 | K3: 279020.33 | L3: 254806.62 | M3: 226259.05 | N3: 3398654.3 | P3: Loja
A4: Alimento Industrializado | B4: 327180.67 | C4: 308100.82 | D4: 352466.18 | E4: 353207.86 | F4: 364516.26 | G4: 384042.9 | H4: 397392.31 | I4: 368390.46 | J4: 327903.02 | K4: 348467.6 | L4: 361806.98 | M4: 482455.5 | N4: 4375930.6 | P4: Loja
A5: Bazar Geral | B5: 74431.11 | C5: 67045.47 | D5: 75341.03 | E5: 73632 | F5: 77822.78 | G5: 75544.26 | H5: 72193.86 | I5: 75018.55 | J5: 69185.24 | K5: 77402.87 | L5: 71077.4 | M5: 79714.86 | N5: 888409.43 | P5: Loja
A6: Bebidas | B6: 259380.16 | C6: 272377.63 | D6: 310951.15 | E6: 282556.2 | F6: 278490.74 | G6: 249035.19 | H6: 257825.41 | I6: 274058.14 | J6: 253503.08 | K6: 262298.38 | L6: 279961.5 | M6: 415539.84 | N6: 3395977.4 | P6: Loja
A7: Bomboniere | B7: 82694.75 | C7: 90179.73 | D7: 110844.88 | E7: 288988.05 | F7: 92768.4 | G7: 101328.27 | H7: 110524.53 | I7: 95877.65 | J7: 85099.08 | K7: 101458.29 | L7: 100897.89 | M7: 141571.68 | N7: 1402233.2 | P7: Loja
A8: Confeitaria | B8: 39745.04 | C8: 33947.91 | D8: 43183.31 | E8: 44045.2 | F8: 55752.02 | G8: 52612.42 | H8: 54752.64 | I8: 59063.79 | J8: 50213.4 | K8: 47274.62 | L8: 44286.99 | M8: 51332.29 | N8: 576209.63 | P8: Confeitaria
A9: Flores | B9: 4658.47 | C9: 5770.68 | D9: 7565.3 | E9: 5700.6 | F9: 18455.19 | G9: 5473.05 | H9: 6648.13 | I9: 11328.82 | J9: 12432.75 | K9: 12079.52 | L9: 15471.18 | M9: 9225.38 | N9: 114809.07 | P9: Loja
A10: Frios e Congelados | B10: 175177.92 | C10: 168334.99 | D10: 186926.16 | E10: 183305.87 | F10: 210000.87 | G10: 205305.45 | H10: 199735.11 | I10: 185109.53 | J10: 175086.45 | K10: 180822.99 | L10: 170822.76 | M10: 208895.67 | N10: 2249523.8 | P10: Frios
A11: Higiene e Perfumaria | B11: 127557.07 | C11: 120728.24 | D11: 133968.08 | E11: 127667.73 | F11: 133108.41 | G11: 130590.46 | H11: 132609.78 | I11: 132479.6 | J11: 123382.26 | K11: 123544.65 | L11: 130162.56 | M11: 130963.07 | N11: 1546761.9 | P11: Loja
A12: Hortifruti | B12: 459703.48 | C12: 433472.8 | D12: 486466.69 | E12: 471087.56 | F12: 448515.09 | G12: 389191.41 | H12: 455596.17 | I12: 478006.01 | J12: 457732.74 | K12: 426335.95 | L12: 411729.71 | M12: 450383.59 | N12: 5368221.2 | P12: Hortifruti
A13: Laticinios | B13: 166606.84 | C13: 157311.96 | D13: 181182.49 | E13: 168710.87 | F13: 176237.7 | G13: 169581.67 | H13: 177352.02 | I13: 180868.36 | J13: 178000.38 | K13: 181855.64 | L13: 163243.78 | M13: 174854.48 | N13: 2075806.2 | P13: Frios
... A19: Rotisseria | B19: 29623.52 | C19: 29019.91 | D19: 32173.46 | E19: 31878.25 | F19: 35938.09 | G19: 36114.5 | H19: 35152.65 | I19: 30917.64 | J19: 28603.18 | K19: 34734.44 | L19: 29573 | M19: 36511.04 | N19: 390239.68 | P19: Rotisseria
A20: Total | B20: 2839277.9 | C20: 2702365.5 | D20: 3066044.8 | E20: 3202572.4 | F20: 3090885 | G20: 2939070.2 | H20: 3107973 | I20: 3033801.9 | J20: 2801352.7 | K20: 2892700.9 | L20: 2797129.7 | M20: 3268745 | N20: 35741919
B21: =B19+B16+B8 -> 204826.83 | C21: =C19+C16+C8 -> 187393.53 | D21: =D19+D16+D8 -> 200833 | E21: =E19+E16+E8 -> 208353.96 | F21: =F19+F16+F8 -> 242701.96 | G21: =G19+G16+G8 -> 244553.8 | H21: =H19+H16+H8 -> 255624.6 | I21: =I19+I16+I8 -> 247240.77 | ... N21: =N19+N16+N8 -> 2664118.3

Sheet Hist LJ03
A1: SubEmpresa | B1: Jan | C1: Fev | D1: Mar | E1: Abr | F1: Mai | G1: Jun | H1: Jul | I1: Ago | J1: Set | K1: Out | L1: Nov | M1: Dez | N1: Ano | P1: Dep
A2: Açougue | B2: 500341.97 | C2: 491054.2 | D2: 534090.08 | E2: 514404.61 | F2: 563234.27 | G2: 514293 | H2: 503441.94 | I2: 528234.97 | J2: 486154.13 | K2: 509265.76 | L2: 534264.99 | M2: 683557.46 | N2: 6362337.4 | P2: Açougue
A3: Alimento Basico | B3: 348592.31 | C3: 326782.54 | D3: 365000.57 | E3: 350327.96 | F3: 396809.02 | G3: 392425.77 | H3: 392622.14 | I3: 376196.45 | J3: 352182.01 | K3: 358003.16 | L3: 341148.13 | M3: 291859.54 | N3: 4291949.6 | P3: Loja
A4: Alimento Industrializado | B4: 330654.14 | C4: 302497.05 | D4: 348112.71 | E4: 331750.02 | F4: 367524.38 | G4: 372165.84 | H4: 370992.3 | I4: 372092.67 | J4: 343197.38 | K4: 361769.61 | L4: 372053.73 | M4: 426732.95 | N4: 4299542.8 | P4: Loja
A5: Bazar Geral | B5: 74497.91 | C5: 73801.87 | D5: 86360.69 | E5: 82882.33 | F5: 88819.74 | G5: 80565.94 | H5: 79711.5 | I5: 88084.48 | J5: 81214.27 | K5: 80654.48 | L5: 84860.43 | M5: 107488.29 | N5: 1008941.9 | P5: Loja
A6: Bebidas | B6: 372901.34 | C6: 383342.6 | D6: 465086.15 | E6: 372108.52 | F6: 416297.33 | G6: 348741.96 | H6: 351827.62 | I6: 418010.31 | J6: 389871.35 | K6: 394850.9 | L6: 447301.44 | M6: 600946.38 | N6: 4961285.9 | P6: Loja
A7: Bomboniere | B7: 85799.31 | C7: 85823.79 | D7: 106172.09 | E7: 186587.15 | F7: 89568.56 | G7: 95674.41 | H7: 101547.13 | I7: 94648.02 | J7: 84700.06 | K7: 97961.72 | L7: 106680.93 | M7: 112801.45 | N7: 1247964.6 | P7: Loja
A8: Confeitaria | B8: 28543.94 | C8: 25978.76 | D8: 35728.77 | E8: 29063.57 | F8: 36066.81 | G8: 37298.54 | H8: 32794.97 | I8: 40870.7 | J8: 40325.79 | K8: 38347.22 | L8: 32554.46 | M8: 33153.05 | N8: 410726.58 | P8: Confeitaria
A9: Flores | B9: 4247.46 | C9: 3372.5 | D9: 4386.97 | E9: 3987.06 | F9: 8776.06 | G9: 4039.39 | H9: 4043.37 | I9: 4376.08 | J9: 4772.9 | K9: 3388.29 | L9: 3403.28 | M9: 3042.91 | N9: 51836.27 | P9: Loja
A10: Frios e Congelados | B10: 167868.84 | C10: 155797.21 | D10: 182888.85 | E10: 168789.3 | F10: 182058.32 | G10: 185079.34 | H10: 179633.12 | I10: 176726.07 | J10: 168467.97 | K10: 173118.13 | L10: 170976.58 | M10: 186203.45 | N10: 2097607.2 | P10: Frios
A11: Higiene e Perfumaria | B11: 164346.02 | C11: 160237.36 | D11: 169271.05 | E11: 161513.98 | F11: 170093.38 | G11: 162891.28 | H11: 161887.43 | I11: 172474.77 | J11: 166441.74 | K11: 171202.86 | L11: 176345.27 | M11: 178622.34 | N11: 2015327.5 | P11: Loja
A12: Hortifruti | B12: 334778.58 | C12: 310265.48 | D12: 349453.96 | E12: 347400.58 | F12: 343417.13 | G12: 315606.98 | H12: 357930.08 | I12: 367066.76 | J12: 378974.06 | K12: 348281.61 | L12: 346212.89 | M12: 410319.48 | N12: 4209707.6 | P12: Hortifruti
A13: Laticinios | B13: 121440.64 | C13: 107171.27 | D13: 129389.23 | E13: 113474.06 | F13: 117541.37 | G13: 115263.62 | H13: 116777.11 | I13: 120469.94 | J13: 121846.36 | K13: 119988.34 | L13: 115280.11 | M13: 119645.54 | N13: 1418287.6 | P13: Frios
... A18: Peixaria | B18: 11742.66 | C18: 13803.23 | D18: 32331.66 | E18: 38104.14 | F18: 9416.78 | G18: 8764.37 | H18: 10426.39 | I18: 10599.31 | J18: 12662.69 | K18: 12781.7 | L18: 10840.36 | M18: 10331.5 | N18: 181804.79 | P18: Frios
A19: Rotisseria | B19: 1010.77 | C19: 146.12 | D19: 32.2 | E19: 404.1 | F19: 51.82 | G19: 13.9 | H19: 722.62 | I19: 6.43 | K19: 26.25 | L19: 4.54 | M19: 194.93 | N19: 2613.68 | P19: Rotisseria
A20: Total | B20: 2785692.2 | C20: 2655535.3 | D20: 3046525.3 | E20: 2909466.9 | F20: 3015715.3 | G20: 2860012.5 | H20: 2892461.7 | I20: 2995538 | J20: 2852898.7 | K20: 2900315.7 | L20: 2981089.7 | M20: 3410146.5 | N20: 35305398
B21: =B19+B16+B8 -> 91793.27 | C21: =C19+C16+C8 -> 82113.09 | D21: =D19+D16+D8 -> 97555.32 | E21: =E19+E16+E8 -> 85599.03 | F21: =F19+F16+F8 -> 98985.83 | G21: =G19+G16+G8 -> 110437.66 | H21: =H19+H16+H8 -> 106571.25 | I21: =I19+I16+I8 -> 116301.16 | ... N21: =N19+N16+N8 -> 1229294.2

Sheet Hist LJ04
A1: SubEmpresa | B1: Jan | C1: Fev | D1: Mar | E1: Abr | F1: Mai | G1: Jun | H1: Jul | I1: Ago | J1: Set | K1: Out | L1: Nov | M1: Dez | N1: Ano | P1: Dep
A2: Açougue | B2: 424669.99 | C2: 393706.94 | D2: 451766.64 | E2: 414476.47 | F2: 441341.92 | G2: 424914.11 | H2: 411874.35 | I2: 433843.49 | J2: 402505.43 | K2: 443708.31 | L2: 458517.34 | M2: 548479.43 | N2: 5249804.4 | P2: Açougue
A3: Alimento Basico | B3: 251495.94 | C3: 236071.14 | D3: 256468.42 | E3: 259913.37 | F3: 291109.99 | G3: 283880.02 | H3: 282294.72 | I3: 266023.05 | J3: 250381.52 | K3: 251784.46 | L3: 244386.8 | M3: 220700.01 | N3: 3094509.4 | P3: Loja
A4: Alimento Industrializado | B4: 254046.42 | C4: 231262.43 | D4: 265437.37 | E4: 258045.27 | F4: 279213.14 | G4: 284398.09 | H4: 288448.63 | I4: 281527.13 | J4: 265054.29 | K4: 281880.13 | L4: 298168.28 | M4: 345253.48 | N4: 3332734.7 | P4: Loja
A5: Bazar Geral | B5: 50950.86 | C5: 46196.07 | D5: 50332.59 | E5: 48608.52 | F5: 55657.66 | G5: 50536.25 | H5: 50923.98 | I5: 54058.52 | J5: 48973.96 | K5: 53924.87 | L5: 55029.14 | M5: 68054.82 | N5: 633247.24 | P5: Loja
A6: Bebidas | B6: 270578.77 | C6: 279353.25 | D6: 327325.76 | E6: 267630.01 | F6: 294668.25 | G6: 260022.09 | H6: 256082.31 | I6: 293070.15 | J6: 273634.34 | K6: 284377.48 | L6: 300927.88 | M6: 396910.43 | N6: 3504580.7 | P6: Loja
A7: Bomboniere | B7: 62263.56 | C7: 62138.92 | D7: 74186.29 | E7: 126265.77 | F7: 70319.64 | G7: 74610.21 | H7: 82853.86 | I7: 73453.57 | J7: 66358.04 | K7: 69114.33 | L7: 79378.64 | M7: 82820.71 | N7: 923763.54 | P7: Loja
A8: Confeitaria | B8: 30446.8 | C8: 29120.95 | D8: 33299.05 | E8: 29667.61 | F8: 36463.57 | G8: 39280.67 | H8: 43942.82 | I8: 44331.67 | J8: 47568.37 | K8: 35449.54 | L8: 35990.43 | M8: 30239.99 | N8: 435801.47 | P8: Confeitaria
A9: Flores | B9: 1725.44 | C9: 1961.88 | D9: 1647.32 | E9: 1326.2 | F9: 5905.61 | G9: 2121.62 | H9: 2491.33 | I9: 3255.17 | J9: 4173.22 | K9: 2774.63 | L9: 3036.99 | M9: 1450.98 | N9: 31870.39 | P9: Loja
A10: Frios e Congelados | B10: 146518.8 | C10: 135906.48 | D10: 157756.38 | E10: 142404.68 | F10: 169667.42 | G10: 163018.56 | H10: 165865.64 | I10: 156573.57 | J10: 146350.52 | K10: 151969.23 | L10: 149051.63 | M10: 165031.19 | N10: 1850114.1 | P10: Frios
A11: Higiene e Perfumaria | B11: 104660.82 | C11: 102024.65 | D11: 106399.61 | E11: 101974.28 | F11: 111972.67 | G11: 106672.61 | H11: 109480.32 | I11: 110456.81 | J11: 108625.31 | K11: 111603.86 | L11: 113038.85 | M11: 119800.85 | N11: 1306710.6 | P11: Loja
A12: Hortifruti | B12: 318676.92 | C12: 303314.41 | D12: 339785.5 | E12: 333942.92 | F12: 319950.59 | G12: 294684.45 | H12: 341823.19 | I12: 339210.47 | J12: 373538.19 | K12: 333537.64 | L12: 331267.03 | M12: 376450.04 | N12: 4006181.3 | P12: Hortifruti
A13: Laticinios | B13: 113145.25 | C13: 103022.34 | D13: 121324.08 | E13: 106946.3 | F13: 113229.27 | G13: 114792.96 | H13: 114197.48 | I13: 116581.72 | J13: 119252.94 | K13: 121962.08 | L13: 115176.82 | M13: 118811.28 | N13: 1378442.5 | P13: Frios
... A19: Rotisseria | B19: 1849.44 | C19: 1999.87 | D19: 2598.8 | E19: 1311.84 | F19: 2044.94 | G19: 2410.29 | H19: 1978.46 | I19: 2472.28 | J19: 1916.89 | K19: 1862.88 | L19: 2469.93 | M19: 1908.74 | N19: 24824.36 | P19: Rotisseria
A20: Total | B20: 2255242.1 | C20: 2123168.4 | D20: 2418000.3 | E20: 2311418.4 | F20: 2406334.2 | G20: 2302464.1 | H20: 2373204.1 | I20: 2392137.9 | J20: 2319689.5 | K20: 2358183 | L20: 2405167.4 | M20: 2700254.2 | N20: 28365264
B21: =B19+B16+B8 -> 119346.32 | C21: =C19+C16+C8 -> 99271.56 | D21: =D19+D16+D8 -> 108554.53 | E21: =E19+E16+E8 -> 103247.44 | F21: =F19+F16+F8 -> 118353.06 | G21: =G19+G16+G8 -> 119984.15 | H21: =H19+H16+H8 -> 136769.4 | I21: =I19+I16+I8 -> 141945.39 | ... N21: =N19+N16+N8 -> 1449615.3

Sheet Hist LJ05
A1: SubEmpresa | B1: Jan | C1: Fev | D1: Mar | E1: Abr | F1: Mai | G1: Jun | H1: Jul | I1: Ago | J1: Set | K1: Out | L1: Nov | M1: Dez | N1: Ano | P1: Dep
A2: Açougue | B2: 705039.31 | C2: 691748.24 | D2: 690129.94 | E2: 739939.94 | F2: 767681.44 | G2: 726405.87 | H2: 776525.19 | I2: 802532.56 | J2: 715617.25 | K2: 775836.51 | L2: 782232.85 | M2: 897668.4 | N2: 9071357.5 | P2: Açougue
A3: Alimento Basico | B3: 378290.69 | C3: 373257.14 | D3: 384734.79 | E3: 398041.56 | F3: 448792.73 | G3: 435847.2 | H3: 435527.24 | I3: 416784.01 | J3: 381398.96 | K3: 369385.69 | L3: 371523.43 | M3: 332362.04 | N3: 4725945.5 | P3: Loja
A4: Alimento Industrializado | B4: 343044.48 | C4: 325431.53 | D4: 366186.61 | E4: 369888.75 | F4: 384779.66 | G4: 401295.98 | H4: 427389.45 | I4: 407792.68 | J4: 380043.68 | K4: 392276.57 | L4: 415123.09 | M4: 529158.05 | N4: 4742410.5 | P4: Loja
A5: Bazar Geral | B5: 54299.53 | C5: 50351.4 | D5: 57275.78 | E5: 58146.45 | F5: 61420.31 | G5: 61579.4 | H5: 62989.1 | I5: 64457.7 | J5: 58725.32 | K5: 62212.54 | L5: 65825.98 | M5: 78484.1 | N5: 735767.61 | P5: Loja
A6: Bebidas | B6: 313889.36 | C6: 352829.64 | D6: 405472.08 | E6: 358084.83 | F6: 360180.94 | G6: 324273.91 | H6: 334083.29 | I6: 364901.63 | J6: 347255.53 | K6: 331395.38 | L6: 380945.32 | M6: 529551.18 | N6: 4402863.1 | P6: Loja
A7: Bomboniere | B7: 79451.67 | C7: 82815.25 | D7: 105309.66 | E7: 281414.59 | F7: 91144.81 | G7: 101197.99 | H7: 119254.47 | I7: 107589.04 | J7: 94746.28 | K7: 109459.66 | L7: 120004.83 | M7: 138970.39 | N7: 1431358.6 | P7: Loja
A8: Confeitaria | B8: 36292.98 | C8: 34594.08 | D8: 36900.58 | E8: 35998.83 | F8: 44481.04 | G8: 48739.07 | H8: 57682.23 | I8: 54579.36 | J8: 46362.07 | K8: 51180.67 | L8: 43523.21 | M8: 40033.25 | N8: 530367.37 | P8: Confeitaria
A9: Flores | B9: 5774.01 | C9: 6739.52 | D9: 8143.21 | E9: 7434.61 | F9: 14796.13 | G9: 8572.28 | H9: 8542.55 | I9: 10896.45 | J9: 12797.01 | K9: 10388.23 | L9: 11742.07 | M9: 7547.21 | N9: 113373.28 | P9: Loja
A10: Frios e Congelados | B10: 209840.24 | C10: 200887.15 | D10: 231168.22 | E10: 218099.56 | F10: 242505.08 | G10: 241346.76 | H10: 246689.44 | I10: 233400.62 | J10: 223967.68 | K10: 229513.47 | L10: 223372.66 | M10: 249167.72 | N10: 2749958.6 | P10: Frios
A11: Higiene e Perfumaria | B11: 120427.37 | C11: 123225.55 | D11: 132997.53 | E11: 128089.09 | F11: 130479.95 | G11: 125690.01 | H11: 132508.94 | I11: 138177.41 | J11: 130878.59 | K11: 135999.38 | L11: 137200.73 | M11: 135423.83 | N11: 1571098.4 | P11: Loja
A12: Hortifruti | B12: 424722.56 | C12: 420312.1 | D12: 454216.08 | E12: 469321.85 | F12: 437491.57 | G12: 407088.39 | H12: 484054.56 | I12: 490780.55 | J12: 515680.83 | K12: 455498.45 | L12: 455345.86 | M12: 515419.31 | N12: 5529932.1 | P12: Hortifruti
A13: Laticinios | B13: 185697.2 | C13: 172673.45 | D13: 195310.12 | E13: 185139.58 | F13: 187496.16 | G13: 182960.08 | H13: 194017.2 | I13: 198221.34 | J13: 197519.82 | K13: 212250.8 | L13: 194227.36 | M13: 204068.56 | N13: 2309581.7 | P13: Frios
... A19: Rotisseria | B19: 316.06 | C19: 222.44 | D19: 636.19 | E19: 29.84 | F19: 656.15 | G19: 754.15 | H19: 515.84 | I19: 337.08 | J19: 584.12 | K19: 875.28 | L19: 327.12 | M19: 36.68 | N19: 5290.95 | P19: Rotisseria
A20: Total | B20: 3181874.2 | C20: 3138878.8 | D20: 3437306.3 | E20: 3626851.4 | F20: 3511361.3 | G20: 3390641.6 | H20: 3635736 | I20: 3635916.8 | J20: 3451916.6 | K20: 3491968.4 | L20: 3548148.3 | M20: 4004814.2 | N20: 42055414
B21: =B19+B16+B8 -> 161397.74 | C21: =C19+C16+C8 -> 149277.97 | D21: =D19+D16+D8 -> 166067.74 | E21: =E19+E16+E8 -> 176050.85 | F21: =F19+F16+F8 -> 193339.68 | G21: =G19+G16+G8 -> 203190.91 | H21: =H19+H16+H8 -> 226901.93 | I21: =I19+I16+I8 -> 217488.55 | ... N21: =N19+N16+N8 -> 2321040.8

Sheet Hist LJ06
A1: SubEmpresa | B1: Jan | C1: Fev | D1: Mar | E1: Abr | F1: Mai | G1: Jun | H1: Jul | I1: Ago | J1: Set | K1: Out | L1: Nov | M1: Dez | N1: Ano | P1: Dep
A2: Açougue | B2: 745868.97 | C2: 775079.21 | D2: 814395.09 | E2: 796031.95 | F2: 830064.26 | G2: 772522.11 | H2: 866045.08 | I2: 851234.39 | J2: 767653.32 | K2: 795755.56 | L2: 796422.07 | M2: 928491.15 | N2: 9739563.2 | P2: Açougue
A3: Alimento Basico | B3: 404370.13 | C3: 379114.6 | D3: 396383.21 | E3: 379124.12 | F3: 430200.18 | G3: 423861.92 | H3: 430548.14 | I3: 427184.52 | J3: 367813.12 | K3: 396553.54 | L3: 373892.48 | M3: 343193.61 | N3: 4752239.6 | P3: Loja
A4: Alimento Industrializado | B4: 420358.79 | C4: 424539.55 | D4: 460923.21 | E4: 474080.01 | F4: 500503.03 | G4: 517767.08 | H4: 534608.58 | I4: 510348.28 | J4: 464817.19 | K4: 516251.18 | L4: 518175.27 | M4: 679026.6 | N4: 6021398.8 | P4: Loja
A5: Bazar Geral | B5: 77449.33 | C5: 76161.7 | D5: 79718.67 | E5: 81739.23 | F5: 83476.34 | G5: 78401.37 | H5: 76455.97 | I5: 84317.04 | J5: 73936.68 | K5: 84625.26 | L5: 80986.59 | M5: 97407.49 | N5: 974675.67 | P5: Loja
A6: Bebidas | B6: 383335.14 | C6: 425288.13 | D6: 478624.7 | E6: 421644.12 | F6: 425303.04 | G6: 373620.27 | H6: 385249.73 | I6: 429970.85 | J6: 382005.58 | K6: 394633.28 | L6: 439858.85 | M6: 617392.33 | N6: 5156926 | P6: Loja
A7: Bomboniere | B7: 103127.51 | C7: 114068.01 | D7: 139477.52 | E7: 331577.35 | F7: 120786.01 | G7: 131614.09 | H7: 136506.98 | I7: 133436.71 | J7: 117976.1 | K7: 136473.08 | L7: 136315.9 | M7: 181847.05 | N7: 1783206.3 | P7: Loja
A8: Confeitaria | B8: 44202.93 | C8: 43199.75 | D8: 51106.56 | E8: 53291.32 | F8: 58158.36 | G8: 60398.91 | H8: 69520.57 | I8: 65756 | J8: 51980.05 | K8: 61716.29 | L8: 50423.34 | M8: 46718.13 | N8: 656472.21 | P8: Confeitaria
A9: Flores | B9: 8048.85 | C9: 8269.16 | D9: 9410.75 | E9: 7365.36 | F9: 17392.01 | G9: 7069.73 | H9: 8844.39 | I9: 11422.82 | J9: 13471.23 | K9: 13312.23 | L9: 14704.18 | M9: 10715.39 | N9: 130026.1 | P9: Loja
A10: Frios e Congelados | B10: 224865.98 | C10: 218571.68 | D10: 246135.64 | E10: 241240.39 | F10: 275136.84 | G10: 262558.38 | H10: 248849.1 | I10: 248531.34 | J10: 234832.33 | K10: 246371.56 | L10: 231264.71 | M10: 271953.49 | N10: 2950311.4 | P10: Frios
A11: Higiene e Perfumaria | B11: 146912.21 | C11: 154218.44 | D11: 160494.43 | E11: 157170.16 | F11: 166967.14 | G11: 154765.11 | H11: 163108.28 | I11: 160675.16 | J11: 153655.35 | K11: 165842.61 | L11: 165271.2 | M11: 169505.3 | N11: 1918585.4 | P11: Loja
A12: Hortifruti | B12: 492596.78 | C12: 510779.98 | D12: 543772.22 | E12: 580892.16 | F12: 535967.53 | G12: 505019.45 | H12: 556548.01 | I12: 570654.05 | J12: 574699.85 | K12: 545980.65 | L12: 548859.28 | M12: 640166.14 | N12: 6605936.1 | P12: Hortifruti
A13: Laticinios | B13: 226605.87 | C13: 214275.86 | D13: 253650.92 | E13: 235269.97 | F13: 238086.56 | G13: 232123.91 | H13: 246166.91 | I13: 248707.55 | J13: 251056.56 | K13: 272067.5 | L13: 250278.08 | M13: 259728.08 | N13: 2928017.8 | P13: Frios
... A19: Rotisseria | B19: 38632.6 | C19: 34805.08 | D19: 38323.18 | E19: 38314.53 | F19: 45571.76 | G19: 49359.41 | H19: 44241.26 | I19: 57427.41 | J19: 52208.87 | K19: 47695.74 | L19: 45537.73 | M19: 53150.16 | N19: 545267.73 | P19: Rotisseria
A20: Total | B20: 3688089.7 | C20: 3750186.4 | D20: 4120868.4 | E20: 4257513.6 | F20: 4148699.6 | G20: 3975894.7 | H20: 4210990.4 | I20: 4228069.2 | J20: 3934609.1 | K20: 4116730.4 | L20: 4088787.4 | M20: 4724319.3 | N20: 49244758
B21: =B19+B16+B8 -> 219912.2 | C21: =C19+C16+C8 -> 209505.33 | D21: =D19+D16+D8 -> 248359.13 | E21: =E19+E16+E8 -> 256536.81 | F21: =F19+F16+F8 -> 279812.19 | G21: =G19+G16+G8 -> 298386.7 | H21: =H19+H16+H8 -> 322938.86 | I21: =I19+I16+I8 -> 321738.85 | ... N21: =N19+N16+N8 -> 3358710.5

Sheet Hist LJ07
A1: SubEmpresa | B1: Jan | C1: Fev | D1: Mar | E1: Abr | F1: Mai | G1: Jun | H1: Jul | I1: Ago | J1: Set | K1: Out | L1: Nov | M1: Dez | N1: Ano | P1: Dep
A2: Açougue | B2: 628266.2 | C2: 579488.74 | D2: 647661.21 | E2: 652380.37 | F2: 691865.59 | G2: 616302.79 | H2: 667003.78 | I2: 664066.04 | J2: 617721.36 | K2: 658504.77 | L2: 699273.98 | M2: 889114.65 | N2: 8011649.5 | P2: Açougue
A3: Alimento Basico | B3: 497983.23 | C3: 466758.68 | D3: 488623.01 | E3: 518011.51 | F3: 523995.4 | G3: 516947.23 | H3: 555183.86 | I3: 518331.36 | J3: 480341.83 | K3: 495973.1 | L3: 506328.05 | M3: 450414.42 | N3: 6018891.7 | P3: Loja
A4: Alimento Industrializado | B4: 496600.49 | C4: 453250.33 | D4: 509442.31 | E4: 513921.33 | F4: 516157.83 | G4: 528863.41 | H4: 571975.13 | I4: 560761.63 | J4: 502089.3 | K4: 502815.18 | L4: 572707.31 | M4: 733775.62 | N4: 6462359.9 | P4: Loja
A5: Bazar Geral | B5: 95415.73 | C5: 87547.24 | D5: 107589.54 | E5: 103766.51 | F5: 101807.51 | G5: 98530.16 | H5: 104158.07 | I5: 107165.59 | J5: 90241.09 | K5: 104290.71 | L5: 113988.43 | M5: 126466.11 | N5: 1240966.7 | P5: Loja
A6: Bebidas | B6: 456327.07 | C6: 447820.18 | D6: 522328.33 | E6: 491876.72 | F6: 459422.15 | G6: 396514.76 | H6: 413428.81 | I6: 474458.38 | J6: 440632.13 | K6: 449321.68 | L6: 515890.6 | M6: 708064.38 | N6: 5776085.2 | P6: Loja
A7: Bomboniere | B7: 122140.02 | C7: 119616.6 | D7: 158073.78 | E7: 376897.01 | F7: 125032.47 | G7: 137321.94 | H7: 154063.6 | I7: 137184.23 | J7: 119443.18 | K7: 128099.06 | L7: 141854.93 | M7: 172569.13 | N7: 1892295.9 | P7: Loja
A8: Confeitaria | B8: 40365.07 | C8: 36233.34 | D8: 46976.49 | E8: 47637.08 | F8: 54294.66 | G8: 53120.62 | H8: 56316.63 | I8: 61808.24 | J8: 55646.06 | K8: 53590.05 | L8: 55635.03 | M8: 51246.18 | N8: 612869.45 | P8: Confeitaria
A9: Flores | B9: 17757.1 | C9: 17152.68 | D9: 21303.34 | E9: 17220.93 | F9: 72951.05 | G9: 24584.28 | H9: 19654.41 | I9: 27115.76 | J9: 40199.09 | K9: 46862.91 | L9: 43677.9 | M9: 27003.56 | N9: 375483.01 | P9: Loja
A10: Frios e Congelados | B10: 243747.19 | C10: 223133.73 | D10: 253107.48 | E10: 231949.63 | F10: 239252.22 | G10: 235815.37 | H10: 252806.98 | I10: 239506.95 | J10: 229547.36 | K10: 227971.99 | L10: 237973.6 | M10: 281056.74 | N10: 2895869.2 | P10: Frios
A11: Higiene e Perfumaria | B11: 208972.37 | C11: 209774.51 | D11: 223803.04 | E11: 226210.65 | F11: 217685.63 | G11: 209270.48 | H11: 221782.98 | I11: 225169.9 | J11: 211700.99 | K11: 205676.99 | L11: 226931.73 | M11: 219628.06 | N11: 2606607.3 | P11: Loja
A12: Hortifruti | B12: 438653.47 | C12: 447034.48 | D12: 513079.9 | E12: 510757.88 | F12: 442675.22 | G12: 422253.14 | H12: 492816.4 | I12: 485782.4 | J12: 512026.78 | K12: 469033.04 | L12: 481602.26 | M12: 542454.39 | N12: 5758169.4 | P12: Hortifruti
A13: Laticinios | B13: 191473.04 | C13: 180170.12 | D13: 211770.74 | E13: 193329.89 | F13: 184034.56 | G13: 188905.2 | H13: 201184.85 | I13: 206128.27 | J13: 202671.36 | K13: 201442.32 | L13: 202284.35 | M13: 219197.72 | N13: 2382592.4 | P13: Frios
... A19: Rotisseria | B19: 24824.99 | C19: 26434.81 | D19: 34448.49 | E19: 37261.63 | F19: 35668.67 | G19: 30914.13 | H19: 29218.13 | I19: 26717.18 | J19: 31078.93 | K19: 30500.43 | L19: 36678.85 | M19: 34124.01 | N19: 377870.25 | P19: Rotisseria
A20: Total | B20: 3821531.6 | C20: 3629668.5 | D20: 4145407.5 | E20: 4341610.6 | F20: 4016592.6 | G20: 3792851.8 | H20: 4114301.7 | I20: 4102324.9 | J20: 3896949.4 | K20: 3922833.8 | L20: 4199361.4 | M20: 4809662.7 | N20: 48793096
B21: =B19+B16+B8 -> 161746.72 | C21: =C19+C16+C8 -> 149587.99 | D21: =D19+D16+D8 -> 178646.74 | E21: =E19+E16+E8 -> 182650.65 | F21: =F19+F16+F8 -> 195146.34 | G21: =G19+G16+G8 -> 190155.84 | H21: =H19+H16+H8 -> 198024.99 | I21: =I19+I16+I8 -> 200675.66 | ... N21: =N19+N16+N8 -> 2225957.7

Sheet Hist LJ08
A1: SubEmpresa | B1: Jan | C1: Fev | D1: Mar | E1: Abr | F1: Mai | G1: Jun | H1: Jul | I1: Ago | J1: Set | K1: Out | L1: Nov | M1: Dez | N1: Ano | P1: Dep
A2: Açougue | B2: 452796.24 | C2: 452305.32 | D2: 449629.1 | E2: 442844.27 | F2: 475745.93 | G2: 428009.36 | H2: 448478.5 | I2: 462691.23 | J2: 416540.04 | K2: 504848.54 | L2: 542381.16 | M2: 686952.65 | N2: 5763222.3 | P2: Açougue
A3: Alimento Basico | B3: 266026.32 | C3: 249061.31 | D3: 252156.9 | E3: 259179.88 | F3: 304668.18 | G3: 280134.76 | H3: 308481.71 | I3: 282274.88 | J3: 256204 | K3: 268268.31 | L3: 297024.09 | M3: 244203.78 | N3: 3267684.1 | P3: Loja
A4: Alimento Industrializado | B4: 398374.07 | C4: 371634.14 | D4: 403353.7 | E4: 406187.07 | F4: 420560.14 | G4: 411379.49 | H4: 443271.36 | I4: 436216.73 | J4: 376275.46 | K4: 426133.51 | L4: 486568.05 | M4: 638806.74 | N4: 5218760.5 | P4: Loja
A5: Bazar Geral | B5: 82666.6 | C5: 79205.53 | D5: 82239.17 | E5: 79925.41 | F5: 85551.12 | G5: 78880.46 | H5: 83914.52 | I5: 79798.96 | J5: 73827.11 | K5: 84097.26 | L5: 87560.19 | M5: 103907.44 | N5: 1001573.8 | P5: Loja
A6: Bebidas | B6: 382336.7 | C6: 367042.11 | D6: 436936.77 | E6: 385088.24 | F6: 418316.57 | G6: 354013.79 | H6: 365257.64 | I6: 378756.47 | J6: 370584.19 | K6: 403895.41 | L6: 422622.16 | M6: 643008.57 | N6: 4927858.6 | P6: Loja
A7: Bomboniere | B7: 128884.43 | C7: 133148.61 | D7: 156814.97 | E7: 298222.97 | F7: 130100.82 | G7: 131082.02 | H7: 141091.1 | I7: 127791.05 | J7: 113161.15 | K7: 137532.25 | L7: 155139.99 | M7: 208427.15 | N7: 1861396.5 | P7: Loja
A8: Confeitaria | B8: 41912.07 | C8: 39261.97 | D8: 43091.78 | E8: 41609.81 | F8: 50260.53 | G8: 55045.07 | H8: 58694.59 | I8: 63727.7 | J8: 52435.89 | K8: 49895.6 | L8: 57043.67 | M8: 55725.49 | N8: 608704.17 | P8: Confeitaria
A9: Flores | B9: 15370.76 | C9: 15725.88 | D9: 14525.67 | E9: 13007.73 | F9: 29392.17 | G9: 13129.65 | H9: 12807.04 | I9: 13346.11 | J9: 15687.82 | K9: 15320.4 | L9: 15669.66 | M9: 13183.2 | N9: 187166.09 | P9: Loja
A10: Frios e Congelados | B10: 236183.33 | C10: 219298.76 | D10: 250986.79 | E10: 239727.81 | F10: 254263.86 | G10: 237955.78 | H10: 247839.15 | I10: 242556.14 | J10: 218422.14 | K10: 242923.44 | L10: 247052.4 | M10: 324015.56 | N10: 2961225.2 | P10: Frios
A11: Higiene e Perfumaria | B11: 174290.45 | C11: 169971.18 | D11: 173110.47 | E11: 168442.89 | F11: 174417.4 | G11: 158994.24 | H11: 165729.27 | I11: 167836.07 | J11: 153441.33 | K11: 166517.4 | L11: 182781.66 | M11: 199124.78 | N11: 2054657.1 | P11: Loja
A12: Hortifruti | B12: 427121.81 | C12: 401340.96 | D12: 452212.31 | E12: 413396.02 | F12: 388735.26 | G12: 334308.89 | H12: 377024.25 | I12: 399432.8 | J12: 394868.35 | K12: 384146.21 | L12: 395746.8 | M12: 466273.94 | N12: 4834607.6 | P12: Hortifruti
A13: Laticinios | B13: 207199.69 | C13: 189758.78 | D13: 207510.57 | E13: 183842.48 | F13: 192222.3 | G13: 181988.49 | H13: 196889.81 | I13: 203478.37 | J13: 211700.14 | K13: 246122.02 | L13: 235772.45 | M13: 253786.34 | N13: 2510271.4 | P13: Frios
... A19: Rotisseria | B19: 64300.63 | C19: 67451.84 | D19: 74791.6 | E19: 69365.28 | F19: 74216.24 | G19: 70912.03 | H19: 74159.8 | I19: 67792.83 | J19: 64632.22 | K19: 65031.37 | L19: 61892.27 | M19: 70447.3 | N19: 824993.41 | P19: Rotisseria
A20: Total | B20: 3219511.4 | C20: 3101720.3 | D20: 3370344.1 | E20: 3379026.8 | F20: 3349745.2 | G20: 3073146 | H20: 3277172.2 | I20: 3265256.8 | J20: 3058804 | K20: 3373792.9 | L20: 3601251.9 | M20: 4325295.1 | N20: 40395067
B21: =B19+B16+B8 -> 243597.23 | C21: =C19+C16+C8 -> 239534.49 | D21: =D19+D16+D8 -> 256443.49 | E21: =E19+E16+E8 -> 259942.32 | F21: =F19+F16+F8 -> 273890.46 | G21: =G19+G16+G8 -> 284558.9 | H21: =H19+H16+H8 -> 297031.4 | I21: =I19+I16+I8 -> 287570.39 | ... N21: =N19+N16+N8 -> 3283968.5

Sheet Hist LJTT
A1: SubEmpresa | B1: Jan | C1: Fev | D1: Mar | E1: Abr | F1: Mai | G1: Jun | H1: Jul | I1: Ago | J1: Set | K1: Out | L1: Nov | M1: Dez | N1: Ano | P1: Dep
A2: Açougue | B2: ='Hist LJ01'!B2+'Hist LJ02'!B2+'Hist LJ03'!B2+'Hist LJ04'!B2+'Hist LJ05'!B2+'Hist LJ06'!B2+'Hist LJ07'!B2+'Hist LJ08'!B2 -> 4753871.5 | C2: ='Hist LJ01'!C2+'Hist LJ02'!C2+'Hist LJ03'!C2+'Hist LJ04'!C2+'Hist LJ05'!C2+'Hist LJ06'!C2+'Hist LJ07'!C2+'Hist LJ08'!C2 -> 4642902.2 | D2: ='Hist LJ01'!D2+'Hist LJ02'!D2+'Hist LJ03'!D2+'Hist LJ04'!D2+'Hist LJ05'!D2+'Hist LJ06'!D2+'Hist LJ07'!D2+'Hist LJ08'!D2 -> 4944626.3 | E2: ='Hist LJ01'!E2+'Hist LJ02'!E2+'Hist LJ03'!E2+'Hist LJ04'!E2+'Hist LJ05'!E2+'Hist LJ06'!E2+'Hist LJ07'!E2+'Hist LJ08'!E2 -> 4933827.2 | F2: ='Hist LJ01'!F2+'Hist LJ02'!F2+'Hist LJ03'!F2+'Hist LJ04'!F2+'Hist LJ05'!F2+'Hist LJ06'!F2+'Hist LJ07'!F2+'Hist LJ08'!F2 -> 5206293.1 | G2: ='Hist LJ01'!G2+'Hist LJ02'!G2+'Hist LJ03'!G2+'Hist LJ04'!G2+'Hist LJ05'!G2+'Hist LJ06'!G2+'Hist LJ07'!G2+'Hist LJ08'!G2 -> 4830383.4 | H2: ='Hist LJ01'!H2+'Hist LJ02'!H2+'Hist LJ03'!H2+'Hist LJ04'!H2+'Hist LJ05'!H2+'Hist LJ06'!H2+'Hist LJ07'!H2+'Hist LJ08'!H2 -> 5099679.6 | I2: ='Hist LJ01'!I2+'Hist LJ02'!I2+'Hist LJ03'!I2+'Hist LJ04'!I2+'Hist LJ05'!I2+'Hist LJ06'!I2+'Hist LJ07'!I2+'Hist LJ08'!I2 -> 5179154.6 | ... N2: ='Hist LJ01'!N2+'Hist LJ02'!N2+'Hist LJ03'!N2+'Hist LJ04'!N2+'Hist LJ05'!N2+'Hist LJ06'!N2+'Hist LJ07'!N2+'Hist LJ08'!N2 -> 61145643 | P2: Açougue
A3: Alimento Basico | B3: ='Hist LJ01'!B3+'Hist LJ02'!B3+'Hist LJ03'!B3+'Hist LJ04'!B3+'Hist LJ05'!B3+'Hist LJ06'!B3+'Hist LJ07'!B3+'Hist LJ08'!B3 -> 2955625.3 | C3: ='Hist LJ01'!C3+'Hist LJ02'!C3+'Hist LJ03'!C3+'Hist LJ04'!C3+'Hist LJ05'!C3+'Hist LJ06'!C3+'Hist LJ07'!C3+'Hist LJ08'!C3 -> 2771438.7 | D3: ='Hist LJ01'!D3+'Hist LJ02'!D3+'Hist LJ03'!D3+'Hist LJ04'!D3+'Hist LJ05'!D3+'Hist LJ06'!D3+'Hist LJ07'!D3+'Hist LJ08'!D3 -> 2963107.5 | E3: ='Hist LJ01'!E3+'Hist LJ02'!E3+'Hist LJ03'!E3+'Hist LJ04'!E3+'Hist LJ05'!E3+'Hist LJ06'!E3+'Hist LJ07'!E3+'Hist LJ08'!E3 -> 2988067.9 | F3: ='Hist LJ01'!F3+'Hist LJ02'!F3+'Hist LJ03'!F3+'Hist LJ04'!F3+'Hist LJ05'!F3+'Hist LJ06'!F3+'Hist LJ07'!F3+'Hist LJ08'!F3 -> 3334980.4 | G3: ='Hist LJ01'!G3+'Hist LJ02'!G3+'Hist LJ03'!G3+'Hist LJ04'!G3+'Hist LJ05'!G3+'Hist LJ06'!G3+'Hist LJ07'!G3+'Hist LJ08'!G3 -> 3258374.8 | H3: ='Hist LJ01'!H3+'Hist LJ02'!H3+'Hist LJ03'!H3+'Hist LJ04'!H3+'Hist LJ05'!H3+'Hist LJ06'!H3+'Hist LJ07'!H3+'Hist LJ08'!H3 -> 3308794 | I3: ='Hist LJ01'!I3+'Hist LJ02'!I3+'Hist LJ03'!I3+'Hist LJ04'!I3+'Hist LJ05'!I3+'Hist LJ06'!I3+'Hist LJ07'!I3+'Hist LJ08'!I3 -> 3129559 | ... N3: ='Hist LJ01'!N3+'Hist LJ02'!N3+'Hist LJ03'!N3+'Hist LJ04'!N3+'Hist LJ05'!N3+'Hist LJ06'!N3+'Hist LJ07'!N3+'Hist LJ08'!N3 -> 36041364 | P3: Loja
A4: Alimento Industrializado | B4: ='Hist LJ01'!B4+'Hist LJ02'!B4+'Hist LJ03'!B4+'Hist LJ04'!B4+'Hist LJ05'!B4+'Hist LJ06'!B4+'Hist LJ07'!B4+'Hist LJ08'!B4 -> 3098333.7 | C4: ='Hist LJ01'!C4+'Hist LJ02'!C4+'Hist LJ03'!C4+'Hist LJ04'!C4+'Hist LJ05'!C4+'Hist LJ06'!C4+'Hist LJ07'!C4+'Hist LJ08'!C4 -> 2914927.9 | D4: ='Hist LJ01'!D4+'Hist LJ02'!D4+'Hist LJ03'!D4+'Hist LJ04'!D4+'Hist LJ05'!D4+'Hist LJ06'!D4+'Hist LJ07'!D4+'Hist LJ08'!D4 -> 3262145.8 | E4: ='Hist LJ01'!E4+'Hist LJ02'!E4+'Hist LJ03'!E4+'Hist LJ04'!E4+'Hist LJ05'!E4+'Hist LJ06'!E4+'Hist LJ07'!E4+'Hist LJ08'!E4 -> 3270526.2 | F4: ='Hist LJ01'!F4+'Hist LJ02'!F4+'Hist LJ03'!F4+'Hist LJ04'!F4+'Hist LJ05'!F4+'Hist LJ06'!F4+'Hist LJ07'!F4+'Hist LJ08'!F4 -> 3432098.2 | G4: ='Hist LJ01'!G4+'Hist LJ02'!G4+'Hist LJ03'!G4+'Hist LJ04'!G4+'Hist LJ05'!G4+'Hist LJ06'!G4+'Hist LJ07'!G4+'Hist LJ08'!G4 -> 3520459.4 | H4: ='Hist LJ01'!H4+'Hist LJ02'!H4+'Hist LJ03'!H4+'Hist LJ04'!H4+'Hist LJ05'!H4+'Hist LJ06'!H4+'Hist LJ07'!H4+'Hist LJ08'!H4 -> 3671469.4 | I4: ='Hist LJ01'!I4+'Hist LJ02'!I4+'Hist LJ03'!I4+'Hist LJ04'!I4+'Hist LJ05'!I4+'Hist LJ06'!I4+'Hist LJ07'!I4+'Hist LJ08'!I4 -> 3549196.8 | ... N4: ='Hist LJ01'!N4+'Hist LJ02'!N4+'Hist LJ03'!N4+'Hist LJ04'!N4+'Hist LJ05'!N4+'Hist LJ06'!N4+'Hist LJ07'!N4+'Hist LJ08'!N4 -> 41739482 | P4: Loja
A5: Bazar Geral | B5: ='Hist LJ01'!B5+'Hist LJ02'!B5+'Hist LJ03'!B5+'Hist LJ04'!B5+'Hist LJ05'!B5+'Hist LJ06'!B5+'Hist LJ07'!B5+'Hist LJ08'!B5 -> 632785.36 | C5: ='Hist LJ01'!C5+'Hist LJ02'!C5+'Hist LJ03'!C5+'Hist LJ04'!C5+'Hist LJ05'!C5+'Hist LJ06'!C5+'Hist LJ07'!C5+'Hist LJ08'!C5 -> 591219.98 | D5: ='Hist LJ01'!D5+'Hist LJ02'!D5+'Hist LJ03'!D5+'Hist LJ04'!D5+'Hist LJ05'!D5+'Hist LJ06'!D5+'Hist LJ07'!D5+'Hist LJ08'!D5 -> 667252.52 | E5: ='Hist LJ01'!E5+'Hist LJ02'!E5+'Hist LJ03'!E5+'Hist LJ04'!E5+'Hist LJ05'!E5+'Hist LJ06'!E5+'Hist LJ07'!E5+'Hist LJ08'!E5 -> 651747.62 | F5: ='Hist LJ01'!F5+'Hist LJ02'!F5+'Hist LJ03'!F5+'Hist LJ04'!F5+'Hist LJ05'!F5+'Hist LJ06'!F5+'Hist LJ07'!F5+'Hist LJ08'!F5 -> 686663.29 | G5: ='Hist LJ01'!G5+'Hist LJ02'!G5+'Hist LJ03'!G5+'Hist LJ04'!G5+'Hist LJ05'!G5+'Hist LJ06'!G5+'Hist LJ07'!G5+'Hist LJ08'!G5 -> 647005.37 | H5: ='Hist LJ01'!H5+'Hist LJ02'!H5+'Hist LJ03'!H5+'Hist LJ04'!H5+'Hist LJ05'!H5+'Hist LJ06'!H5+'Hist LJ07'!H5+'Hist LJ08'!H5 -> 650302.52 | I5: ='Hist LJ01'!I5+'Hist LJ02'!I5+'Hist LJ03'!I5+'Hist LJ04'!I5+'Hist LJ05'!I5+'Hist LJ06'!I5+'Hist LJ07'!I5+'Hist LJ08'!I5 -> 679893.08 | ... N5: ='Hist LJ01'!N5+'Hist LJ02'!N5+'Hist LJ03'!N5+'Hist LJ04'!N5+'Hist LJ05'!N5+'Hist LJ06'!N5+'Hist LJ07'!N5+'Hist LJ08'!N5 -> 8019258.1 | P5: Loja
A6: Bebidas | B6: ='Hist LJ01'!B6+'Hist LJ02'!B6+'Hist LJ03'!B6+'Hist LJ04'!B6+'Hist LJ05'!B6+'Hist LJ06'!B6+'Hist LJ07'!B6+'Hist LJ08'!B6 -> 2862034.1 | C6: ='Hist LJ01'!C6+'Hist LJ02'!C6+'Hist LJ03'!C6+'Hist LJ04'!C6+'Hist LJ05'!C6+'Hist LJ06'!C6+'Hist LJ07'!C6+'Hist LJ08'!C6 -> 2954126.1 | D6: ='Hist LJ01'!D6+'Hist LJ02'!D6+'Hist LJ03'!D6+'Hist LJ04'!D6+'Hist LJ05'!D6+'Hist LJ06'!D6+'Hist LJ07'!D6+'Hist LJ08'!D6 -> 3474013 | E6: ='Hist LJ01'!E6+'Hist LJ02'!E6+'Hist LJ03'!E6+'Hist LJ04'!E6+'Hist LJ05'!E6+'Hist LJ06'!E6+'Hist LJ07'!E6+'Hist LJ08'!E6 -> 3019881.5 | F6: ='Hist LJ01'!F6+'Hist LJ02'!F6+'Hist LJ03'!F6+'Hist LJ04'!F6+'Hist LJ05'!F6+'Hist LJ06'!F6+'Hist LJ07'!F6+'Hist LJ08'!F6 -> 3103416.6 | G6: ='Hist LJ01'!G6+'Hist LJ02'!G6+'Hist LJ03'!G6+'Hist LJ04'!G6+'Hist LJ05'!G6+'Hist LJ06'!G6+'Hist LJ07'!G6+'Hist LJ08'!G6 -> 2699231.1 | H6: ='Hist LJ01'!H6+'Hist LJ02'!H6+'Hist LJ03'!H6+'Hist LJ04'!H6+'Hist LJ05'!H6+'Hist LJ06'!H6+'Hist LJ07'!H6+'Hist LJ08'!H6 -> 2755152.5 | I6: ='Hist LJ01'!I6+'Hist LJ02'!I6+'Hist LJ03'!I6+'Hist LJ04'!I6+'Hist LJ05'!I6+'Hist LJ06'!I6+'Hist LJ07'!I6+'Hist LJ08'!I6 -> 3074939.5 | ... N6: ='Hist LJ01'!N6+'Hist LJ02'!N6+'Hist LJ03'!N6+'Hist LJ04'!N6+'Hist LJ05'!N6+'Hist LJ06'!N6+'Hist LJ07'!N6+'Hist LJ08'!N6 -> 37641460 | P6: Loja
A7: Bomboniere | B7: ='Hist LJ01'!B7+'Hist LJ02'!B7+'Hist LJ03'!B7+'Hist LJ04'!B7+'Hist LJ05'!B7+'Hist LJ06'!B7+'Hist LJ07'!B7+'Hist LJ08'!B7 -> 799211.63 | C7: ='Hist LJ01'!C7+'Hist LJ02'!C7+'Hist LJ03'!C7+'Hist LJ04'!C7+'Hist LJ05'!C7+'Hist LJ06'!C7+'Hist LJ07'!C7+'Hist LJ08'!C7 -> 823192.55 | D7: ='Hist LJ01'!D7+'Hist LJ02'!D7+'Hist LJ03'!D7+'Hist LJ04'!D7+'Hist LJ05'!D7+'Hist LJ06'!D7+'Hist LJ07'!D7+'Hist LJ08'!D7 -> 1023474.3 | E7: ='Hist LJ01'!E7+'Hist LJ02'!E7+'Hist LJ03'!E7+'Hist LJ04'!E7+'Hist LJ05'!E7+'Hist LJ06'!E7+'Hist LJ07'!E7+'Hist LJ08'!E7 -> 2288516.4 | F7: ='Hist LJ01'!F7+'Hist LJ02'!F7+'Hist LJ03'!F7+'Hist LJ04'!F7+'Hist LJ05'!F7+'Hist LJ06'!F7+'Hist LJ07'!F7+'Hist LJ08'!F7 -> 868151.8 | G7: ='Hist LJ01'!G7+'Hist LJ02'!G7+'Hist LJ03'!G7+'Hist LJ04'!G7+'Hist LJ05'!G7+'Hist LJ06'!G7+'Hist LJ07'!G7+'Hist LJ08'!G7 -> 927486.89 | H7: ='Hist LJ01'!H7+'Hist LJ02'!H7+'Hist LJ03'!H7+'Hist LJ04'!H7+'Hist LJ05'!H7+'Hist LJ06'!H7+'Hist LJ07'!H7+'Hist LJ08'!H7 -> 1003036.9 | I7: ='Hist LJ01'!I7+'Hist LJ02'!I7+'Hist LJ03'!I7+'Hist LJ04'!I7+'Hist LJ05'!I7+'Hist LJ06'!I7+'Hist LJ07'!I7+'Hist LJ08'!I7 -> 921986.16 | ... N7: ='Hist LJ01'!N7+'Hist LJ02'!N7+'Hist LJ03'!N7+'Hist LJ04'!N7+'Hist LJ05'!N7+'Hist LJ06'!N7+'Hist LJ07'!N7+'Hist LJ08'!N7 -> 12641060 | P7: Loja
A8: Confeitaria | B8: ='Hist LJ01'!B8+'Hist LJ02'!B8+'Hist LJ03'!B8+'Hist LJ04'!B8+'Hist LJ05'!B8+'Hist LJ06'!B8+'Hist LJ07'!B8+'Hist LJ08'!B8 -> 367674.68 | C8: ='Hist LJ01'!C8+'Hist LJ02'!C8+'Hist LJ03'!C8+'Hist LJ04'!C8+'Hist LJ05'!C8+'Hist LJ06'!C8+'Hist LJ07'!C8+'Hist LJ08'!C8 -> 344135.25 | D8: ='Hist LJ01'!D8+'Hist LJ02'!D8+'Hist LJ03'!D8+'Hist LJ04'!D8+'Hist LJ05'!D8+'Hist LJ06'!D8+'Hist LJ07'!D8+'Hist LJ08'!D8 -> 404830.67 | E8: ='Hist LJ01'!E8+'Hist LJ02'!E8+'Hist LJ03'!E8+'Hist LJ04'!E8+'Hist LJ05'!E8+'Hist LJ06'!E8+'Hist LJ07'!E8+'Hist LJ08'!E8 -> 383181.33 | F8: ='Hist LJ01'!F8+'Hist LJ02'!F8+'Hist LJ03'!F8+'Hist LJ04'!F8+'Hist LJ05'!F8+'Hist LJ06'!F8+'Hist LJ07'!F8+'Hist LJ08'!F8 -> 460020.43 | G8: ='Hist LJ01'!G8+'Hist LJ02'!G8+'Hist LJ03'!G8+'Hist LJ04'!G8+'Hist LJ05'!G8+'Hist LJ06'!G8+'Hist LJ07'!G8+'Hist LJ08'!G8 -> 463504.81 | H8: ='Hist LJ01'!H8+'Hist LJ02'!H8+'Hist LJ03'!H8+'Hist LJ04'!H8+'Hist LJ05'!H8+'Hist LJ06'!H8+'Hist LJ07'!H8+'Hist LJ08'!H8 -> 488872.87 | I8: ='Hist LJ01'!I8+'Hist LJ02'!I8+'Hist LJ03'!I8+'Hist LJ04'!I8+'Hist LJ05'!I8+'Hist LJ06'!I8+'Hist LJ07'!I8+'Hist LJ08'!I8 -> 523841.2 | ... N8: ='Hist LJ01'!N8+'Hist LJ02'!N8+'Hist LJ03'!N8+'Hist LJ04'!N8+'Hist LJ05'!N8+'Hist LJ06'!N8+'Hist LJ07'!N8+'Hist LJ08'!N8 -> 5208350 | P8: Confeitaria
A9: Flores | B9: ='Hist LJ01'!B9+'Hist LJ02'!B9+'Hist LJ03'!B9+'Hist LJ04'!B9+'Hist LJ05'!B9+'Hist LJ06'!B9+'Hist LJ07'!B9+'Hist LJ08'!B9 -> 67206.13 | C9: ='Hist LJ01'!C9+'Hist LJ02'!C9+'Hist LJ03'!C9+'Hist LJ04'!C9+'Hist LJ05'!C9+'Hist LJ06'!C9+'Hist LJ07'!C9+'Hist LJ08'!C9 -> 69283.04 | D9: ='Hist LJ01'!D9+'Hist LJ02'!D9+'Hist LJ03'!D9+'Hist LJ04'!D9+'Hist LJ05'!D9+'Hist LJ06'!D9+'Hist LJ07'!D9+'Hist LJ08'!D9 -> 79203.15 | E9: ='Hist LJ01'!E9+'Hist LJ02'!E9+'Hist LJ03'!E9+'Hist LJ04'!E9+'Hist LJ05'!E9+'Hist LJ06'!E9+'Hist LJ07'!E9+'Hist LJ08'!E9 -> 63047 | F9: ='Hist LJ01'!F9+'Hist LJ02'!F9+'Hist LJ03'!F9+'Hist LJ04'!F9+'Hist LJ05'!F9+'Hist LJ06'!F9+'Hist LJ07'!F9+'Hist LJ08'!F9 -> 198043.97 | G9: ='Hist LJ01'!G9+'Hist LJ02'!G9+'Hist LJ03'!G9+'Hist LJ04'!G9+'Hist LJ05'!G9+'Hist LJ06'!G9+'Hist LJ07'!G9+'Hist LJ08'!G9 -> 76545.79 | H9: ='Hist LJ01'!H9+'Hist LJ02'!H9+'Hist LJ03'!H9+'Hist LJ04'!H9+'Hist LJ05'!H9+'Hist LJ06'!H9+'Hist LJ07'!H9+'Hist LJ08'!H9 -> 71021.58 | I9: ='Hist LJ01'!I9+'Hist LJ02'!I9+'Hist LJ03'!I9+'Hist LJ04'!I9+'Hist LJ05'!I9+'Hist LJ06'!I9+'Hist LJ07'!I9+'Hist LJ08'!I9 -> 94674.51 | ... N9: ='Hist LJ01'!N9+'Hist LJ02'!N9+'Hist LJ03'!N9+'Hist LJ04'!N9+'Hist LJ05'!N9+'Hist LJ06'!N9+'Hist LJ07'!N9+'Hist LJ08'!N9 -> 1157949.6 | P9: Loja
A10: Frios e Congelados | B10: ='Hist LJ01'!B10+'Hist LJ02'!B10+'Hist LJ03'!B10+'Hist LJ04'!B10+'Hist LJ05'!B10+'Hist LJ06'!B10+'Hist LJ07'!B10+'Hist LJ08'!B10 -> 1654501.6 | C10: ='Hist LJ01'!C10+'Hist LJ02'!C10+'Hist LJ03'!C10+'Hist LJ04'!C10+'Hist LJ05'!C10+'Hist LJ06'!C10+'Hist LJ07'!C10+'Hist LJ08'!C10 -> 1553666.2 | D10: ='Hist LJ01'!D10+'Hist LJ02'!D10+'Hist LJ03'!D10+'Hist LJ04'!D10+'Hist LJ05'!D10+'Hist LJ06'!D10+'Hist LJ07'!D10+'Hist LJ08'!D10 -> 1774187.4 | E10: ='Hist LJ01'!E10+'Hist LJ02'!E10+'Hist LJ03'!E10+'Hist LJ04'!E10+'Hist LJ05'!E10+'Hist LJ06'!E10+'Hist LJ07'!E10+'Hist LJ08'!E10 -> 1684496.9 | F10: ='Hist LJ01'!F10+'Hist LJ02'!F10+'Hist LJ03'!F10+'Hist LJ04'!F10+'Hist LJ05'!F10+'Hist LJ06'!F10+'Hist LJ07'!F10+'Hist LJ08'!F10 -> 1866023.9 | G10: ='Hist LJ01'!G10+'Hist LJ02'!G10+'Hist LJ03'!G10+'Hist LJ04'!G10+'Hist LJ05'!G10+'Hist LJ06'!G10+'Hist LJ07'!G10+'Hist LJ08'!G10 -> 1815499.5 | H10: ='Hist LJ01'!H10+'Hist LJ02'!H10+'Hist LJ03'!H10+'Hist LJ04'!H10+'Hist LJ05'!H10+'Hist LJ06'!H10+'Hist LJ07'!H10+'Hist LJ08'!H10 -> 1819001.5 | I10: ='Hist LJ01'!I10+'Hist LJ02'!I10+'Hist LJ03'!I10+'Hist LJ04'!I10+'Hist LJ05'!I10+'Hist LJ06'!I10+'Hist LJ07'!I10+'Hist LJ08'!I10 -> 1742932 | ... N10: ='Hist LJ01'!N10+'Hist LJ02'!N10+'Hist LJ03'!N10+'Hist LJ04'!N10+'Hist LJ05'!N10+'Hist LJ06'!N10+'Hist LJ07'!N10+'Hist LJ08'!N10 -> 20930116 | P10: Frios
A11: Higiene e Perfumaria | B11: ='Hist LJ01'!B11+'Hist LJ02'!B11+'Hist LJ03'!B11+'Hist LJ04'!B11+'Hist LJ05'!B11+'Hist LJ06'!B11+'Hist LJ07'!B11+'Hist LJ08'!B11 -> 1272667.8 | C11: ='Hist LJ01'!C11+'Hist LJ02'!C11+'Hist LJ03'!C11+'Hist LJ04'!C11+'Hist LJ05'!C11+'Hist LJ06'!C11+'Hist LJ07'!C11+'Hist LJ08'!C11 -> 1256568.7 | D11: ='Hist LJ01'!D11+'Hist LJ02'!D11+'Hist LJ03'!D11+'Hist LJ04'!D11+'Hist LJ05'!D11+'Hist LJ06'!D11+'Hist LJ07'!D11+'Hist LJ08'!D11 -> 1338297.8 | E11: ='Hist LJ01'!E11+'Hist LJ02'!E11+'Hist LJ03'!E11+'Hist LJ04'!E11+'Hist LJ05'!E11+'Hist LJ06'!E11+'Hist LJ07'!E11+'Hist LJ08'!E11 -> 1296936 | F11: ='Hist LJ01'!F11+'Hist LJ02'!F11+'Hist LJ03'!F11+'Hist LJ04'!F11+'Hist LJ05'!F11+'Hist LJ06'!F11+'Hist LJ07'!F11+'Hist LJ08'!F11 -> 1341228.2 | G11: ='Hist LJ01'!G11+'Hist LJ02'!G11+'Hist LJ03'!G11+'Hist LJ04'!G11+'Hist LJ05'!G11+'Hist LJ06'!G11+'Hist LJ07'!G11+'Hist LJ08'!G11 -> 1269010.7 | H11: ='Hist LJ01'!H11+'Hist LJ02'!H11+'Hist LJ03'!H11+'Hist LJ04'!H11+'Hist LJ05'!H11+'Hist LJ06'!H11+'Hist LJ07'!H11+'Hist LJ08'!H11 -> 1318190.2 | I11: ='Hist LJ01'!I11+'Hist LJ02'!I11+'Hist LJ03'!I11+'Hist LJ04'!I11+'Hist LJ05'!I11+'Hist LJ06'!I11+'Hist LJ07'!I11+'Hist LJ08'!I11 -> 1343635.7 | ... N11: ='Hist LJ01'!N11+'Hist LJ02'!N11+'Hist LJ03'!N11+'Hist LJ04'!N11+'Hist LJ05'!N11+'Hist LJ06'!N11+'Hist LJ07'!N11+'Hist LJ08'!N11 -> 15804299 | P11: Loja
A12: Hortifruti | B12: ='Hist LJ01'!B12+'Hist LJ02'!B12+'Hist LJ03'!B12+'Hist LJ04'!B12+'Hist LJ05'!B12+'Hist LJ06'!B12+'Hist LJ07'!B12+'Hist LJ08'!B12 -> 3544291.4 | C12: ='Hist LJ01'!C12+'Hist LJ02'!C12+'Hist LJ03'!C12+'Hist LJ04'!C12+'Hist LJ05'!C12+'Hist LJ06'!C12+'Hist LJ07'!C12+'Hist LJ08'!C12 -> 3399574.3 | D12: ='Hist LJ01'!D12+'Hist LJ02'!D12+'Hist LJ03'!D12+'Hist LJ04'!D12+'Hist LJ05'!D12+'Hist LJ06'!D12+'Hist LJ07'!D12+'Hist LJ08'!D12 -> 3799733.4 | E12: ='Hist LJ01'!E12+'Hist LJ02'!E12+'Hist LJ03'!E12+'Hist LJ04'!E12+'Hist LJ05'!E12+'Hist LJ06'!E12+'Hist LJ07'!E12+'Hist LJ08'!E12 -> 3792948.2 | F12: ='Hist LJ01'!F12+'Hist LJ02'!F12+'Hist LJ03'!F12+'Hist LJ04'!F12+'Hist LJ05'!F12+'Hist LJ06'!F12+'Hist LJ07'!F12+'Hist LJ08'!F12 -> 3559615.7 | G12: ='Hist LJ01'!G12+'Hist LJ02'!G12+'Hist LJ03'!G12+'Hist LJ04'!G12+'Hist LJ05'!G12+'Hist LJ06'!G12+'Hist LJ07'!G12+'Hist LJ08'!G12 -> 3241336.7 | H12: ='Hist LJ01'!H12+'Hist LJ02'!H12+'Hist LJ03'!H12+'Hist LJ04'!H12+'Hist LJ05'!H12+'Hist LJ06'!H12+'Hist LJ07'!H12+'Hist LJ08'!H12 -> 3755247.5 | I12: ='Hist LJ01'!I12+'Hist LJ02'!I12+'Hist LJ03'!I12+'Hist LJ04'!I12+'Hist LJ05'!I12+'Hist LJ06'!I12+'Hist LJ07'!I12+'Hist LJ08'!I12 -> 3812107.5 | ... N12: ='Hist LJ01'!N12+'Hist LJ02'!N12+'Hist LJ03'!N12+'Hist LJ04'!N12+'Hist LJ05'!N12+'Hist LJ06'!N12+'Hist LJ07'!N12+'Hist LJ08'!N12 -> 44203373 | P12: Hortifruti
A13: Laticinios | B13: ='Hist LJ01'!B13+'Hist LJ02'!B13+'Hist LJ03'!B13+'Hist LJ04'!B13+'Hist LJ05'!B13+'Hist LJ06'!B13+'Hist LJ07'!B13+'Hist LJ08'!B13 -> 1452847.3 | C13: ='Hist LJ01'!C13+'Hist LJ02'!C13+'Hist LJ03'!C13+'Hist LJ04'!C13+'Hist LJ05'!C13+'Hist LJ06'!C13+'Hist LJ07'!C13+'Hist LJ08'!C13 -> 1348136.4 | D13: ='Hist LJ01'!D13+'Hist LJ02'!D13+'Hist LJ03'!D13+'Hist LJ04'!D13+'Hist LJ05'!D13+'Hist LJ06'!D13+'Hist LJ07'!D13+'Hist LJ08'!D13 -> 1542530.3 | E13: ='Hist LJ01'!E13+'Hist LJ02'!E13+'Hist LJ03'!E13+'Hist LJ04'!E13+'Hist LJ05'!E13+'Hist LJ06'!E13+'Hist LJ07'!E13+'Hist LJ08'!E13 -> 1412677.3 | F13: ='Hist LJ01'!F13+'Hist LJ02'!F13+'Hist LJ03'!F13+'Hist LJ04'!F13+'Hist LJ05'!F13+'Hist LJ06'!F13+'Hist LJ07'!F13+'Hist LJ08'!F13 -> 1435565.3 | G13: ='Hist LJ01'!G13+'Hist LJ02'!G13+'Hist LJ03'!G13+'Hist LJ04'!G13+'Hist LJ05'!G13+'Hist LJ06'!G13+'Hist LJ07'!G13+'Hist LJ08'!G13 -> 1410401.6 | H13: ='Hist LJ01'!H13+'Hist LJ02'!H13+'Hist LJ03'!H13+'Hist LJ04'!H13+'Hist LJ05'!H13+'Hist LJ06'!H13+'Hist LJ07'!H13+'Hist LJ08'!H13 -> 1492264 | I13: ='Hist LJ01'!I13+'Hist LJ02'!I13+'Hist LJ03'!I13+'Hist LJ04'!I13+'Hist LJ05'!I13+'Hist LJ06'!I13+'Hist LJ07'!I13+'Hist LJ08'!I13 -> 1511673.2 | ... N13: ='Hist LJ01'!N13+'Hist LJ02'!N13+'Hist LJ03'!N13+'Hist LJ04'!N13+'Hist LJ05'!N13+'Hist LJ06'!N13+'Hist LJ07'!N13+'Hist LJ08'!N13 -> 17875500 | P13: Frios
... A19: Rotisseria | B19: ='Hist LJ01'!B19+'Hist LJ02'!B19+'Hist LJ03'!B19+'Hist LJ04'!B19+'Hist LJ05'!B19+'Hist LJ06'!B19+'Hist LJ07'!B19+'Hist LJ08'!B19 -> 249533.08 | C19: ='Hist LJ01'!C19+'Hist LJ02'!C19+'Hist LJ03'!C19+'Hist LJ04'!C19+'Hist LJ05'!C19+'Hist LJ06'!C19+'Hist LJ07'!C19+'Hist LJ08'!C19 -> 250954.64 | D19: ='Hist LJ01'!D19+'Hist LJ02'!D19+'Hist LJ03'!D19+'Hist LJ04'!D19+'Hist LJ05'!D19+'Hist LJ06'!D19+'Hist LJ07'!D19+'Hist LJ08'!D19 -> 284076.16 | E19: ='Hist LJ01'!E19+'Hist LJ02'!E19+'Hist LJ03'!E19+'Hist LJ04'!E19+'Hist LJ05'!E19+'Hist LJ06'!E19+'Hist LJ07'!E19+'Hist LJ08'!E19 -> 261065.08 | F19: ='Hist LJ01'!F19+'Hist LJ02'!F19+'Hist LJ03'!F19+'Hist LJ04'!F19+'Hist LJ05'!F19+'Hist LJ06'!F19+'Hist LJ07'!F19+'Hist LJ08'!F19 -> 293554.61 | G19: ='Hist LJ01'!G19+'Hist LJ02'!G19+'Hist LJ03'!G19+'Hist LJ04'!G19+'Hist LJ05'!G19+'Hist LJ06'!G19+'Hist LJ07'!G19+'Hist LJ08'!G19 -> 287888.43 | H19: ='Hist LJ01'!H19+'Hist LJ02'!H19+'Hist LJ03'!H19+'Hist LJ04'!H19+'Hist LJ05'!H19+'Hist LJ06'!H19+'Hist LJ07'!H19+'Hist LJ08'!H19 -> 281163.33 | I19: ='Hist LJ01'!I19+'Hist LJ02'!I19+'Hist LJ03'!I19+'Hist LJ04'!I19+'Hist LJ05'!I19+'Hist LJ06'!I19+'Hist LJ07'!I19+'Hist LJ08'!I19 -> 286504.69 | ... N19: ='Hist LJ01'!N19+'Hist LJ02'!N19+'Hist LJ03'!N19+'Hist LJ04'!N19+'Hist LJ05'!N19+'Hist LJ06'!N19+'Hist LJ07'!N19+'Hist LJ08'!N19 -> 3329681.1 | P19: Rotisseria
A20: Total | B20: ='Hist LJ01'!B20+'Hist LJ02'!B20+'Hist LJ03'!B20+'Hist LJ04'!B20+'Hist LJ05'!B20+'Hist LJ06'!B20+'Hist LJ07'!B20+'Hist LJ08'!B20 -> 26463387 | C20: ='Hist LJ01'!C20+'Hist LJ02'!C20+'Hist LJ03'!C20+'Hist LJ04'!C20+'Hist LJ05'!C20+'Hist LJ06'!C20+'Hist LJ07'!C20+'Hist LJ08'!C20 -> 25496698 | D20: ='Hist LJ01'!D20+'Hist LJ02'!D20+'Hist LJ03'!D20+'Hist LJ04'!D20+'Hist LJ05'!D20+'Hist LJ06'!D20+'Hist LJ07'!D20+'Hist LJ08'!D20 -> 28607644 | E20: ='Hist LJ01'!E20+'Hist LJ02'!E20+'Hist LJ03'!E20+'Hist LJ04'!E20+'Hist LJ05'!E20+'Hist LJ06'!E20+'Hist LJ07'!E20+'Hist LJ08'!E20 -> 29096926 | F20: ='Hist LJ01'!F20+'Hist LJ02'!F20+'Hist LJ03'!F20+'Hist LJ04'!F20+'Hist LJ05'!F20+'Hist LJ06'!F20+'Hist LJ07'!F20+'Hist LJ08'!F20 -> 28598246 | G20: ='Hist LJ01'!G20+'Hist LJ02'!G20+'Hist LJ03'!G20+'Hist LJ04'!G20+'Hist LJ05'!G20+'Hist LJ06'!G20+'Hist LJ07'!G20+'Hist LJ08'!G20 -> 27142168 | H20: ='Hist LJ01'!H20+'Hist LJ02'!H20+'Hist LJ03'!H20+'Hist LJ04'!H20+'Hist LJ05'!H20+'Hist LJ06'!H20+'Hist LJ07'!H20+'Hist LJ08'!H20 -> 28623444 | I20: ='Hist LJ01'!I20+'Hist LJ02'!I20+'Hist LJ03'!I20+'Hist LJ04'!I20+'Hist LJ05'!I20+'Hist LJ06'!I20+'Hist LJ07'!I20+'Hist LJ08'!I20 -> 28673916 | ... N20: ='Hist LJ01'!N20+'Hist LJ02'!N20+'Hist LJ03'!N20+'Hist LJ04'!N20+'Hist LJ05'!N20+'Hist LJ06'!N20+'Hist LJ07'!N20+'Hist LJ08'!N20 -> 3.3984706e+08
B21: ='Hist LJ01'!B21+'Hist LJ02'!B21+'Hist LJ03'!B21+'Hist LJ04'!B21+'Hist LJ05'!B21+'Hist LJ06'!B21+'Hist LJ07'!B21+'Hist LJ08'!B21 -> 1608763.3 | C21: ='Hist LJ01'!C21+'Hist LJ02'!C21+'Hist LJ03'!C21+'Hist LJ04'!C21+'Hist LJ05'!C21+'Hist LJ06'!C21+'Hist LJ07'!C21+'Hist LJ08'!C21 -> 1493883.9 | D21: ='Hist LJ01'!D21+'Hist LJ02'!D21+'Hist LJ03'!D21+'Hist LJ04'!D21+'Hist LJ05'!D21+'Hist LJ06'!D21+'Hist LJ07'!D21+'Hist LJ08'!D21 -> 1671739.1 | E21: ='Hist LJ01'!E21+'Hist LJ02'!E21+'Hist LJ03'!E21+'Hist LJ04'!E21+'Hist LJ05'!E21+'Hist LJ06'!E21+'Hist LJ07'!E21+'Hist LJ08'!E21 -> 1652331.4 | F21: ='Hist LJ01'!F21+'Hist LJ02'!F21+'Hist LJ03'!F21+'Hist LJ04'!F21+'Hist LJ05'!F21+'Hist LJ06'!F21+'Hist LJ07'!F21+'Hist LJ08'!F21 -> 1853162.3 | G21: ='Hist LJ01'!G21+'Hist LJ02'!G21+'Hist LJ03'!G21+'Hist LJ04'!G21+'Hist LJ05'!G21+'Hist LJ06'!G21+'Hist LJ07'!G21+'Hist LJ08'!G21 -> 1892702.6 | H21: ='Hist LJ01'!H21+'Hist LJ02'!H21+'Hist LJ03'!H21+'Hist LJ04'!H21+'Hist LJ05'!H21+'Hist LJ06'!H21+'Hist LJ07'!H21+'Hist LJ08'!H21 -> 2004919.4 | I21: ='Hist LJ01'!I21+'Hist LJ02'!I21+'Hist LJ03'!I21+'Hist LJ04'!I21+'Hist LJ05'!I21+'Hist LJ06'!I21+'Hist LJ07'!I21+'Hist LJ08'!I21 -> 2019552 | ... N21: ='Hist LJ01'!N21+'Hist LJ02'!N21+'Hist LJ03'!N21+'Hist LJ04'!N21+'Hist LJ05'!N21+'Hist LJ06'!N21+'Hist LJ07'!N21+'Hist LJ08'!N21 -> 21800258
